Workbook
Name in_Mode: 'Inputs'!$B$6
Name in_Case: 'Inputs'!$B$7
Name in_MultLow: 'Inputs'!$B$8
Name in_MultBase: 'Inputs'!$B$9
Name in_MultHigh: 'Inputs'!$B$10
Name in_StartCash: 'Inputs'!$B$11
Name in_ModelStart: 'Inputs'!$B$12
Name in_PricePouch: 'Inputs'!$B$16
Name in_SubDisc: 'Inputs'!$B$17
Name in_PriceStick: 'Inputs'!$B$18
Name in_PriceStickBox: 'Inputs'!$B$19
Name in_WsPouch: 'Inputs'!$B$20
Name in_WsStick: 'Inputs'!$B$21
Name in_DistDisc: 'Inputs'!$B$22
Name in_FoundDisc: 'Inputs'!$B$23
Name in_ShakerCost: 'Inputs'!$B$24
Name in_CogsStd: 'Inputs'!$B$28
Name in_CogsLean: 'Inputs'!$B$29
Name in_StickCogsStd: 'Inputs'!$B$30
Name in_StickCogsLean: 'Inputs'!$B$31
Name in_ShipOrder: 'Inputs'!$B$32
Name in_FreeShip: 'Inputs'!$B$33
Name in_ShipCharge: 'Inputs'!$B$34
Name in_CardPct: 'Inputs'!$B$35
Name in_CardFixed: 'Inputs'!$B$36
Name in_FreightPouch: 'Inputs'!$B$37
Name in_FreightStick: 'Inputs'!$B$38
Name in_FreightDist: 'Inputs'!$B$39
Name in_SubShare: 'Inputs'!$B$43
Name in_SubChurn: 'Inputs'!$B$44
Name in_Repeat: 'Inputs'!$B$45
Name in_PouchPerOrder: 'Inputs'!$B$46
Name in_StickAttach: 'Inputs'!$B$47
Name in_SticksPerBox: 'Inputs'!$B$48
Name in_CAC: 'Inputs'!$B$49
Name in_WaitSize: 'Inputs'!$B$50
Name in_WaitConv: 'Inputs'!$B$51
Name in_StoreChurn: 'Inputs'!$B$52
Name in_PouchPerStore: 'Inputs'!$B$53
Name in_StickPerStore: 'Inputs'!$B$54
Name in_Net30: 'Inputs'!$B$55
Name in_SampleBudget: 'Inputs'!$B$56
Name in_SampleStart: 'Inputs'!$B$57
Name in_RunLean: 'Inputs'!$B$61
Name in_RunStd: 'Inputs'!$B$62
Name in_StickRunLean: 'Inputs'!$B$63
Name in_StickRunStd: 'Inputs'!$B$64
Name in_Cover: 'Inputs'!$B$65
Name in_Lead: 'Inputs'!$B$66
Name in_PODate: 'Inputs'!$B$67
Name in_Deposit: 'Inputs'!$B$68
Name in_BalanceDate: 'Inputs'!$B$69
Name in_FirstShip: 'Inputs'!$B$70
Name in_SampleCreditLean: 'Inputs'!$B$71
Name in_SampleCreditStd: 'Inputs'!$B$72
Name in_Flavor2On: 'Inputs'!$B$73
Name in_Flavor2Run: 'Inputs'!$B$74
Name in_HydraOn: 'Inputs'!$B$75
Name in_FxShopify: 'Inputs'!$B$79
Name in_FxShopify_Start: 'Inputs'!$D$79

Sheet README
A1: Picked financial model: how to use it
A2: Version 1.0, built Oct 2026 from STRATEGY.md, TIMELINE.md, EXPANSION.md, OPERATIONS.md and LAUNCH_GUIDE.md. Pre-launch: nothing in this file is an actual sale.
A4: How to use it
A5: 1. Go to Inputs. Yellow cells are the only cells to change. Every input has a source / note saying where the figure came from.
A6: 2. Pick the run-size mode (Lean = 144-unit runs at Pure Private Label, Standard = 1,000-unit runs) and the demand case (Low / Base / High).
A7: 3. Set starting cash to the money you will actually put in, and replace the demand table (section 8) with your own plan.
A8: 4. Read Monthly Cash Flow for the month-by-month view: the summary at the top gives the cash low point, break-even month and cash at Jun / Dec 2027.
A9: 5. Read Scenarios to see all three demand cases, and Lean vs Standard, side by side. Read Unit Economics for contribution per order, CAC payback and LTV.
A10: 6. Save a copy with a new version number before big changes (picked-model-v1.1.xlsx) so there is a trail.
A12: What is an estimate (replace with quotes, in this order)
A13: 1. Pouch cost of goods: $23 standard is STRATEGY.md's estimate; $30 lean is a placeholder (small runs cost more). Only the whey price is sourced. Replace both with manufacturer quotes first: they drive every margin.
A14: 2. Stick pack cost ($1.30), the lean stick run size (1,440 assumes 144 boxes of 10) and stick freight ($0.10).
... A37: No invented sales: every volume is a labelled scenario assumption. No credentials. Brand colours: #F0505E headers, #1E1A17 text, #FFF7EC fills; yellow = input.

Sheet Inputs
A1: Picked: model inputs
A2: Yellow cells are inputs. Change them; every other sheet recalculates. Nothing here is an actual sale: demand rows are scenario assumptions the owner sets.
A4: 1. Model settings
A5: Input | B5: Value | E5: Unit | F5: Source / note
A6: Run-size mode (Lean = 144-unit runs, Standard = 1,000-unit runs) | B6: Lean | E6: list | F6: TOGGLE. Lean follows EXPANSION.md / TIMELINE.md lean path (Pure Private Label 144-unit MOQ). Standard follows LAUNCH_GUIDE.md 1,000-pouch budget.
A7: Demand case shown on Monthly Cash Flow | B7: Base | E7: list | F7: TOGGLE: Low / Base / High. Scales every demand row below by the multiplier for that case.
A8: Demand multiplier: Low case | B8: 0.5 | E8: x | F8: SCENARIO ASSUMPTION. Owner sets.
A9: Demand multiplier: Base case | B9: 1 | E9: x | F9: SCENARIO ASSUMPTION. 1.0 = the demand table exactly as entered.
A10: Demand multiplier: High case | B10: 1.5 | E10: x | F10: SCENARIO ASSUMPTION. Owner sets.
A11: Starting cash on 1 Oct 2026 | B11: 25000 | E11: $ | F11: OWNER INPUT. TIMELINE.md: lean path about $15k-25k through May 2027; standard path about $65k-95k. Set to the cash you will actually put in.
A12: First month of the model | B12: 46296 | E12: date | F12: Structural. Model runs 15 months from here (Oct 2026 to Dec 2027). Use the first day of a month.
A14: 2. Prices
A15: Input | B15: Value | E15: Unit | F15: Source / note
A16: Pouch, 20 servings, one-off price | B16: 54.99 | E16: $/pouch | F16: STRATEGY.md range and price table.
A17: Subscription discount | B17: 0.15 | E17: % | F17: STRATEGY.md: pouch on subscription 15% off ($46.74).
A18: Single stick, suggested retail at a counter | B18: 3.99 | E18: $/stick | F18: STRATEGY.md. This is the store's shelf price; Picked receives the wholesale stick price. Used for the retailer-margin check.
A19: Stick pack box of 10, own website | B19: 34.99 | E19: $/box | F19: STRATEGY.md.
A20: Wholesale price per pouch (direct to store) | B20: 27.5 | E20: $/pouch | F20: STRATEGY.md proposed store terms. A proposal until the owner confirms.
A21: Wholesale price per stick | B21: 2 | E21: $/stick | F21: STRATEGY.md proposed store terms (keystone against $3.99 SRP). A proposal until the owner confirms.
A22: Distributor discount off wholesale | B22: 0.25 | E22: % | F22: STRATEGY.md / LAUNCH_GUIDE.md: about 25% distributor margin. Unit Economics only; distributors are not in the monthly plan.
A23: Founding offer: discount on waitlist first order | B23: 0.2 | E23: % | F23: STRATEGY.md founding offer: 20% off the first pouch plus a free shaker. Applied on top of normal pricing (conservative).
A24: Founding offer: cost of one free shaker | B24: 4 | E24: $/shaker | F24: ESTIMATE, no quote. Replace with the shaker supplier's quote.
A26: 3. Unit costs and fees
A27: Input | B27: Value | E27: Unit | F27: Source / note
A28: Pouch landed cost of goods, Standard run (1,000) | B28: 23 | E28: $/pouch | F28: STRATEGY.md estimate $21-25, plan on $23. Only the whey price is sourced (USDA, about $14/lb). QUOTE PENDING: replace with manufacturer quote.
A29: Pouch landed cost of goods, Lean run (144) | B29: 30 | E29: $/pouch | F29: ESTIMATE, small runs cost more, replace with quote (Pure Private Label 144-unit run). EXPANSION.md: 144 pouches for about $3.5k-5k.
A30: Protein stick pack cost of goods, Standard run | B30: 1.3 | E30: $/stick | F30: LAUNCH_GUIDE.md budget: stick packs at about $1.30. ESTIMATE, quote pending.
A31: Protein stick pack cost of goods, Lean run | B31: 1.3 | E31: $/stick | F31: ESTIMATE: no small-run quote; set equal to standard until quoted. Small runs likely cost more.
A32: Shipping and packing per DTC order | B32: 8 | E32: $/order | F32: STRATEGY.md 'about $8'. OPERATIONS.md: postage $8-13 at the 2 lb rate (less if cubic applies) plus a $0.18-0.28 mailer.
A33: Free shipping on DTC orders? (1 = yes, Picked absorbs; 0 = customer pays) | B33: 1 | E33: 1/0 | F33: ASSUMPTION matching STRATEGY.md's margin table, which deducts the full $8. OPERATIONS.md plans free shipping over $50.
A34: Shipping charged to customer when free shipping is off | B34: 8 | E34: $/order | F34: ASSUMPTION. Only used when the free-shipping input is 0.
A35: Card fee, percent | B35: 0.029 | E35: % | F35: OPERATIONS.md: Shopify Payments on Basic, 2.9% + 30c.
A36: Card fee, fixed per order | B36: 0.3 | E36: $/order | F36: OPERATIONS.md.
A37: Freight to a store, per pouch | B37: 1 | E37: $/pouch | F37: STRATEGY.md: about $1 freight.
A38: Freight to a store, per stick | B38: 0.1 | E38: $/stick | F38: ESTIMATE, no source. Replace with real shipping cost per counter box.
A39: Freight to a distributor, per pouch | B39: 0 | E39: $/pouch | F39: STRATEGY.md distributor row shows none.
A41: 4. Customers, retention and acquisition (scenario assumptions)
A42: Input | B42: Value | E42: Unit | F42: Source / note
A43: Share of new DTC customers who subscribe | B43: 0.25 | E43: % | F43: SCENARIO ASSUMPTION, conservative. Replace with the Shopify subscription share once orders exist.
A44: Monthly churn of subscribers | B44: 0.12 | E44: %/month | F44: SCENARIO ASSUMPTION. Subscribers receive one pouch a month.
A45: Repeat rate: one-off orders followed by another order next month | B45: 0.2 | E45: % | F45: SCENARIO ASSUMPTION. EXPANSION.md gate is 25% reordering within 60 days; default is set below the gate.
A46: Pouches per DTC pouch order | B46: 1 | E46: pouches | F46: ASSUMPTION.
A47: DTC stick-box orders per DTC pouch order | B47: 0.1 | E47: % | F47: SCENARIO ASSUMPTION.
A48: Sticks per box | B48: 10 | E48: sticks | F48: STRATEGY.md.
A49: CAC: paid acquisition cost per first order | B49: 25 | E49: $/customer | F49: ASSUMPTION (owner brief default $25). STRATEGY.md: keep paid cost per first order under about $22 until subscriptions prove out.
A50: Waitlist size when pre-orders open | B50: 300 | E50: people | F50: SCENARIO ASSUMPTION. Replace with actual Klaviyo signups (STRATEGY.md weekly number #1).
A51: Waitlist conversion to a first order | B51: 0.1 | E51: % | F51: SCENARIO ASSUMPTION. Orders are booked in the first ship month (conservative: pre-order cash may arrive earlier).
A52: Monthly churn of store accounts | B52: 0.05 | E52: %/month | F52: SCENARIO ASSUMPTION.
A53: Pouches sold per active store per month | B53: 2 | E53: pouches | F53: SCENARIO ASSUMPTION.
A54: Sticks sold per active store per month | B54: 20 | E54: sticks | F54: SCENARIO ASSUMPTION.
... A57: Sampling budget starts | B57: 46388 | E57: date | F57: LAUNCH_GUIDE.md: sample in person from pre-orders on.
A59: 5. Production runs and inventory
A60: Input | B60: Value | E60: Unit | F60: Source / note
A61: Pouch run size, Lean | B61: 144 | E61: pouches | F61: EXPANSION.md: Pure Private Label minimum 144 units.
A62: Pouch run size, Standard | B62: 1000 | E62: pouches | F62: LAUNCH_GUIDE.md: first run 1,000 pouches.
A63: Protein stick run size, Lean | B63: 1440 | E63: sticks | F63: ASSUMPTION: the 144-unit minimum read as 144 boxes of 10. Confirm with the quote.
A64: Protein stick run size, Standard | B64: 3000 | E64: sticks | F64: LAUNCH_GUIDE.md: 3,000 stick packs.
A65: Reorder point: stock on hand + on order, in months of current demand | B65: 3.5 | E65: months | F65: OPERATIONS.md: reorder at 6 weeks of sales plus the manufacturer's lead time (8-10 weeks), about 3.5 months. Reorders are whole runs.
A66: Reorder lead time (whole months, 1 to 3) | B66: 2 | E66: months | F66: EXPANSION.md: about 8-10 weeks from approved label to finished goods. Reorders are paid in full when placed (conservative; a deposit/balance split would be later).
A67: First run purchase order and deposit | B67: 46374 | E67: date | F67: TIMELINE.md: purchase order and deposit Dec 18, 2026.
A68: Deposit paid with the purchase order | B68: 0.5 | E68: % | F68: ASSUMPTION. Confirm the manufacturer's payment terms.
A69: First run balance paid | B69: 46444 | E69: date | F69: ASSUMPTION: balance due on completion, before first ship.
A70: First Strawberry ships (sales start) | B70: 46447 | E70: date | F70: TIMELINE.md: late Feb to mid Mar 2027. Demand before this month is zero.
A71: Sample fee credited against first order, Lean | B71: 500 | E71: $ | F71: EXPANSION.md: $500 of the $695 Pure Private Label sample fee is credited to the first order.
A72: Sample fee credited against first order, Standard | B72: 0 | E72: $ | F72: No credit assumed for other manufacturers.
... A75: Develop Real Fruit Hydration sticks? (1 = yes) | B75: 1 | E75: 1/0 | F75: TIMELINE.md: launch May 2027. Cost only: hydration revenue is NOT modelled (no price or volume set yet).
A77: 6. Monthly fixed costs
A78: Cost | B78: Per month | D78: Starts | E78: Unit | F78: Source / note
A79: Shopify Basic | B79: 39 | D79: 46307 | E79: $/month | F79: OPERATIONS.md: $39/month ($29 billed yearly). TIMELINE.md: store setup from Oct 12, 2026.
A80: Klaviyo email | B80: 20 | D80: 46388 | E80: $/month | F80: ESTIMATE. OPERATIONS.md: free to 250 profiles, about $100 at 5,000. Assumes a small paid tier once the waitlist passes 250; check Klaviyo's page.
A81: Product liability insurance | B81: 250 | D81: 46328 | E81: $/month | F81: Owner brief $250/month. LAUNCH_GUIDE.md: $1,500-3,000 a year; TIMELINE.md: in force from Nov 2, 2026. QUOTE PENDING.
A82: Other software (SMS credits, apps) | B82: 15 | D82: 46388 | E82: $/month | F82: OPERATIONS.md: Klaviyo SMS from $15. Reviews, Flow, Inbox, Pirate Ship, Wave are free.
A83: Bookkeeping | B83: 200 | D83: 46447 | E83: $/month | F83: OPERATIONS.md: a bookkeeper costs about $200-600/month. Set 0 if you keep Wave yourself.
A84: Amazon Professional plan | B84: 0 | D84: 46539 | E84: $/month | F84: OPERATIONS.md: $39.99/month. Default 0 because Amazon sales are not modelled; enter it when you list.
A86: 7. One-time launch costs (amount used depends on the run-size mode)
A87: Item | B87: Lean | C87: Standard | D87: Paid in | E87: Applies if | F87: Source / note
A88: Company, trademark, lawyer review, insurance setup | B88: 4500 | C88: 7500 | D88: 46304 | E88: always | F88: TIMELINE.md cash by stage: $3k-6k lean, $5k-10k standard (midpoints). Monthly insurance is also in section 6; lower this if the bucket already covers the premium.
A89: Samples and flavour development (Strawberry) | B89: 695 | C89: 4500 | D89: 46318 | E89: always | F89: Lean: EXPANSION.md, $695 at Pure Private Label. Standard: LAUNCH_GUIDE.md $3,000-6,000 (midpoint). TIMELINE.md: samples ordered Oct 23, 2026.
A90: Label and regulatory review | B90: 1500 | C90: 2250 | D90: 46360 | E90: always | F90: LAUNCH_GUIDE.md: $1,500-3,000. TIMELINE.md: label reviewed by Dec 2026. QUOTE PENDING.
A91: Launch kit: shakers, display, sampling supplies, apps | B91: 2000 | C91: 3000 | D91: 46419 | E91: always | F91: LAUNCH_GUIDE.md: $2,000-4,000 (standard path). Lean figure is an ESTIMATE.
A92: Real Fruit Hydration sticks (development and first run) | B92: 4000 | C92: 12500 | D92: 46478 | E92: toggle | F92: TIMELINE.md: $3k-5k lean (144-unit run), $10k-15k standard (7,500 sticks at StickPax); midpoints. Paid the month before the May 2027 launch.
A93: Second protein flavour: samples and development | B93: 695 | C93: 2000 | D93: 46461 | E93: toggle | F93: Lean: EXPANSION.md $695 samples. Standard: ESTIMATE (LAUNCH_GUIDE.md implies about $1.5k-3k per extra flavour). The flavour's first run is an inventory purchase (section 5).
A94: Optional: Picked Creatine via Supliful | B94: 0 | C94: 0 | D94: 46332 | E94: always | F94: TIMELINE.md: $300-1k in fees and samples, optional. Default 0; its revenue is not modelled.
A96: 8. Monthly demand, Base case (SCENARIO ASSUMPTIONS, not forecasts or actual sales)
A97: Month | B97: Organic / waitlist-driven new customers | C97: Paid new customers | D97: New store accounts | F97: Source / note
A98: =DATE(2027,3,1) | B98: 15 | C98: 0 | D98: 2 | F98: Conservative defaults chosen for illustration; the owner replaces them. Organic = sampling, content, referrals. Paid = new customers bought at the CAC above (STRATEGY.md: only once a first order costs < ~$22). Stores = new direct accounts (LAUNCH_GUIDE.md rung 1 gate: 10 reordering). Waitlist conversions are added on top in the first ship month.
A99: =EDATE(A98,1) | B99: 15 | C99: 0 | D99: 2
A100: =EDATE(A99,1) | B100: 20 | C100: 5 | D100: 2
A101: =EDATE(A100,1) | B101: 20 | C101: 5 | D101: 2
A102: =EDATE(A101,1) | B102: 25 | C102: 10 | D102: 1
A103: =EDATE(A102,1) | B103: 25 | C103: 10 | D103: 1
A104: =EDATE(A103,1) | B104: 30 | C104: 10 | D104: 1
A105: =EDATE(A104,1) | B105: 30 | C105: 10 | D105: 1
A106: =EDATE(A105,1) | B106: 35 | C106: 15 | D106: 1
A107: =EDATE(A106,1) | B107: 40 | C107: 15 | D107: 1

Sheet Unit Economics
A1: Picked: unit economics per order
A2: Estimates from the Inputs sheet. Contribution is before marketing and fixed costs.
A4: A. At Standard-run cost of goods (reconciles to STRATEGY.md's table)
A5: Channel | B5: Price received | C5: Goods | D5: Shipping / freight | E5: Card fees | F5: Contribution | G5: Margin | H5: STRATEGY.md says (at $23 goods)
A6: DTC one-off pouch | B6: =in_PricePouch | C6: =in_CogsStd | D6: =in_ShipOrder | E6: =B6*in_CardPct+in_CardFixed | F6: =B6-C6-D6-E6 | G6: =IF(B6=0,0,F6/B6) | H6: about $22
A7: DTC subscription pouch | B7: =in_PricePouch*(1-in_SubDisc) | C7: =in_CogsStd | D7: =in_ShipOrder | E7: =B7*in_CardPct+in_CardFixed | F7: =B7-C7-D7-E7 | G7: =IF(B7=0,0,F7/B7) | H7: about $14
A8: Wholesale direct to store, pouch | B8: =in_WsPouch | C8: =in_CogsStd | D8: =in_FreightPouch | E8: =0 | F8: =B8-C8-D8-E8 | G8: =IF(B8=0,0,F8/B8) | H8: about $3.50
A9: Distributor, pouch (25% off wholesale) | B9: =in_WsPouch*(1-in_DistDisc) | C9: =in_CogsStd | D9: =in_FreightDist | E9: =0 | F9: =B9-C9-D9-E9 | G9: =IF(B9=0,0,F9/B9) | H9: a loss
A10: DTC stick box of 10 | B10: =in_PriceStickBox | C10: =in_StickCogsStd*in_SticksPerBox | D10: =in_ShipOrder | E10: =B10*in_CardPct+in_CardFixed | F10: =B10-C10-D10-E10 | G10: =IF(B10=0,0,F10/B10) | H10: n/a
A11: Wholesale stick (single) | B11: =in_WsStick | C11: =in_StickCogsStd | D11: =in_FreightStick | E11: =0 | F11: =B11-C11-D11-E11 | G11: =IF(B11=0,0,F11/B11) | H11: n/a
A13: B. At the active run-size mode's cost of goods (Inputs toggle)
A14: Channel | B14: Price received | C14: Goods | D14: Shipping / freight | E14: Card fees | F14: Contribution | G14: Margin | H14: STRATEGY.md says (at $23 goods)
A15: DTC one-off pouch | B15: =in_PricePouch | C15: =IF(in_Mode="Lean",in_CogsLean,in_CogsStd) | D15: =in_ShipOrder | E15: =B15*in_CardPct+in_CardFixed | F15: =B15-C15-D15-E15 | G15: =IF(B15=0,0,F15/B15) | H15: about $22
A16: DTC subscription pouch | B16: =in_PricePouch*(1-in_SubDisc) | C16: =IF(in_Mode="Lean",in_CogsLean,in_CogsStd) | D16: =in_ShipOrder | E16: =B16*in_CardPct+in_CardFixed | F16: =B16-C16-D16-E16 | G16: =IF(B16=0,0,F16/B16) | H16: about $14
A17: Wholesale direct to store, pouch | B17: =in_WsPouch | C17: =IF(in_Mode="Lean",in_CogsLean,in_CogsStd) | D17: =in_FreightPouch | E17: =0 | F17: =B17-C17-D17-E17 | G17: =IF(B17=0,0,F17/B17) | H17: about $3.50
A18: Distributor, pouch (25% off wholesale) | B18: =in_WsPouch*(1-in_DistDisc) | C18: =IF(in_Mode="Lean",in_CogsLean,in_CogsStd) | D18: =in_FreightDist | E18: =0 | F18: =B18-C18-D18-E18 | G18: =IF(B18=0,0,F18/B18) | H18: a loss
A19: DTC stick box of 10 | B19: =in_PriceStickBox | C19: =IF(in_Mode="Lean",in_StickCogsLean,in_StickCogsStd)*in_SticksPerBox | D19: =in_ShipOrder | E19: =B19*in_CardPct+in_CardFixed | F19: =B19-C19-D19-E19 | G19: =IF(B19=0,0,F19/B19) | H19: n/a
A20: Wholesale stick (single) | B20: =in_WsStick | C20: =IF(in_Mode="Lean",in_StickCogsLean,in_StickCogsStd) | D20: =in_FreightStick | E20: =0 | F20: =B20-C20-D20-E20 | G20: =IF(B20=0,0,F20/B20) | H20: n/a
A21: Active mode: | B21: =in_Mode
A22: Retailer margin on a single stick at SRP | B22: =(in_PriceStick-in_WsStick)/in_PriceStick | H22: STRATEGY.md: keystone, 50% retailer margin
A23: Pouch goods cost at which distributors break even | B23: =in_WsPouch*(1-in_DistDisc)-in_FreightDist | H23: STRATEGY.md: go to distributors only once goods cost $16 or less
A25: C. CAC payback and lifetime value (contribution, undiscounted, before fixed costs)
A26: Measure | B26: Standard COGS | C26: Active mode | H26: How it is calculated
A27: CAC (paid cost per first order) | B27: =in_CAC | C27: =in_CAC | H27: Inputs
A28: Contribution, DTC one-off order | B28: =F6 | C28: =F15 | H28: Table A / B
A29: Contribution, DTC subscription order | B29: =F7 | C29: =F16 | H29: Table A / B
A30: First one-off order contribution after CAC | B30: =B28-B27 | C30: =C28-C27 | H30: Negative = the first order does not pay for the ad
A31: One-off orders needed to pay back CAC | B31: =IF(B28<=0,"never",B27/B28) | C31: =IF(C28<=0,"never",C27/C28) | H31: CAC / one-off contribution
A32: Subscription months to pay back CAC | B32: =IF(B29<=0,"never",B27/B29) | C32: =IF(C29<=0,"never",C27/C29) | H32: CAC / subscription contribution
A33: Expected orders per one-off customer | B33: =1/(1-in_Repeat) | C33: =1/(1-in_Repeat) | H33: 1 / (1 - repeat rate)
A34: Expected orders (months) per subscriber | B34: =1/in_SubChurn | C34: =1/in_SubChurn | H34: 1 / monthly churn
A35: LTV, one-off customer | B35: =B28*B33 | C35: =C28*C33 | H35: Contribution x expected orders
A36: LTV, subscriber | B36: =B29*B34 | C36: =C29*C34 | H36: Contribution x expected months
A37: Blended LTV per new DTC customer | B37: =in_SubShare*B36+(1-in_SubShare)*B35 | C37: =in_SubShare*C36+(1-in_SubShare)*C35 | H37: Weighted by subscription share
A38: LTV : CAC | B38: =IF(B27=0,"n/a",B37/B27) | C38: =IF(C27=0,"n/a",C37/C27) | H38: Common rule of thumb: aim for 3x or better
A39: Highest CAC that still breaks even over the lifetime | B39: =B37 | C39: =C37 | H39: Equals blended LTV
A40: CAC that keeps a 3:1 LTV : CAC | B40: =B37/3 | C40: =C37/3 | H40: Blended LTV / 3

Sheet Monthly Cash Flow
A1: Picked: monthly cash flow (mode and demand case from Inputs)
A2: Months Oct 2026 to Dec 2027. All figures are projections from the Inputs sheet, not actual results. Cash view: inventory is a cash outflow when bought; COGS appears only in the operating view at the bottom.
A3: Run-size mode | B3: =in_Mode
A4: Demand multiplier | B4: =IF(in_Case="Low",in_MultLow,IF(in_Case="High",in_MultHigh,in_MultBase))
A5: Demand case | B5: =in_Case
A6: Pouch cost of goods (by mode) | B6: =IF($B$3="Lean",in_CogsLean,in_CogsStd)
A7: Stick cost of goods (by mode) | B7: =IF($B$3="Lean",in_StickCogsLean,in_StickCogsStd)
A8: Pouch run size (by mode) | B8: =IF($B$3="Lean",in_RunLean,in_RunStd)
A9: Stick run size (by mode) | B9: =IF($B$3="Lean",in_StickRunLean,in_StickRunStd)
A10: Sample credit on first order (by mode) | B10: =IF($B$3="Lean",in_SampleCreditLean,in_SampleCreditStd)
A12: Summary for this sheet's mode and case
A13: Lowest cash balance | B13: =MIN($C$120:$Q$120)
A14: Month of lowest cash balance | B14: =INDEX($C$23:$Q$23,MATCH(MIN($C$120:$Q$120),$C$120:$Q$120,0))
A15: Peak funding need (lowest cumulative net cash flow) | B15: =MIN(0,MIN($C$119:$Q$119))
A16: Operating break-even month (first month operating profit >= 0) | B16: =IFERROR(INDEX($C$23:$Q$23,MATCH(1,$C$127:$Q$127,0)),"Not by Dec 2027")
A17: Cash payback month (cumulative net cash flow back to >= 0) | B17: =IFERROR(INDEX($C$23:$Q$23,MATCH(1,$C$128:$Q$128,0)),"Not by Dec 2027")
A18: Cash balance, end of Jun 2027 | B18: =IFERROR(INDEX($C$120:$Q$120,MATCH(DATE(2027,6,1),$C$23:$Q$23,0)),"n/a")
A19: Cash balance, end of Dec 2027 | B19: =IFERROR(INDEX($C$120:$Q$120,MATCH(DATE(2027,12,1),$C$23:$Q$23,0)),"n/a")
A20: Stockout check (pouch + stick units short; should be 0) | B20: =SUM($C$54:$Q$54)+SUM($C$65:$Q$65)
A21: Operating profit, Oct 2026 to Dec 2027 (launch costs excluded) | B21: =SUM($C$126:$Q$126)
A23: Line | B23: Note | C23: =DATE(YEAR(in_ModelStart),MONTH(in_ModelStart),1) | D23: =EDATE(C23,1) | E23: =EDATE(D23,1) | F23: =EDATE(E23,1) | G23: =EDATE(F23,1) | H23: =EDATE(G23,1) | I23: =EDATE(H23,1) | J23: =EDATE(I23,1) | K23: =EDATE(J23,1) | ... Q23: =EDATE(P23,1) | R23: Total
A24: Selling? (1 from the first ship month) | C24: =IF(C$23>=DATE(YEAR(in_FirstShip),MONTH(in_FirstShip),1),1,0) | D24: =IF(D$23>=DATE(YEAR(in_FirstShip),MONTH(in_FirstShip),1),1,0) | E24: =IF(E$23>=DATE(YEAR(in_FirstShip),MONTH(in_FirstShip),1),1,0) | F24: =IF(F$23>=DATE(YEAR(in_FirstShip),MONTH(in_FirstShip),1),1,0) | G24: =IF(G$23>=DATE(YEAR(in_FirstShip),MONTH(in_FirstShip),1),1,0) | H24: =IF(H$23>=DATE(YEAR(in_FirstShip),MONTH(in_FirstShip),1),1,0) | I24: =IF(I$23>=DATE(YEAR(in_FirstShip),MONTH(in_FirstShip),1),1,0) | J24: =IF(J$23>=DATE(YEAR(in_FirstShip),MONTH(in_FirstShip),1),1,0) | ... Q24: =IF(Q$23>=DATE(YEAR(in_FirstShip),MONTH(in_FirstShip),1),1,0)
A26: DTC customers and orders
A27: Waitlist first orders (first ship month only) | B27: Waitlist x conversion | C27: =IF(EOMONTH(in_FirstShip,0)=EOMONTH(C$23,0),in_WaitSize*in_WaitConv*$B$4,0) | D27: =IF(EOMONTH(in_FirstShip,0)=EOMONTH(D$23,0),in_WaitSize*in_WaitConv*$B$4,0) | E27: =IF(EOMONTH(in_FirstShip,0)=EOMONTH(E$23,0),in_WaitSize*in_WaitConv*$B$4,0) | F27: =IF(EOMONTH(in_FirstShip,0)=EOMONTH(F$23,0),in_WaitSize*in_WaitConv*$B$4,0) | G27: =IF(EOMONTH(in_FirstShip,0)=EOMONTH(G$23,0),in_WaitSize*in_WaitConv*$B$4,0) | H27: =IF(EOMONTH(in_FirstShip,0)=EOMONTH(H$23,0),in_WaitSize*in_WaitConv*$B$4,0) | I27: =IF(EOMONTH(in_FirstShip,0)=EOMONTH(I$23,0),in_WaitSize*in_WaitConv*$B$4,0) | J27: =IF(EOMONTH(in_FirstShip,0)=EOMONTH(J$23,0),in_WaitSize*in_WaitConv*$B$4,0) | ... Q27: =IF(EOMONTH(in_FirstShip,0)=EOMONTH(Q$23,0),in_WaitSize*in_WaitConv*$B$4,0) | R27: =SUM(C27:Q27)
A28: Organic new customers | C28: =IFERROR(INDEX(Inputs!$B$98:$B$107,MATCH(C$23,Inputs!$A$98:$A$107,0)),0)*$B$4*C24 | D28: =IFERROR(INDEX(Inputs!$B$98:$B$107,MATCH(D$23,Inputs!$A$98:$A$107,0)),0)*$B$4*D24 | E28: =IFERROR(INDEX(Inputs!$B$98:$B$107,MATCH(E$23,Inputs!$A$98:$A$107,0)),0)*$B$4*E24 | F28: =IFERROR(INDEX(Inputs!$B$98:$B$107,MATCH(F$23,Inputs!$A$98:$A$107,0)),0)*$B$4*F24 | G28: =IFERROR(INDEX(Inputs!$B$98:$B$107,MATCH(G$23,Inputs!$A$98:$A$107,0)),0)*$B$4*G24 | H28: =IFERROR(INDEX(Inputs!$B$98:$B$107,MATCH(H$23,Inputs!$A$98:$A$107,0)),0)*$B$4*H24 | I28: =IFERROR(INDEX(Inputs!$B$98:$B$107,MATCH(I$23,Inputs!$A$98:$A$107,0)),0)*$B$4*I24 | J28: =IFERROR(INDEX(Inputs!$B$98:$B$107,MATCH(J$23,Inputs!$A$98:$A$107,0)),0)*$B$4*J24 | ... Q28: =IFERROR(INDEX(Inputs!$B$98:$B$107,MATCH(Q$23,Inputs!$A$98:$A$107,0)),0)*$B$4*Q24 | R28: =SUM(C28:Q28)
A29: Paid new customers | C29: =IFERROR(INDEX(Inputs!$C$98:$C$107,MATCH(C$23,Inputs!$A$98:$A$107,0)),0)*$B$4*C24 | D29: =IFERROR(INDEX(Inputs!$C$98:$C$107,MATCH(D$23,Inputs!$A$98:$A$107,0)),0)*$B$4*D24 | E29: =IFERROR(INDEX(Inputs!$C$98:$C$107,MATCH(E$23,Inputs!$A$98:$A$107,0)),0)*$B$4*E24 | F29: =IFERROR(INDEX(Inputs!$C$98:$C$107,MATCH(F$23,Inputs!$A$98:$A$107,0)),0)*$B$4*F24 | G29: =IFERROR(INDEX(Inputs!$C$98:$C$107,MATCH(G$23,Inputs!$A$98:$A$107,0)),0)*$B$4*G24 | H29: =IFERROR(INDEX(Inputs!$C$98:$C$107,MATCH(H$23,Inputs!$A$98:$A$107,0)),0)*$B$4*H24 | I29: =IFERROR(INDEX(Inputs!$C$98:$C$107,MATCH(I$23,Inputs!$A$98:$A$107,0)),0)*$B$4*I24 | J29: =IFERROR(INDEX(Inputs!$C$98:$C$107,MATCH(J$23,Inputs!$A$98:$A$107,0)),0)*$B$4*J24 | ... Q29: =IFERROR(INDEX(Inputs!$C$98:$C$107,MATCH(Q$23,Inputs!$A$98:$A$107,0)),0)*$B$4*Q24 | R29: =SUM(C29:Q29)
A30: Total new DTC customers | C30: =C27+C28+C29 | D30: =D27+D28+D29 | E30: =E27+E28+E29 | F30: =F27+F28+F29 | G30: =G27+G28+G29 | H30: =H27+H28+H29 | I30: =I27+I28+I29 | J30: =J27+J28+J29 | ... Q30: =Q27+Q28+Q29 | R30: =SUM(C30:Q30)
A31: New subscribers | C31: =C30*in_SubShare | D31: =D30*in_SubShare | E31: =E30*in_SubShare | F31: =F30*in_SubShare | G31: =G30*in_SubShare | H31: =H30*in_SubShare | I31: =I30*in_SubShare | J31: =J30*in_SubShare | ... Q31: =Q30*in_SubShare | R31: =SUM(C31:Q31)
A32: Active subscribers, end of month (= subscription orders) | B32: 1 pouch/month each | C32: =C31 | D32: =C32*(1-in_SubChurn)+D31 | E32: =D32*(1-in_SubChurn)+E31 | F32: =E32*(1-in_SubChurn)+F31 | G32: =F32*(1-in_SubChurn)+G31 | H32: =G32*(1-in_SubChurn)+H31 | I32: =H32*(1-in_SubChurn)+I31 | J32: =I32*(1-in_SubChurn)+J31 | K32: =J32*(1-in_SubChurn)+K31 | ... Q32: =P32*(1-in_SubChurn)+Q31
A33: One-off first orders | C33: =C30*(1-in_SubShare) | D33: =D30*(1-in_SubShare) | E33: =E30*(1-in_SubShare) | F33: =F30*(1-in_SubShare) | G33: =G30*(1-in_SubShare) | H33: =H30*(1-in_SubShare) | I33: =I30*(1-in_SubShare) | J33: =J30*(1-in_SubShare) | ... Q33: =Q30*(1-in_SubShare) | R33: =SUM(C33:Q33)
A34: One-off repeat orders | C34: =0 | D34: =C35*in_Repeat | E34: =D35*in_Repeat | F34: =E35*in_Repeat | G34: =F35*in_Repeat | H34: =G35*in_Repeat | I34: =H35*in_Repeat | J34: =I35*in_Repeat | K34: =J35*in_Repeat | ... Q34: =P35*in_Repeat | R34: =SUM(C34:Q34)
A35: Total one-off pouch orders | C35: =C33+C34 | D35: =D33+D34 | E35: =E33+E34 | F35: =F33+F34 | G35: =G33+G34 | H35: =H33+H34 | I35: =I33+I34 | J35: =J33+J34 | ... Q35: =Q33+Q34 | R35: =SUM(C35:Q35)
A36: Total DTC pouch orders (one-off + subscription) | C36: =C35+C32 | D36: =D35+D32 | E36: =E35+E32 | F36: =F35+F32 | G36: =G35+G32 | H36: =H35+H32 | I36: =I35+I32 | J36: =J35+J32 | ... Q36: =Q35+Q32 | R36: =SUM(C36:Q36)
A37: DTC stick-box orders | C37: =C36*in_StickAttach | D37: =D36*in_StickAttach | E37: =E36*in_StickAttach | F37: =F36*in_StickAttach | G37: =G36*in_StickAttach | H37: =H36*in_StickAttach | I37: =I36*in_StickAttach | J37: =J36*in_StickAttach | ... Q37: =Q36*in_StickAttach | R37: =SUM(C37:Q37)
A39: Wholesale (direct to stores)
A40: New store accounts | C40: =IFERROR(INDEX(Inputs!$D$98:$D$107,MATCH(C$23,Inputs!$A$98:$A$107,0)),0)*$B$4*C24 | D40: =IFERROR(INDEX(Inputs!$D$98:$D$107,MATCH(D$23,Inputs!$A$98:$A$107,0)),0)*$B$4*D24 | E40: =IFERROR(INDEX(Inputs!$D$98:$D$107,MATCH(E$23,Inputs!$A$98:$A$107,0)),0)*$B$4*E24 | F40: =IFERROR(INDEX(Inputs!$D$98:$D$107,MATCH(F$23,Inputs!$A$98:$A$107,0)),0)*$B$4*F24 | G40: =IFERROR(INDEX(Inputs!$D$98:$D$107,MATCH(G$23,Inputs!$A$98:$A$107,0)),0)*$B$4*G24 | H40: =IFERROR(INDEX(Inputs!$D$98:$D$107,MATCH(H$23,Inputs!$A$98:$A$107,0)),0)*$B$4*H24 | I40: =IFERROR(INDEX(Inputs!$D$98:$D$107,MATCH(I$23,Inputs!$A$98:$A$107,0)),0)*$B$4*I24 | J40: =IFERROR(INDEX(Inputs!$D$98:$D$107,MATCH(J$23,Inputs!$A$98:$A$107,0)),0)*$B$4*J24 | ... Q40: =IFERROR(INDEX(Inputs!$D$98:$D$107,MATCH(Q$23,Inputs!$A$98:$A$107,0)),0)*$B$4*Q24 | R40: =SUM(C40:Q40)
A41: Active store accounts, end of month | C41: =C40 | D41: =C41*(1-in_StoreChurn)+D40 | E41: =D41*(1-in_StoreChurn)+E40 | F41: =E41*(1-in_StoreChurn)+F40 | G41: =F41*(1-in_StoreChurn)+G40 | H41: =G41*(1-in_StoreChurn)+H40 | I41: =H41*(1-in_StoreChurn)+I40 | J41: =I41*(1-in_StoreChurn)+J40 | K41: =J41*(1-in_StoreChurn)+K40 | ... Q41: =P41*(1-in_StoreChurn)+Q40
A42: Wholesale pouches shipped | C42: =C41*in_PouchPerStore | D42: =D41*in_PouchPerStore | E42: =E41*in_PouchPerStore | F42: =F41*in_PouchPerStore | G42: =G41*in_PouchPerStore | H42: =H41*in_PouchPerStore | I42: =I41*in_PouchPerStore | J42: =J41*in_PouchPerStore | ... Q42: =Q41*in_PouchPerStore | R42: =SUM(C42:Q42)
A43: Wholesale sticks shipped | C43: =C41*in_StickPerStore | D43: =D41*in_StickPerStore | E43: =E41*in_StickPerStore | F43: =F41*in_StickPerStore | G43: =G41*in_StickPerStore | H43: =H41*in_StickPerStore | I43: =I41*in_StickPerStore | J43: =J41*in_StickPerStore | ... Q43: =Q41*in_StickPerStore | R43: =SUM(C43:Q43)
A45: Pouch inventory (units)
A46: Pouch demand | C46: =C36*in_PouchPerOrder+C42 | D46: =D36*in_PouchPerOrder+D42 | E46: =E36*in_PouchPerOrder+E42 | F46: =F36*in_PouchPerOrder+F42 | G46: =G36*in_PouchPerOrder+G42 | H46: =H36*in_PouchPerOrder+H42 | I46: =I36*in_PouchPerOrder+I42 | J46: =J36*in_PouchPerOrder+J42 | ... Q46: =Q36*in_PouchPerOrder+Q42 | R46: =SUM(C46:Q46)
A47: Opening stock | C47: =0 | D47: =C55 | E47: =D55 | F47: =E55 | G47: =F55 | H47: =G55 | I47: =H55 | J47: =I55 | K47: =J55 | ... Q47: =P55
A48: First run received | C48: =IF(EOMONTH(in_FirstShip,0)=EOMONTH(C$23,0),$B$8,0) | D48: =IF(EOMONTH(in_FirstShip,0)=EOMONTH(D$23,0),$B$8,0) | E48: =IF(EOMONTH(in_FirstShip,0)=EOMONTH(E$23,0),$B$8,0) | F48: =IF(EOMONTH(in_FirstShip,0)=EOMONTH(F$23,0),$B$8,0) | G48: =IF(EOMONTH(in_FirstShip,0)=EOMONTH(G$23,0),$B$8,0) | H48: =IF(EOMONTH(in_FirstShip,0)=EOMONTH(H$23,0),$B$8,0) | I48: =IF(EOMONTH(in_FirstShip,0)=EOMONTH(I$23,0),$B$8,0) | J48: =IF(EOMONTH(in_FirstShip,0)=EOMONTH(J$23,0),$B$8,0) | ... Q48: =IF(EOMONTH(in_FirstShip,0)=EOMONTH(Q$23,0),$B$8,0) | R48: =SUM(C48:Q48)
A49: Second flavour first run received | C49: =IF(AND(in_Flavor2On=1,EOMONTH(in_Flavor2Run,0)=EOMONTH(C$23,0)),$B$8,0) | D49: =IF(AND(in_Flavor2On=1,EOMONTH(in_Flavor2Run,0)=EOMONTH(D$23,0)),$B$8,0) | E49: =IF(AND(in_Flavor2On=1,EOMONTH(in_Flavor2Run,0)=EOMONTH(E$23,0)),$B$8,0) | F49: =IF(AND(in_Flavor2On=1,EOMONTH(in_Flavor2Run,0)=EOMONTH(F$23,0)),$B$8,0) | G49: =IF(AND(in_Flavor2On=1,EOMONTH(in_Flavor2Run,0)=EOMONTH(G$23,0)),$B$8,0) | H49: =IF(AND(in_Flavor2On=1,EOMONTH(in_Flavor2Run,0)=EOMONTH(H$23,0)),$B$8,0) | I49: =IF(AND(in_Flavor2On=1,EOMONTH(in_Flavor2Run,0)=EOMONTH(I$23,0)),$B$8,0) | J49: =IF(AND(in_Flavor2On=1,EOMONTH(in_Flavor2Run,0)=EOMONTH(J$23,0)),$B$8,0) | ... Q49: =IF(AND(in_Flavor2On=1,EOMONTH(in_Flavor2Run,0)=EOMONTH(Q$23,0)),$B$8,0) | R49: =SUM(C49:Q49)
A50: Reorders received (placed lead-time months earlier) | B50: Lead-time input | C50: =IF(in_Lead=1,0,IF(in_Lead=2,0,IF(in_Lead=3,0,0))) | D50: =IF(in_Lead=1,C52,IF(in_Lead=2,0,IF(in_Lead=3,0,0))) | E50: =IF(in_Lead=1,D52,IF(in_Lead=2,C52,IF(in_Lead=3,0,0))) | F50: =IF(in_Lead=1,E52,IF(in_Lead=2,D52,IF(in_Lead=3,C52,0))) | G50: =IF(in_Lead=1,F52,IF(in_Lead=2,E52,IF(in_Lead=3,D52,0))) | H50: =IF(in_Lead=1,G52,IF(in_Lead=2,F52,IF(in_Lead=3,E52,0))) | I50: =IF(in_Lead=1,H52,IF(in_Lead=2,G52,IF(in_Lead=3,F52,0))) | J50: =IF(in_Lead=1,I52,IF(in_Lead=2,H52,IF(in_Lead=3,G52,0))) | K50: =IF(in_Lead=1,J52,IF(in_Lead=2,I52,IF(in_Lead=3,H52,0))) | L50: =IF(in_Lead=1,K52,IF(in_Lead=2,J52,IF(in_Lead=3,I52,0))) | M50: =IF(in_Lead=1,L52,IF(in_Lead=2,K52,IF(in_Lead=3,J52,0))) | ... Q50: =IF(in_Lead=1,P52,IF(in_Lead=2,O52,IF(in_Lead=3,N52,0))) | R50: =SUM(C50:Q50)
A51: On order, still in transit after this month | C51: =IF(in_Lead>=2,0,0)+IF(in_Lead>=3,0,0) | D51: =IF(in_Lead>=2,C52,0)+IF(in_Lead>=3,0,0) | E51: =IF(in_Lead>=2,D52,0)+IF(in_Lead>=3,C52,0) | F51: =IF(in_Lead>=2,E52,0)+IF(in_Lead>=3,D52,0) | G51: =IF(in_Lead>=2,F52,0)+IF(in_Lead>=3,E52,0) | H51: =IF(in_Lead>=2,G52,0)+IF(in_Lead>=3,F52,0) | I51: =IF(in_Lead>=2,H52,0)+IF(in_Lead>=3,G52,0) | J51: =IF(in_Lead>=2,I52,0)+IF(in_Lead>=3,H52,0) | K51: =IF(in_Lead>=2,J52,0)+IF(in_Lead>=3,I52,0) | L51: =IF(in_Lead>=2,K52,0)+IF(in_Lead>=3,J52,0) | ... Q51: =IF(in_Lead>=2,P52,0)+IF(in_Lead>=3,O52,0)
A52: Reorder placed and paid (stock + on order below reorder point) | B52: Paid when placed | C52: =IF(C24=1,IF(C47+C48+C49+C50+C51<C46*in_Cover,ROUNDUP((C46*in_Cover-(C47+C48+C49+C50+C51))/$B$8,0)*$B$8,0),0) | D52: =IF(D24=1,IF(D47+D48+D49+D50+D51<D46*in_Cover,ROUNDUP((D46*in_Cover-(D47+D48+D49+D50+D51))/$B$8,0)*$B$8,0),0) | E52: =IF(E24=1,IF(E47+E48+E49+E50+E51<E46*in_Cover,ROUNDUP((E46*in_Cover-(E47+E48+E49+E50+E51))/$B$8,0)*$B$8,0),0) | F52: =IF(F24=1,IF(F47+F48+F49+F50+F51<F46*in_Cover,ROUNDUP((F46*in_Cover-(F47+F48+F49+F50+F51))/$B$8,0)*$B$8,0),0) | G52: =IF(G24=1,IF(G47+G48+G49+G50+G51<G46*in_Cover,ROUNDUP((G46*in_Cover-(G47+G48+G49+G50+G51))/$B$8,0)*$B$8,0),0) | H52: =IF(H24=1,IF(H47+H48+H49+H50+H51<H46*in_Cover,ROUNDUP((H46*in_Cover-(H47+H48+H49+H50+H51))/$B$8,0)*$B$8,0),0) | I52: =IF(I24=1,IF(I47+I48+I49+I50+I51<I46*in_Cover,ROUNDUP((I46*in_Cover-(I47+I48+I49+I50+I51))/$B$8,0)*$B$8,0),0) | J52: =IF(J24=1,IF(J47+J48+J49+J50+J51<J46*in_Cover,ROUNDUP((J46*in_Cover-(J47+J48+J49+J50+J51))/$B$8,0)*$B$8,0),0) | ... Q52: =IF(Q24=1,IF(Q47+Q48+Q49+Q50+Q51<Q46*in_Cover,ROUNDUP((Q46*in_Cover-(Q47+Q48+Q49+Q50+Q51))/$B$8,0)*$B$8,0),0) | R52: =SUM(C52:Q52)
A53: Pouches sold | C53: =MIN(C46,C47+C48+C49+C50) | D53: =MIN(D46,D47+D48+D49+D50) | E53: =MIN(E46,E47+E48+E49+E50) | F53: =MIN(F46,F47+F48+F49+F50) | G53: =MIN(G46,G47+G48+G49+G50) | H53: =MIN(H46,H47+H48+H49+H50) | I53: =MIN(I46,I47+I48+I49+I50) | J53: =MIN(J46,J47+J48+J49+J50) | ... Q53: =MIN(Q46,Q47+Q48+Q49+Q50) | R53: =SUM(C53:Q53)
A54: Pouch shortfall (check: should be 0) | B54: Must stay 0 | C54: =C46-C53 | D54: =D46-D53 | E54: =E46-E53 | F54: =F46-F53 | G54: =G46-G53 | H54: =H46-H53 | I54: =I46-I53 | J54: =J46-J53 | ... Q54: =Q46-Q53 | R54: =SUM(C54:Q54)
A55: Closing stock | C55: =C47+C48+C49+C50-C53 | D55: =D47+D48+D49+D50-D53 | E55: =E47+E48+E49+E50-E53 | F55: =F47+F48+F49+F50-F53 | G55: =G47+G48+G49+G50-G53 | H55: =H47+H48+H49+H50-H53 | I55: =I47+I48+I49+I50-I53 | J55: =J47+J48+J49+J50-J53 | ... Q55: =Q47+Q48+Q49+Q50-Q53
A57: Protein stick inventory (units)
A58: Stick demand | C58: =C37*in_SticksPerBox+C43 | D58: =D37*in_SticksPerBox+D43 | E58: =E37*in_SticksPerBox+E43 | F58: =F37*in_SticksPerBox+F43 | G58: =G37*in_SticksPerBox+G43 | H58: =H37*in_SticksPerBox+H43 | I58: =I37*in_SticksPerBox+I43 | J58: =J37*in_SticksPerBox+J43 | ... Q58: =Q37*in_SticksPerBox+Q43 | R58: =SUM(C58:Q58)
A59: Opening stock | C59: =0 | D59: =C66 | E59: =D66 | F59: =E66 | G59: =F66 | H59: =G66 | I59: =H66 | J59: =I66 | K59: =J66 | ... Q59: =P66
A60: First run received | C60: =IF(EOMONTH(in_FirstShip,0)=EOMONTH(C$23,0),$B$9,0) | D60: =IF(EOMONTH(in_FirstShip,0)=EOMONTH(D$23,0),$B$9,0) | E60: =IF(EOMONTH(in_FirstShip,0)=EOMONTH(E$23,0),$B$9,0) | F60: =IF(EOMONTH(in_FirstShip,0)=EOMONTH(F$23,0),$B$9,0) | G60: =IF(EOMONTH(in_FirstShip,0)=EOMONTH(G$23,0),$B$9,0) | H60: =IF(EOMONTH(in_FirstShip,0)=EOMONTH(H$23,0),$B$9,0) | I60: =IF(EOMONTH(in_FirstShip,0)=EOMONTH(I$23,0),$B$9,0) | J60: =IF(EOMONTH(in_FirstShip,0)=EOMONTH(J$23,0),$B$9,0) | ... Q60: =IF(EOMONTH(in_FirstShip,0)=EOMONTH(Q$23,0),$B$9,0) | R60: =SUM(C60:Q60)
A61: Reorders received (placed lead-time months earlier) | C61: =IF(in_Lead=1,0,IF(in_Lead=2,0,IF(in_Lead=3,0,0))) | D61: =IF(in_Lead=1,C63,IF(in_Lead=2,0,IF(in_Lead=3,0,0))) | E61: =IF(in_Lead=1,D63,IF(in_Lead=2,C63,IF(in_Lead=3,0,0))) | F61: =IF(in_Lead=1,E63,IF(in_Lead=2,D63,IF(in_Lead=3,C63,0))) | G61: =IF(in_Lead=1,F63,IF(in_Lead=2,E63,IF(in_Lead=3,D63,0))) | H61: =IF(in_Lead=1,G63,IF(in_Lead=2,F63,IF(in_Lead=3,E63,0))) | I61: =IF(in_Lead=1,H63,IF(in_Lead=2,G63,IF(in_Lead=3,F63,0))) | J61: =IF(in_Lead=1,I63,IF(in_Lead=2,H63,IF(in_Lead=3,G63,0))) | K61: =IF(in_Lead=1,J63,IF(in_Lead=2,I63,IF(in_Lead=3,H63,0))) | L61: =IF(in_Lead=1,K63,IF(in_Lead=2,J63,IF(in_Lead=3,I63,0))) | M61: =IF(in_Lead=1,L63,IF(in_Lead=2,K63,IF(in_Lead=3,J63,0))) | ... Q61: =IF(in_Lead=1,P63,IF(in_Lead=2,O63,IF(in_Lead=3,N63,0))) | R61: =SUM(C61:Q61)
A62: On order, still in transit after this month | C62: =IF(in_Lead>=2,0,0)+IF(in_Lead>=3,0,0) | D62: =IF(in_Lead>=2,C63,0)+IF(in_Lead>=3,0,0) | E62: =IF(in_Lead>=2,D63,0)+IF(in_Lead>=3,C63,0) | F62: =IF(in_Lead>=2,E63,0)+IF(in_Lead>=3,D63,0) | G62: =IF(in_Lead>=2,F63,0)+IF(in_Lead>=3,E63,0) | H62: =IF(in_Lead>=2,G63,0)+IF(in_Lead>=3,F63,0) | I62: =IF(in_Lead>=2,H63,0)+IF(in_Lead>=3,G63,0) | J62: =IF(in_Lead>=2,I63,0)+IF(in_Lead>=3,H63,0) | K62: =IF(in_Lead>=2,J63,0)+IF(in_Lead>=3,I63,0) | L62: =IF(in_Lead>=2,K63,0)+IF(in_Lead>=3,J63,0) | ... Q62: =IF(in_Lead>=2,P63,0)+IF(in_Lead>=3,O63,0)
A63: Reorder placed and paid | C63: =IF(C24=1,IF(C59+C60+C61+C62<C58*in_Cover,ROUNDUP((C58*in_Cover-(C59+C60+C61+C62))/$B$9,0)*$B$9,0),0) | D63: =IF(D24=1,IF(D59+D60+D61+D62<D58*in_Cover,ROUNDUP((D58*in_Cover-(D59+D60+D61+D62))/$B$9,0)*$B$9,0),0) | E63: =IF(E24=1,IF(E59+E60+E61+E62<E58*in_Cover,ROUNDUP((E58*in_Cover-(E59+E60+E61+E62))/$B$9,0)*$B$9,0),0) | F63: =IF(F24=1,IF(F59+F60+F61+F62<F58*in_Cover,ROUNDUP((F58*in_Cover-(F59+F60+F61+F62))/$B$9,0)*$B$9,0),0) | G63: =IF(G24=1,IF(G59+G60+G61+G62<G58*in_Cover,ROUNDUP((G58*in_Cover-(G59+G60+G61+G62))/$B$9,0)*$B$9,0),0) | H63: =IF(H24=1,IF(H59+H60+H61+H62<H58*in_Cover,ROUNDUP((H58*in_Cover-(H59+H60+H61+H62))/$B$9,0)*$B$9,0),0) | I63: =IF(I24=1,IF(I59+I60+I61+I62<I58*in_Cover,ROUNDUP((I58*in_Cover-(I59+I60+I61+I62))/$B$9,0)*$B$9,0),0) | J63: =IF(J24=1,IF(J59+J60+J61+J62<J58*in_Cover,ROUNDUP((J58*in_Cover-(J59+J60+J61+J62))/$B$9,0)*$B$9,0),0) | ... Q63: =IF(Q24=1,IF(Q59+Q60+Q61+Q62<Q58*in_Cover,ROUNDUP((Q58*in_Cover-(Q59+Q60+Q61+Q62))/$B$9,0)*$B$9,0),0) | R63: =SUM(C63:Q63)
A64: Sticks sold | C64: =MIN(C58,C59+C60+C61) | D64: =MIN(D58,D59+D60+D61) | E64: =MIN(E58,E59+E60+E61) | F64: =MIN(F58,F59+F60+F61) | G64: =MIN(G58,G59+G60+G61) | H64: =MIN(H58,H59+H60+H61) | I64: =MIN(I58,I59+I60+I61) | J64: =MIN(J58,J59+J60+J61) | ... Q64: =MIN(Q58,Q59+Q60+Q61) | R64: =SUM(C64:Q64)
A65: Stick shortfall (check: should be 0) | B65: Must stay 0 | C65: =C58-C64 | D65: =D58-D64 | E65: =E58-E64 | F65: =F58-F64 | G65: =G58-G64 | H65: =H58-H64 | I65: =I58-I64 | J65: =J58-J64 | ... Q65: =Q58-Q64 | R65: =SUM(C65:Q65)
A66: Closing stock | C66: =C59+C60+C61-C64 | D66: =D59+D60+D61-D64 | E66: =E59+E60+E61-E64 | F66: =F59+F60+F61-F64 | G66: =G59+G60+G61-G64 | H66: =H59+H60+H61-H64 | I66: =I59+I60+I61-I64 | J66: =J59+J60+J61-J64 | ... Q66: =Q59+Q60+Q61-Q64
A68: Cash in
A69: DTC one-off pouches | C69: =C35*in_PricePouch | D69: =D35*in_PricePouch | E69: =E35*in_PricePouch | F69: =F35*in_PricePouch | G69: =G35*in_PricePouch | H69: =H35*in_PricePouch | I69: =I35*in_PricePouch | J69: =J35*in_PricePouch | ... Q69: =Q35*in_PricePouch | R69: =SUM(C69:Q69)
A70: DTC subscription pouches | C70: =C32*in_PricePouch*(1-in_SubDisc) | D70: =D32*in_PricePouch*(1-in_SubDisc) | E70: =E32*in_PricePouch*(1-in_SubDisc) | F70: =F32*in_PricePouch*(1-in_SubDisc) | G70: =G32*in_PricePouch*(1-in_SubDisc) | H70: =H32*in_PricePouch*(1-in_SubDisc) | I70: =I32*in_PricePouch*(1-in_SubDisc) | J70: =J32*in_PricePouch*(1-in_SubDisc) | ... Q70: =Q32*in_PricePouch*(1-in_SubDisc) | R70: =SUM(C70:Q70)
A71: Founding offer discount (waitlist first orders) | C71: =-C27*in_PricePouch*in_FoundDisc | D71: =-D27*in_PricePouch*in_FoundDisc | E71: =-E27*in_PricePouch*in_FoundDisc | F71: =-F27*in_PricePouch*in_FoundDisc | G71: =-G27*in_PricePouch*in_FoundDisc | H71: =-H27*in_PricePouch*in_FoundDisc | I71: =-I27*in_PricePouch*in_FoundDisc | J71: =-J27*in_PricePouch*in_FoundDisc | ... Q71: =-Q27*in_PricePouch*in_FoundDisc | R71: =SUM(C71:Q71)
A72: DTC stick boxes | C72: =C37*in_PriceStickBox | D72: =D37*in_PriceStickBox | E72: =E37*in_PriceStickBox | F72: =F37*in_PriceStickBox | G72: =G37*in_PriceStickBox | H72: =H37*in_PriceStickBox | I72: =I37*in_PriceStickBox | J72: =J37*in_PriceStickBox | ... Q72: =Q37*in_PriceStickBox | R72: =SUM(C72:Q72)
A73: Shipping charged to customers | C73: =IF(in_FreeShip=1,0,(C36+C37)*in_ShipCharge) | D73: =IF(in_FreeShip=1,0,(D36+D37)*in_ShipCharge) | E73: =IF(in_FreeShip=1,0,(E36+E37)*in_ShipCharge) | F73: =IF(in_FreeShip=1,0,(F36+F37)*in_ShipCharge) | G73: =IF(in_FreeShip=1,0,(G36+G37)*in_ShipCharge) | H73: =IF(in_FreeShip=1,0,(H36+H37)*in_ShipCharge) | I73: =IF(in_FreeShip=1,0,(I36+I37)*in_ShipCharge) | J73: =IF(in_FreeShip=1,0,(J36+J37)*in_ShipCharge) | ... Q73: =IF(in_FreeShip=1,0,(Q36+Q37)*in_ShipCharge) | R73: =SUM(C73:Q73)
A74: DTC revenue | C74: =SUM(C69:C73) | D74: =SUM(D69:D73) | E74: =SUM(E69:E73) | F74: =SUM(F69:F73) | G74: =SUM(G69:G73) | H74: =SUM(H69:H73) | I74: =SUM(I69:I73) | J74: =SUM(J69:J73) | ... Q74: =SUM(Q69:Q73) | R74: =SUM(C74:Q74)
A75: Wholesale invoiced (pouches + sticks) | C75: =C42*in_WsPouch+C43*in_WsStick | D75: =D42*in_WsPouch+D43*in_WsStick | E75: =E42*in_WsPouch+E43*in_WsStick | F75: =F42*in_WsPouch+F43*in_WsStick | G75: =G42*in_WsPouch+G43*in_WsStick | H75: =H42*in_WsPouch+H43*in_WsStick | I75: =I42*in_WsPouch+I43*in_WsStick | J75: =J42*in_WsPouch+J43*in_WsStick | ... Q75: =Q42*in_WsPouch+Q43*in_WsStick | R75: =SUM(C75:Q75)
A76: Wholesale cash collected | B76: Net 30 toggle | C76: =IF(in_Net30=1,0,C75) | D76: =IF(in_Net30=1,C75,D75) | E76: =IF(in_Net30=1,D75,E75) | F76: =IF(in_Net30=1,E75,F75) | G76: =IF(in_Net30=1,F75,G75) | H76: =IF(in_Net30=1,G75,H75) | I76: =IF(in_Net30=1,H75,I75) | J76: =IF(in_Net30=1,I75,J75) | K76: =IF(in_Net30=1,J75,K75) | ... Q76: =IF(in_Net30=1,P75,Q75) | R76: =SUM(C76:Q76)
A77: Total cash in | C77: =C74+C76 | D77: =D74+D76 | E77: =E74+E76 | F77: =F74+F76 | G77: =G74+G76 | H77: =H74+H76 | I77: =I74+I76 | J77: =J74+J76 | ... Q77: =Q74+Q76 | R77: =SUM(C77:Q77)
A79: Inventory purchases (cash out)
A80: First pouch run (deposit, then balance; less sample credit) | B80: Mode-dependent | C80: =$B$8*$B$6*(IF(EOMONTH(in_PODate,0)=EOMONTH(C$23,0),in_Deposit,0)+IF(EOMONTH(in_BalanceDate,0)=EOMONTH(C$23,0),1-in_Deposit,0))-IF(EOMONTH(in_PODate,0)=EOMONTH(C$23,0),$B$10,0) | D80: =$B$8*$B$6*(IF(EOMONTH(in_PODate,0)=EOMONTH(D$23,0),in_Deposit,0)+IF(EOMONTH(in_BalanceDate,0)=EOMONTH(D$23,0),1-in_Deposit,0))-IF(EOMONTH(in_PODate,0)=EOMONTH(D$23,0),$B$10,0) | E80: =$B$8*$B$6*(IF(EOMONTH(in_PODate,0)=EOMONTH(E$23,0),in_Deposit,0)+IF(EOMONTH(in_BalanceDate,0)=EOMONTH(E$23,0),1-in_Deposit,0))-IF(EOMONTH(in_PODate,0)=EOMONTH(E$23,0),$B$10,0) | F80: =$B$8*$B$6*(IF(EOMONTH(in_PODate,0)=EOMONTH(F$23,0),in_Deposit,0)+IF(EOMONTH(in_BalanceDate,0)=EOMONTH(F$23,0),1-in_Deposit,0))-IF(EOMONTH(in_PODate,0)=EOMONTH(F$23,0),$B$10,0) | G80: =$B$8*$B$6*(IF(EOMONTH(in_PODate,0)=EOMONTH(G$23,0),in_Deposit,0)+IF(EOMONTH(in_BalanceDate,0)=EOMONTH(G$23,0),1-in_Deposit,0))-IF(EOMONTH(in_PODate,0)=EOMONTH(G$23,0),$B$10,0) | H80: =$B$8*$B$6*(IF(EOMONTH(in_PODate,0)=EOMONTH(H$23,0),in_Deposit,0)+IF(EOMONTH(in_BalanceDate,0)=EOMONTH(H$23,0),1-in_Deposit,0))-IF(EOMONTH(in_PODate,0)=EOMONTH(H$23,0),$B$10,0) | I80: =$B$8*$B$6*(IF(EOMONTH(in_PODate,0)=EOMONTH(I$23,0),in_Deposit,0)+IF(EOMONTH(in_BalanceDate,0)=EOMONTH(I$23,0),1-in_Deposit,0))-IF(EOMONTH(in_PODate,0)=EOMONTH(I$23,0),$B$10,0) | J80: =$B$8*$B$6*(IF(EOMONTH(in_PODate,0)=EOMONTH(J$23,0),in_Deposit,0)+IF(EOMONTH(in_BalanceDate,0)=EOMONTH(J$23,0),1-in_Deposit,0))-IF(EOMONTH(in_PODate,0)=EOMONTH(J$23,0),$B$10,0) | ... Q80: =$B$8*$B$6*(IF(EOMONTH(in_PODate,0)=EOMONTH(Q$23,0),in_Deposit,0)+IF(EOMONTH(in_BalanceDate,0)=EOMONTH(Q$23,0),1-in_Deposit,0))-IF(EOMONTH(in_PODate,0)=EOMONTH(Q$23,0),$B$10,0) | R80: =SUM(C80:Q80)
A81: First protein stick run (deposit, then balance) | C81: =$B$9*$B$7*(IF(EOMONTH(in_PODate,0)=EOMONTH(C$23,0),in_Deposit,0)+IF(EOMONTH(in_BalanceDate,0)=EOMONTH(C$23,0),1-in_Deposit,0)) | D81: =$B$9*$B$7*(IF(EOMONTH(in_PODate,0)=EOMONTH(D$23,0),in_Deposit,0)+IF(EOMONTH(in_BalanceDate,0)=EOMONTH(D$23,0),1-in_Deposit,0)) | E81: =$B$9*$B$7*(IF(EOMONTH(in_PODate,0)=EOMONTH(E$23,0),in_Deposit,0)+IF(EOMONTH(in_BalanceDate,0)=EOMONTH(E$23,0),1-in_Deposit,0)) | F81: =$B$9*$B$7*(IF(EOMONTH(in_PODate,0)=EOMONTH(F$23,0),in_Deposit,0)+IF(EOMONTH(in_BalanceDate,0)=EOMONTH(F$23,0),1-in_Deposit,0)) | G81: =$B$9*$B$7*(IF(EOMONTH(in_PODate,0)=EOMONTH(G$23,0),in_Deposit,0)+IF(EOMONTH(in_BalanceDate,0)=EOMONTH(G$23,0),1-in_Deposit,0)) | H81: =$B$9*$B$7*(IF(EOMONTH(in_PODate,0)=EOMONTH(H$23,0),in_Deposit,0)+IF(EOMONTH(in_BalanceDate,0)=EOMONTH(H$23,0),1-in_Deposit,0)) | I81: =$B$9*$B$7*(IF(EOMONTH(in_PODate,0)=EOMONTH(I$23,0),in_Deposit,0)+IF(EOMONTH(in_BalanceDate,0)=EOMONTH(I$23,0),1-in_Deposit,0)) | J81: =$B$9*$B$7*(IF(EOMONTH(in_PODate,0)=EOMONTH(J$23,0),in_Deposit,0)+IF(EOMONTH(in_BalanceDate,0)=EOMONTH(J$23,0),1-in_Deposit,0)) | ... Q81: =$B$9*$B$7*(IF(EOMONTH(in_PODate,0)=EOMONTH(Q$23,0),in_Deposit,0)+IF(EOMONTH(in_BalanceDate,0)=EOMONTH(Q$23,0),1-in_Deposit,0)) | R81: =SUM(C81:Q81)
A82: Second flavour first run | C82: =C49*$B$6 | D82: =D49*$B$6 | E82: =E49*$B$6 | F82: =F49*$B$6 | G82: =G49*$B$6 | H82: =H49*$B$6 | I82: =I49*$B$6 | J82: =J49*$B$6 | ... Q82: =Q49*$B$6 | R82: =SUM(C82:Q82)
A83: Reorders placed (pouches and sticks, paid in full when placed) | C83: =C52*$B$6+C63*$B$7 | D83: =D52*$B$6+D63*$B$7 | E83: =E52*$B$6+E63*$B$7 | F83: =F52*$B$6+F63*$B$7 | G83: =G52*$B$6+G63*$B$7 | H83: =H52*$B$6+H63*$B$7 | I83: =I52*$B$6+I63*$B$7 | J83: =J52*$B$6+J63*$B$7 | ... Q83: =Q52*$B$6+Q63*$B$7 | R83: =SUM(C83:Q83)
A84: Total inventory purchases | C84: =SUM(C80:C83) | D84: =SUM(D80:D83) | E84: =SUM(E80:E83) | F84: =SUM(F80:F83) | G84: =SUM(G80:G83) | H84: =SUM(H80:H83) | I84: =SUM(I80:I83) | J84: =SUM(J80:J83) | ... Q84: =SUM(Q80:Q83) | R84: =SUM(C84:Q84)
A86: Variable costs (cash out)
A87: DTC shipping and packing | C87: =(C36+C37)*in_ShipOrder | D87: =(D36+D37)*in_ShipOrder | E87: =(E36+E37)*in_ShipOrder | F87: =(F36+F37)*in_ShipOrder | G87: =(G36+G37)*in_ShipOrder | H87: =(H36+H37)*in_ShipOrder | I87: =(I36+I37)*in_ShipOrder | J87: =(J36+J37)*in_ShipOrder | ... Q87: =(Q36+Q37)*in_ShipOrder | R87: =SUM(C87:Q87)
A88: Freight to stores | C88: =C42*in_FreightPouch+C43*in_FreightStick | D88: =D42*in_FreightPouch+D43*in_FreightStick | E88: =E42*in_FreightPouch+E43*in_FreightStick | F88: =F42*in_FreightPouch+F43*in_FreightStick | G88: =G42*in_FreightPouch+G43*in_FreightStick | H88: =H42*in_FreightPouch+H43*in_FreightStick | I88: =I42*in_FreightPouch+I43*in_FreightStick | J88: =J42*in_FreightPouch+J43*in_FreightStick | ... Q88: =Q42*in_FreightPouch+Q43*in_FreightStick | R88: =SUM(C88:Q88)
A89: Card fees | C89: =C74*in_CardPct+(C36+C37)*in_CardFixed | D89: =D74*in_CardPct+(D36+D37)*in_CardFixed | E89: =E74*in_CardPct+(E36+E37)*in_CardFixed | F89: =F74*in_CardPct+(F36+F37)*in_CardFixed | G89: =G74*in_CardPct+(G36+G37)*in_CardFixed | H89: =H74*in_CardPct+(H36+H37)*in_CardFixed | I89: =I74*in_CardPct+(I36+I37)*in_CardFixed | J89: =J74*in_CardPct+(J36+J37)*in_CardFixed | ... Q89: =Q74*in_CardPct+(Q36+Q37)*in_CardFixed | R89: =SUM(C89:Q89)
A90: Founding offer free shakers | C90: =C27*in_ShakerCost | D90: =D27*in_ShakerCost | E90: =E27*in_ShakerCost | F90: =F27*in_ShakerCost | G90: =G27*in_ShakerCost | H90: =H27*in_ShakerCost | I90: =I27*in_ShakerCost | J90: =J27*in_ShakerCost | ... Q90: =Q27*in_ShakerCost | R90: =SUM(C90:Q90)
A91: Total variable costs | C91: =SUM(C87:C90) | D91: =SUM(D87:D90) | E91: =SUM(E87:E90) | F91: =SUM(F87:F90) | G91: =SUM(G87:G90) | H91: =SUM(H87:H90) | I91: =SUM(I87:I90) | J91: =SUM(J87:J90) | ... Q91: =SUM(Q87:Q90) | R91: =SUM(C91:Q91)
A93: Marketing (cash out)
A94: Paid acquisition (paid new customers x CAC) | C94: =C29*in_CAC | D94: =D29*in_CAC | E94: =E29*in_CAC | F94: =F29*in_CAC | G94: =G29*in_CAC | H94: =H29*in_CAC | I94: =I29*in_CAC | J94: =J29*in_CAC | ... Q94: =Q29*in_CAC | R94: =SUM(C94:Q94)
A95: Sampling and content | C95: =IF(C$23>=DATE(YEAR(in_SampleStart),MONTH(in_SampleStart),1),in_SampleBudget,0) | D95: =IF(D$23>=DATE(YEAR(in_SampleStart),MONTH(in_SampleStart),1),in_SampleBudget,0) | E95: =IF(E$23>=DATE(YEAR(in_SampleStart),MONTH(in_SampleStart),1),in_SampleBudget,0) | F95: =IF(F$23>=DATE(YEAR(in_SampleStart),MONTH(in_SampleStart),1),in_SampleBudget,0) | G95: =IF(G$23>=DATE(YEAR(in_SampleStart),MONTH(in_SampleStart),1),in_SampleBudget,0) | H95: =IF(H$23>=DATE(YEAR(in_SampleStart),MONTH(in_SampleStart),1),in_SampleBudget,0) | I95: =IF(I$23>=DATE(YEAR(in_SampleStart),MONTH(in_SampleStart),1),in_SampleBudget,0) | J95: =IF(J$23>=DATE(YEAR(in_SampleStart),MONTH(in_SampleStart),1),in_SampleBudget,0) | ... Q95: =IF(Q$23>=DATE(YEAR(in_SampleStart),MONTH(in_SampleStart),1),in_SampleBudget,0) | R95: =SUM(C95:Q95)
A96: Total marketing | C96: =C94+C95 | D96: =D94+D95 | E96: =E94+E95 | F96: =F94+F95 | G96: =G94+G95 | H96: =H94+H95 | I96: =I94+I95 | J96: =J94+J95 | ... Q96: =Q94+Q95 | R96: =SUM(C96:Q96)
A98: Fixed costs (cash out)
A99: Shopify Basic | C99: =IF(C$23>=DATE(YEAR(in_FxShopify_Start),MONTH(in_FxShopify_Start),1),in_FxShopify,0) | D99: =IF(D$23>=DATE(YEAR(in_FxShopify_Start),MONTH(in_FxShopify_Start),1),in_FxShopify,0) | E99: =IF(E$23>=DATE(YEAR(in_FxShopify_Start),MONTH(in_FxShopify_Start),1),in_FxShopify,0) | F99: =IF(F$23>=DATE(YEAR(in_FxShopify_Start),MONTH(in_FxShopify_Start),1),in_FxShopify,0) | G99: =IF(G$23>=DATE(YEAR(in_FxShopify_Start),MONTH(in_FxShopify_Start),1),in_FxShopify,0) | H99: =IF(H$23>=DATE(YEAR(in_FxShopify_Start),MONTH(in_FxShopify_Start),1),in_FxShopify,0) | I99: =IF(I$23>=DATE(YEAR(in_FxShopify_Start),MONTH(in_FxShopify_Start),1),in_FxShopify,0) | J99: =IF(J$23>=DATE(YEAR(in_FxShopify_Start),MONTH(in_FxShopify_Start),1),in_FxShopify,0) | ... Q99: =IF(Q$23>=DATE(YEAR(in_FxShopify_Start),MONTH(in_FxShopify_Start),1),in_FxShopify,0) | R99: =SUM(C99:Q99)
A100: Klaviyo email | C100: =IF(C$23>=DATE(YEAR(in_FxKlaviyo_Start),MONTH(in_FxKlaviyo_Start),1),in_FxKlaviyo,0) | D100: =IF(D$23>=DATE(YEAR(in_FxKlaviyo_Start),MONTH(in_FxKlaviyo_Start),1),in_FxKlaviyo,0) | E100: =IF(E$23>=DATE(YEAR(in_FxKlaviyo_Start),MONTH(in_FxKlaviyo_Start),1),in_FxKlaviyo,0) | F100: =IF(F$23>=DATE(YEAR(in_FxKlaviyo_Start),MONTH(in_FxKlaviyo_Start),1),in_FxKlaviyo,0) | G100: =IF(G$23>=DATE(YEAR(in_FxKlaviyo_Start),MONTH(in_FxKlaviyo_Start),1),in_FxKlaviyo,0) | H100: =IF(H$23>=DATE(YEAR(in_FxKlaviyo_Start),MONTH(in_FxKlaviyo_Start),1),in_FxKlaviyo,0) | I100: =IF(I$23>=DATE(YEAR(in_FxKlaviyo_Start),MONTH(in_FxKlaviyo_Start),1),in_FxKlaviyo,0) | J100: =IF(J$23>=DATE(YEAR(in_FxKlaviyo_Start),MONTH(in_FxKlaviyo_Start),1),in_FxKlaviyo,0) | ... Q100: =IF(Q$23>=DATE(YEAR(in_FxKlaviyo_Start),MONTH(in_FxKlaviyo_Start),1),in_FxKlaviyo,0) | R100: =SUM(C100:Q100)
A101: Product liability insurance | C101: =IF(C$23>=DATE(YEAR(in_FxInsurance_Start),MONTH(in_FxInsurance_Start),1),in_FxInsurance,0) | D101: =IF(D$23>=DATE(YEAR(in_FxInsurance_Start),MONTH(in_FxInsurance_Start),1),in_FxInsurance,0) | E101: =IF(E$23>=DATE(YEAR(in_FxInsurance_Start),MONTH(in_FxInsurance_Start),1),in_FxInsurance,0) | F101: =IF(F$23>=DATE(YEAR(in_FxInsurance_Start),MONTH(in_FxInsurance_Start),1),in_FxInsurance,0) | G101: =IF(G$23>=DATE(YEAR(in_FxInsurance_Start),MONTH(in_FxInsurance_Start),1),in_FxInsurance,0) | H101: =IF(H$23>=DATE(YEAR(in_FxInsurance_Start),MONTH(in_FxInsurance_Start),1),in_FxInsurance,0) | I101: =IF(I$23>=DATE(YEAR(in_FxInsurance_Start),MONTH(in_FxInsurance_Start),1),in_FxInsurance,0) | J101: =IF(J$23>=DATE(YEAR(in_FxInsurance_Start),MONTH(in_FxInsurance_Start),1),in_FxInsurance,0) | ... Q101: =IF(Q$23>=DATE(YEAR(in_FxInsurance_Start),MONTH(in_FxInsurance_Start),1),in_FxInsurance,0) | R101: =SUM(C101:Q101)
A102: Other software (SMS credits, apps) | C102: =IF(C$23>=DATE(YEAR(in_FxSoftware_Start),MONTH(in_FxSoftware_Start),1),in_FxSoftware,0) | D102: =IF(D$23>=DATE(YEAR(in_FxSoftware_Start),MONTH(in_FxSoftware_Start),1),in_FxSoftware,0) | E102: =IF(E$23>=DATE(YEAR(in_FxSoftware_Start),MONTH(in_FxSoftware_Start),1),in_FxSoftware,0) | F102: =IF(F$23>=DATE(YEAR(in_FxSoftware_Start),MONTH(in_FxSoftware_Start),1),in_FxSoftware,0) | G102: =IF(G$23>=DATE(YEAR(in_FxSoftware_Start),MONTH(in_FxSoftware_Start),1),in_FxSoftware,0) | H102: =IF(H$23>=DATE(YEAR(in_FxSoftware_Start),MONTH(in_FxSoftware_Start),1),in_FxSoftware,0) | I102: =IF(I$23>=DATE(YEAR(in_FxSoftware_Start),MONTH(in_FxSoftware_Start),1),in_FxSoftware,0) | J102: =IF(J$23>=DATE(YEAR(in_FxSoftware_Start),MONTH(in_FxSoftware_Start),1),in_FxSoftware,0) | ... Q102: =IF(Q$23>=DATE(YEAR(in_FxSoftware_Start),MONTH(in_FxSoftware_Start),1),in_FxSoftware,0) | R102: =SUM(C102:Q102)
A103: Bookkeeping | C103: =IF(C$23>=DATE(YEAR(in_FxBooks_Start),MONTH(in_FxBooks_Start),1),in_FxBooks,0) | D103: =IF(D$23>=DATE(YEAR(in_FxBooks_Start),MONTH(in_FxBooks_Start),1),in_FxBooks,0) | E103: =IF(E$23>=DATE(YEAR(in_FxBooks_Start),MONTH(in_FxBooks_Start),1),in_FxBooks,0) | F103: =IF(F$23>=DATE(YEAR(in_FxBooks_Start),MONTH(in_FxBooks_Start),1),in_FxBooks,0) | G103: =IF(G$23>=DATE(YEAR(in_FxBooks_Start),MONTH(in_FxBooks_Start),1),in_FxBooks,0) | H103: =IF(H$23>=DATE(YEAR(in_FxBooks_Start),MONTH(in_FxBooks_Start),1),in_FxBooks,0) | I103: =IF(I$23>=DATE(YEAR(in_FxBooks_Start),MONTH(in_FxBooks_Start),1),in_FxBooks,0) | J103: =IF(J$23>=DATE(YEAR(in_FxBooks_Start),MONTH(in_FxBooks_Start),1),in_FxBooks,0) | ... Q103: =IF(Q$23>=DATE(YEAR(in_FxBooks_Start),MONTH(in_FxBooks_Start),1),in_FxBooks,0) | R103: =SUM(C103:Q103)
A104: Amazon Professional plan | C104: =IF(C$23>=DATE(YEAR(in_FxAmazon_Start),MONTH(in_FxAmazon_Start),1),in_FxAmazon,0) | D104: =IF(D$23>=DATE(YEAR(in_FxAmazon_Start),MONTH(in_FxAmazon_Start),1),in_FxAmazon,0) | E104: =IF(E$23>=DATE(YEAR(in_FxAmazon_Start),MONTH(in_FxAmazon_Start),1),in_FxAmazon,0) | F104: =IF(F$23>=DATE(YEAR(in_FxAmazon_Start),MONTH(in_FxAmazon_Start),1),in_FxAmazon,0) | G104: =IF(G$23>=DATE(YEAR(in_FxAmazon_Start),MONTH(in_FxAmazon_Start),1),in_FxAmazon,0) | H104: =IF(H$23>=DATE(YEAR(in_FxAmazon_Start),MONTH(in_FxAmazon_Start),1),in_FxAmazon,0) | I104: =IF(I$23>=DATE(YEAR(in_FxAmazon_Start),MONTH(in_FxAmazon_Start),1),in_FxAmazon,0) | J104: =IF(J$23>=DATE(YEAR(in_FxAmazon_Start),MONTH(in_FxAmazon_Start),1),in_FxAmazon,0) | ... Q104: =IF(Q$23>=DATE(YEAR(in_FxAmazon_Start),MONTH(in_FxAmazon_Start),1),in_FxAmazon,0) | R104: =SUM(C104:Q104)
A105: Total fixed costs | C105: =SUM(C99:C104) | D105: =SUM(D99:D104) | E105: =SUM(E99:E104) | F105: =SUM(F99:F104) | G105: =SUM(G99:G104) | H105: =SUM(H99:H104) | I105: =SUM(I99:I104) | J105: =SUM(J99:J104) | ... Q105: =SUM(Q99:Q104) | R105: =SUM(C105:Q105)
A107: One-time launch costs (cash out)
A108: Company, trademark, lawyer review, insurance setup | C108: =IF(EOMONTH(in_OtCompany_D,0)=EOMONTH(C$23,0),IF($B$3="Lean",in_OtCompany_L,in_OtCompany_S),0) | D108: =IF(EOMONTH(in_OtCompany_D,0)=EOMONTH(D$23,0),IF($B$3="Lean",in_OtCompany_L,in_OtCompany_S),0) | E108: =IF(EOMONTH(in_OtCompany_D,0)=EOMONTH(E$23,0),IF($B$3="Lean",in_OtCompany_L,in_OtCompany_S),0) | F108: =IF(EOMONTH(in_OtCompany_D,0)=EOMONTH(F$23,0),IF($B$3="Lean",in_OtCompany_L,in_OtCompany_S),0) | G108: =IF(EOMONTH(in_OtCompany_D,0)=EOMONTH(G$23,0),IF($B$3="Lean",in_OtCompany_L,in_OtCompany_S),0) | H108: =IF(EOMONTH(in_OtCompany_D,0)=EOMONTH(H$23,0),IF($B$3="Lean",in_OtCompany_L,in_OtCompany_S),0) | I108: =IF(EOMONTH(in_OtCompany_D,0)=EOMONTH(I$23,0),IF($B$3="Lean",in_OtCompany_L,in_OtCompany_S),0) | J108: =IF(EOMONTH(in_OtCompany_D,0)=EOMONTH(J$23,0),IF($B$3="Lean",in_OtCompany_L,in_OtCompany_S),0) | ... Q108: =IF(EOMONTH(in_OtCompany_D,0)=EOMONTH(Q$23,0),IF($B$3="Lean",in_OtCompany_L,in_OtCompany_S),0) | R108: =SUM(C108:Q108)
A109: Samples and flavour development (Strawberry) | C109: =IF(EOMONTH(in_OtSamples_D,0)=EOMONTH(C$23,0),IF($B$3="Lean",in_OtSamples_L,in_OtSamples_S),0) | D109: =IF(EOMONTH(in_OtSamples_D,0)=EOMONTH(D$23,0),IF($B$3="Lean",in_OtSamples_L,in_OtSamples_S),0) | E109: =IF(EOMONTH(in_OtSamples_D,0)=EOMONTH(E$23,0),IF($B$3="Lean",in_OtSamples_L,in_OtSamples_S),0) | F109: =IF(EOMONTH(in_OtSamples_D,0)=EOMONTH(F$23,0),IF($B$3="Lean",in_OtSamples_L,in_OtSamples_S),0) | G109: =IF(EOMONTH(in_OtSamples_D,0)=EOMONTH(G$23,0),IF($B$3="Lean",in_OtSamples_L,in_OtSamples_S),0) | H109: =IF(EOMONTH(in_OtSamples_D,0)=EOMONTH(H$23,0),IF($B$3="Lean",in_OtSamples_L,in_OtSamples_S),0) | I109: =IF(EOMONTH(in_OtSamples_D,0)=EOMONTH(I$23,0),IF($B$3="Lean",in_OtSamples_L,in_OtSamples_S),0) | J109: =IF(EOMONTH(in_OtSamples_D,0)=EOMONTH(J$23,0),IF($B$3="Lean",in_OtSamples_L,in_OtSamples_S),0) | ... Q109: =IF(EOMONTH(in_OtSamples_D,0)=EOMONTH(Q$23,0),IF($B$3="Lean",in_OtSamples_L,in_OtSamples_S),0) | R109: =SUM(C109:Q109)
A110: Label and regulatory review | C110: =IF(EOMONTH(in_OtLabel_D,0)=EOMONTH(C$23,0),IF($B$3="Lean",in_OtLabel_L,in_OtLabel_S),0) | D110: =IF(EOMONTH(in_OtLabel_D,0)=EOMONTH(D$23,0),IF($B$3="Lean",in_OtLabel_L,in_OtLabel_S),0) | E110: =IF(EOMONTH(in_OtLabel_D,0)=EOMONTH(E$23,0),IF($B$3="Lean",in_OtLabel_L,in_OtLabel_S),0) | F110: =IF(EOMONTH(in_OtLabel_D,0)=EOMONTH(F$23,0),IF($B$3="Lean",in_OtLabel_L,in_OtLabel_S),0) | G110: =IF(EOMONTH(in_OtLabel_D,0)=EOMONTH(G$23,0),IF($B$3="Lean",in_OtLabel_L,in_OtLabel_S),0) | H110: =IF(EOMONTH(in_OtLabel_D,0)=EOMONTH(H$23,0),IF($B$3="Lean",in_OtLabel_L,in_OtLabel_S),0) | I110: =IF(EOMONTH(in_OtLabel_D,0)=EOMONTH(I$23,0),IF($B$3="Lean",in_OtLabel_L,in_OtLabel_S),0) | J110: =IF(EOMONTH(in_OtLabel_D,0)=EOMONTH(J$23,0),IF($B$3="Lean",in_OtLabel_L,in_OtLabel_S),0) | ... Q110: =IF(EOMONTH(in_OtLabel_D,0)=EOMONTH(Q$23,0),IF($B$3="Lean",in_OtLabel_L,in_OtLabel_S),0) | R110: =SUM(C110:Q110)
A111: Launch kit: shakers, display, sampling supplies, apps | C111: =IF(EOMONTH(in_OtKit_D,0)=EOMONTH(C$23,0),IF($B$3="Lean",in_OtKit_L,in_OtKit_S),0) | D111: =IF(EOMONTH(in_OtKit_D,0)=EOMONTH(D$23,0),IF($B$3="Lean",in_OtKit_L,in_OtKit_S),0) | E111: =IF(EOMONTH(in_OtKit_D,0)=EOMONTH(E$23,0),IF($B$3="Lean",in_OtKit_L,in_OtKit_S),0) | F111: =IF(EOMONTH(in_OtKit_D,0)=EOMONTH(F$23,0),IF($B$3="Lean",in_OtKit_L,in_OtKit_S),0) | G111: =IF(EOMONTH(in_OtKit_D,0)=EOMONTH(G$23,0),IF($B$3="Lean",in_OtKit_L,in_OtKit_S),0) | H111: =IF(EOMONTH(in_OtKit_D,0)=EOMONTH(H$23,0),IF($B$3="Lean",in_OtKit_L,in_OtKit_S),0) | I111: =IF(EOMONTH(in_OtKit_D,0)=EOMONTH(I$23,0),IF($B$3="Lean",in_OtKit_L,in_OtKit_S),0) | J111: =IF(EOMONTH(in_OtKit_D,0)=EOMONTH(J$23,0),IF($B$3="Lean",in_OtKit_L,in_OtKit_S),0) | ... Q111: =IF(EOMONTH(in_OtKit_D,0)=EOMONTH(Q$23,0),IF($B$3="Lean",in_OtKit_L,in_OtKit_S),0) | R111: =SUM(C111:Q111)
A112: Real Fruit Hydration sticks (development and first run) | C112: =IF(EOMONTH(in_OtHydra_D,0)=EOMONTH(C$23,0),IF($B$3="Lean",in_OtHydra_L,in_OtHydra_S),0)*in_HydraOn | D112: =IF(EOMONTH(in_OtHydra_D,0)=EOMONTH(D$23,0),IF($B$3="Lean",in_OtHydra_L,in_OtHydra_S),0)*in_HydraOn | E112: =IF(EOMONTH(in_OtHydra_D,0)=EOMONTH(E$23,0),IF($B$3="Lean",in_OtHydra_L,in_OtHydra_S),0)*in_HydraOn | F112: =IF(EOMONTH(in_OtHydra_D,0)=EOMONTH(F$23,0),IF($B$3="Lean",in_OtHydra_L,in_OtHydra_S),0)*in_HydraOn | G112: =IF(EOMONTH(in_OtHydra_D,0)=EOMONTH(G$23,0),IF($B$3="Lean",in_OtHydra_L,in_OtHydra_S),0)*in_HydraOn | H112: =IF(EOMONTH(in_OtHydra_D,0)=EOMONTH(H$23,0),IF($B$3="Lean",in_OtHydra_L,in_OtHydra_S),0)*in_HydraOn | I112: =IF(EOMONTH(in_OtHydra_D,0)=EOMONTH(I$23,0),IF($B$3="Lean",in_OtHydra_L,in_OtHydra_S),0)*in_HydraOn | J112: =IF(EOMONTH(in_OtHydra_D,0)=EOMONTH(J$23,0),IF($B$3="Lean",in_OtHydra_L,in_OtHydra_S),0)*in_HydraOn | ... Q112: =IF(EOMONTH(in_OtHydra_D,0)=EOMONTH(Q$23,0),IF($B$3="Lean",in_OtHydra_L,in_OtHydra_S),0)*in_HydraOn | R112: =SUM(C112:Q112)
...

Sheet Scenarios
A1: Picked: scenarios
A2: Change the run-size toggle and the multipliers on Inputs. Each case runs its own full copy of the monthly model (hidden sheets calc_*), so all cases show at once. Cash balance = starting cash + cumulative net cash flow.
A3: Active run-size mode | B3: =in_Mode
A4: Starting cash | B4: =in_StartCash
A6: A. Demand cases under the active run-size mode
A7: Demand case | B7: Multiplier | C7: Cash balance end Jun 2027 | D7: Cash balance end Dec 2027 | E7: Lowest cash balance | F7: Lowest month | G7: Operating break-even month | H7: Cash payback month
A8: Low | B8: =in_MultLow | C8: =IF(in_Mode="Lean",'calc_Lean_Low'!$B$18,'calc_Standard_Low'!$B$18) | D8: =IF(in_Mode="Lean",'calc_Lean_Low'!$B$19,'calc_Standard_Low'!$B$19) | E8: =IF(in_Mode="Lean",'calc_Lean_Low'!$B$13,'calc_Standard_Low'!$B$13) | F8: =IF(in_Mode="Lean",'calc_Lean_Low'!$B$14,'calc_Standard_Low'!$B$14) | G8: =IF(in_Mode="Lean",'calc_Lean_Low'!$B$16,'calc_Standard_Low'!$B$16) | H8: =IF(in_Mode="Lean",'calc_Lean_Low'!$B$17,'calc_Standard_Low'!$B$17)
A9: Base | B9: =in_MultBase | C9: =IF(in_Mode="Lean",'calc_Lean_Base'!$B$18,'calc_Standard_Base'!$B$18) | D9: =IF(in_Mode="Lean",'calc_Lean_Base'!$B$19,'calc_Standard_Base'!$B$19) | E9: =IF(in_Mode="Lean",'calc_Lean_Base'!$B$13,'calc_Standard_Base'!$B$13) | F9: =IF(in_Mode="Lean",'calc_Lean_Base'!$B$14,'calc_Standard_Base'!$B$14) | G9: =IF(in_Mode="Lean",'calc_Lean_Base'!$B$16,'calc_Standard_Base'!$B$16) | H9: =IF(in_Mode="Lean",'calc_Lean_Base'!$B$17,'calc_Standard_Base'!$B$17)
A10: High | B10: =in_MultHigh | C10: =IF(in_Mode="Lean",'calc_Lean_High'!$B$18,'calc_Standard_High'!$B$18) | D10: =IF(in_Mode="Lean",'calc_Lean_High'!$B$19,'calc_Standard_High'!$B$19) | E10: =IF(in_Mode="Lean",'calc_Lean_High'!$B$13,'calc_Standard_High'!$B$13) | F10: =IF(in_Mode="Lean",'calc_Lean_High'!$B$14,'calc_Standard_High'!$B$14) | G10: =IF(in_Mode="Lean",'calc_Lean_High'!$B$16,'calc_Standard_High'!$B$16) | H10: =IF(in_Mode="Lean",'calc_Lean_High'!$B$17,'calc_Standard_High'!$B$17)
A12: B. Lean (144-unit runs) vs Standard (1,000-unit runs), every demand case
A13: Demand case | B13: Run size | C13: Cash balance end Jun 2027 | D13: Cash balance end Dec 2027 | E13: Lowest cash balance | F13: Lowest month | G13: Operating break-even month | H13: Peak funding need
A14: Low | B14: Lean | C14: ='calc_Lean_Low'!$B$18 | D14: ='calc_Lean_Low'!$B$19 | E14: ='calc_Lean_Low'!$B$13 | F14: ='calc_Lean_Low'!$B$14 | G14: ='calc_Lean_Low'!$B$16 | H14: ='calc_Lean_Low'!$B$15
A15: Low | B15: Standard | C15: ='calc_Standard_Low'!$B$18 | D15: ='calc_Standard_Low'!$B$19 | E15: ='calc_Standard_Low'!$B$13 | F15: ='calc_Standard_Low'!$B$14 | G15: ='calc_Standard_Low'!$B$16 | H15: ='calc_Standard_Low'!$B$15
A16: Base | B16: Lean | C16: ='calc_Lean_Base'!$B$18 | D16: ='calc_Lean_Base'!$B$19 | E16: ='calc_Lean_Base'!$B$13 | F16: ='calc_Lean_Base'!$B$14 | G16: ='calc_Lean_Base'!$B$16 | H16: ='calc_Lean_Base'!$B$15
A17: Base | B17: Standard | C17: ='calc_Standard_Base'!$B$18 | D17: ='calc_Standard_Base'!$B$19 | E17: ='calc_Standard_Base'!$B$13 | F17: ='calc_Standard_Base'!$B$14 | G17: ='calc_Standard_Base'!$B$16 | H17: ='calc_Standard_Base'!$B$15
A18: High | B18: Lean | C18: ='calc_Lean_High'!$B$18 | D18: ='calc_Lean_High'!$B$19 | E18: ='calc_Lean_High'!$B$13 | F18: ='calc_Lean_High'!$B$14 | G18: ='calc_Lean_High'!$B$16 | H18: ='calc_Lean_High'!$B$15
A19: High | B19: Standard | C19: ='calc_Standard_High'!$B$18 | D19: ='calc_Standard_High'!$B$19 | E19: ='calc_Standard_High'!$B$13 | F19: ='calc_Standard_High'!$B$14 | G19: ='calc_Standard_High'!$B$16 | H19: ='calc_Standard_High'!$B$15
A21: Operating break-even = first month operating profit (revenue - COGS on units sold - variable - marketing - fixed) is zero or better; launch costs and inventory build are excluded. Cash payback = first month cumulative net cash flow returns to zero. Peak funding need = the most cash out before money comes back.

Sheet calc_Lean_Low
A1: Calculation copy: Lean runs, Low demand (feeds Scenarios; do not edit)
A2: Months Oct 2026 to Dec 2027. All figures are projections from the Inputs sheet, not actual results. Cash view: inventory is a cash outflow when bought; COGS appears only in the operating view at the bottom.
A3: Run-size mode | B3: ="Lean"
A4: Demand multiplier | B4: =in_MultLow
A5: Demand case | B5: ="Low"
A6: Pouch cost of goods (by mode) | B6: =IF($B$3="Lean",in_CogsLean,in_CogsStd)
A7: Stick cost of goods (by mode) | B7: =IF($B$3="Lean",in_StickCogsLean,in_StickCogsStd)
A8: Pouch run size (by mode) | B8: =IF($B$3="Lean",in_RunLean,in_RunStd)
A9: Stick run size (by mode) | B9: =IF($B$3="Lean",in_StickRunLean,in_StickRunStd)
A10: Sample credit on first order (by mode) | B10: =IF($B$3="Lean",in_SampleCreditLean,in_SampleCreditStd)
A12: Summary for this sheet's mode and case
A13: Lowest cash balance | B13: =MIN($C$120:$Q$120)
A14: Month of lowest cash balance | B14: =INDEX($C$23:$Q$23,MATCH(MIN($C$120:$Q$120),$C$120:$Q$120,0))
A15: Peak funding need (lowest cumulative net cash flow) | B15: =MIN(0,MIN($C$119:$Q$119))
A16: Operating break-even month (first month operating profit >= 0) | B16: =IFERROR(INDEX($C$23:$Q$23,MATCH(1,$C$127:$Q$127,0)),"Not by Dec 2027")
A17: Cash payback month (cumulative net cash flow back to >= 0) | B17: =IFERROR(INDEX($C$23:$Q$23,MATCH(1,$C$128:$Q$128,0)),"Not by Dec 2027")
A18: Cash balance, end of Jun 2027 | B18: =IFERROR(INDEX($C$120:$Q$120,MATCH(DATE(2027,6,1),$C$23:$Q$23,0)),"n/a")
A19: Cash balance, end of Dec 2027 | B19: =IFERROR(INDEX($C$120:$Q$120,MATCH(DATE(2027,12,1),$C$23:$Q$23,0)),"n/a")
A20: Stockout check (pouch + stick units short; should be 0) | B20: =SUM($C$54:$Q$54)+SUM($C$65:$Q$65)
A21: Operating profit, Oct 2026 to Dec 2027 (launch costs excluded) | B21: =SUM($C$126:$Q$126)
A23: Line | B23: Note | C23: =DATE(YEAR(in_ModelStart),MONTH(in_ModelStart),1) | D23: =EDATE(C23,1) | E23: =EDATE(D23,1) | F23: =EDATE(E23,1) | G23: =EDATE(F23,1) | H23: =EDATE(G23,1) | I23: =EDATE(H23,1) | J23: =EDATE(I23,1) | K23: =EDATE(J23,1) | ... Q23: =EDATE(P23,1) | R23: Total
A24: Selling? (1 from the first ship month) | C24: =IF(C$23>=DATE(YEAR(in_FirstShip),MONTH(in_FirstShip),1),1,0) | D24: =IF(D$23>=DATE(YEAR(in_FirstShip),MONTH(in_FirstShip),1),1,0) | E24: =IF(E$23>=DATE(YEAR(in_FirstShip),MONTH(in_FirstShip),1),1,0) | F24: =IF(F$23>=DATE(YEAR(in_FirstShip),MONTH(in_FirstShip),1),1,0) | G24: =IF(G$23>=DATE(YEAR(in_FirstShip),MONTH(in_FirstShip),1),1,0) | H24: =IF(H$23>=DATE(YEAR(in_FirstShip),MONTH(in_FirstShip),1),1,0) | I24: =IF(I$23>=DATE(YEAR(in_FirstShip),MONTH(in_FirstShip),1),1,0) | J24: =IF(J$23>=DATE(YEAR(in_FirstShip),MONTH(in_FirstShip),1),1,0) | ... Q24: =IF(Q$23>=DATE(YEAR(in_FirstShip),MONTH(in_FirstShip),1),1,0)
A26: DTC customers and orders
A27: Waitlist first orders (first ship month only) | B27: Waitlist x conversion | C27: =IF(EOMONTH(in_FirstShip,0)=EOMONTH(C$23,0),in_WaitSize*in_WaitConv*$B$4,0) | D27: =IF(EOMONTH(in_FirstShip,0)=EOMONTH(D$23,0),in_WaitSize*in_WaitConv*$B$4,0) | E27: =IF(EOMONTH(in_FirstShip,0)=EOMONTH(E$23,0),in_WaitSize*in_WaitConv*$B$4,0) | F27: =IF(EOMONTH(in_FirstShip,0)=EOMONTH(F$23,0),in_WaitSize*in_WaitConv*$B$4,0) | G27: =IF(EOMONTH(in_FirstShip,0)=EOMONTH(G$23,0),in_WaitSize*in_WaitConv*$B$4,0) | H27: =IF(EOMONTH(in_FirstShip,0)=EOMONTH(H$23,0),in_WaitSize*in_WaitConv*$B$4,0) | I27: =IF(EOMONTH(in_FirstShip,0)=EOMONTH(I$23,0),in_WaitSize*in_WaitConv*$B$4,0) | J27: =IF(EOMONTH(in_FirstShip,0)=EOMONTH(J$23,0),in_WaitSize*in_WaitConv*$B$4,0) | ... Q27: =IF(EOMONTH(in_FirstShip,0)=EOMONTH(Q$23,0),in_WaitSize*in_WaitConv*$B$4,0) | R27: =SUM(C27:Q27)
A28: Organic new customers | C28: =IFERROR(INDEX(Inputs!$B$98:$B$107,MATCH(C$23,Inputs!$A$98:$A$107,0)),0)*$B$4*C24 | D28: =IFERROR(INDEX(Inputs!$B$98:$B$107,MATCH(D$23,Inputs!$A$98:$A$107,0)),0)*$B$4*D24 | E28: =IFERROR(INDEX(Inputs!$B$98:$B$107,MATCH(E$23,Inputs!$A$98:$A$107,0)),0)*$B$4*E24 | F28: =IFERROR(INDEX(Inputs!$B$98:$B$107,MATCH(F$23,Inputs!$A$98:$A$107,0)),0)*$B$4*F24 | G28: =IFERROR(INDEX(Inputs!$B$98:$B$107,MATCH(G$23,Inputs!$A$98:$A$107,0)),0)*$B$4*G24 | H28: =IFERROR(INDEX(Inputs!$B$98:$B$107,MATCH(H$23,Inputs!$A$98:$A$107,0)),0)*$B$4*H24 | I28: =IFERROR(INDEX(Inputs!$B$98:$B$107,MATCH(I$23,Inputs!$A$98:$A$107,0)),0)*$B$4*I24 | J28: =IFERROR(INDEX(Inputs!$B$98:$B$107,MATCH(J$23,Inputs!$A$98:$A$107,0)),0)*$B$4*J24 | ... Q28: =IFERROR(INDEX(Inputs!$B$98:$B$107,MATCH(Q$23,Inputs!$A$98:$A$107,0)),0)*$B$4*Q24 | R28: =SUM(C28:Q28)
A29: Paid new customers | C29: =IFERROR(INDEX(Inputs!$C$98:$C$107,MATCH(C$23,Inputs!$A$98:$A$107,0)),0)*$B$4*C24 | D29: =IFERROR(INDEX(Inputs!$C$98:$C$107,MATCH(D$23,Inputs!$A$98:$A$107,0)),0)*$B$4*D24 | E29: =IFERROR(INDEX(Inputs!$C$98:$C$107,MATCH(E$23,Inputs!$A$98:$A$107,0)),0)*$B$4*E24 | F29: =IFERROR(INDEX(Inputs!$C$98:$C$107,MATCH(F$23,Inputs!$A$98:$A$107,0)),0)*$B$4*F24 | G29: =IFERROR(INDEX(Inputs!$C$98:$C$107,MATCH(G$23,Inputs!$A$98:$A$107,0)),0)*$B$4*G24 | H29: =IFERROR(INDEX(Inputs!$C$98:$C$107,MATCH(H$23,Inputs!$A$98:$A$107,0)),0)*$B$4*H24 | I29: =IFERROR(INDEX(Inputs!$C$98:$C$107,MATCH(I$23,Inputs!$A$98:$A$107,0)),0)*$B$4*I24 | J29: =IFERROR(INDEX(Inputs!$C$98:$C$107,MATCH(J$23,Inputs!$A$98:$A$107,0)),0)*$B$4*J24 | ... Q29: =IFERROR(INDEX(Inputs!$C$98:$C$107,MATCH(Q$23,Inputs!$A$98:$A$107,0)),0)*$B$4*Q24 | R29: =SUM(C29:Q29)
A30: Total new DTC customers | C30: =C27+C28+C29 | D30: =D27+D28+D29 | E30: =E27+E28+E29 | F30: =F27+F28+F29 | G30: =G27+G28+G29 | H30: =H27+H28+H29 | I30: =I27+I28+I29 | J30: =J27+J28+J29 | ... Q30: =Q27+Q28+Q29 | R30: =SUM(C30:Q30)
A31: New subscribers | C31: =C30*in_SubShare | D31: =D30*in_SubShare | E31: =E30*in_SubShare | F31: =F30*in_SubShare | G31: =G30*in_SubShare | H31: =H30*in_SubShare | I31: =I30*in_SubShare | J31: =J30*in_SubShare | ... Q31: =Q30*in_SubShare | R31: =SUM(C31:Q31)
A32: Active subscribers, end of month (= subscription orders) | B32: 1 pouch/month each | C32: =C31 | D32: =C32*(1-in_SubChurn)+D31 | E32: =D32*(1-in_SubChurn)+E31 | F32: =E32*(1-in_SubChurn)+F31 | G32: =F32*(1-in_SubChurn)+G31 | H32: =G32*(1-in_SubChurn)+H31 | I32: =H32*(1-in_SubChurn)+I31 | J32: =I32*(1-in_SubChurn)+J31 | K32: =J32*(1-in_SubChurn)+K31 | ... Q32: =P32*(1-in_SubChurn)+Q31
A33: One-off first orders | C33: =C30*(1-in_SubShare) | D33: =D30*(1-in_SubShare) | E33: =E30*(1-in_SubShare) | F33: =F30*(1-in_SubShare) | G33: =G30*(1-in_SubShare) | H33: =H30*(1-in_SubShare) | I33: =I30*(1-in_SubShare) | J33: =J30*(1-in_SubShare) | ... Q33: =Q30*(1-in_SubShare) | R33: =SUM(C33:Q33)
A34: One-off repeat orders | C34: =0 | D34: =C35*in_Repeat | E34: =D35*in_Repeat | F34: =E35*in_Repeat | G34: =F35*in_Repeat | H34: =G35*in_Repeat | I34: =H35*in_Repeat | J34: =I35*in_Repeat | K34: =J35*in_Repeat | ... Q34: =P35*in_Repeat | R34: =SUM(C34:Q34)
A35: Total one-off pouch orders | C35: =C33+C34 | D35: =D33+D34 | E35: =E33+E34 | F35: =F33+F34 | G35: =G33+G34 | H35: =H33+H34 | I35: =I33+I34 | J35: =J33+J34 | ... Q35: =Q33+Q34 | R35: =SUM(C35:Q35)
A36: Total DTC pouch orders (one-off + subscription) | C36: =C35+C32 | D36: =D35+D32 | E36: =E35+E32 | F36: =F35+F32 | G36: =G35+G32 | H36: =H35+H32 | I36: =I35+I32 | J36: =J35+J32 | ... Q36: =Q35+Q32 | R36: =SUM(C36:Q36)
A37: DTC stick-box orders | C37: =C36*in_StickAttach | D37: =D36*in_StickAttach | E37: =E36*in_StickAttach | F37: =F36*in_StickAttach | G37: =G36*in_StickAttach | H37: =H36*in_StickAttach | I37: =I36*in_StickAttach | J37: =J36*in_StickAttach | ... Q37: =Q36*in_StickAttach | R37: =SUM(C37:Q37)
A39: Wholesale (direct to stores)
A40: New store accounts | C40: =IFERROR(INDEX(Inputs!$D$98:$D$107,MATCH(C$23,Inputs!$A$98:$A$107,0)),0)*$B$4*C24 | D40: =IFERROR(INDEX(Inputs!$D$98:$D$107,MATCH(D$23,Inputs!$A$98:$A$107,0)),0)*$B$4*D24 | E40: =IFERROR(INDEX(Inputs!$D$98:$D$107,MATCH(E$23,Inputs!$A$98:$A$107,0)),0)*$B$4*E24 | F40: =IFERROR(INDEX(Inputs!$D$98:$D$107,MATCH(F$23,Inputs!$A$98:$A$107,0)),0)*$B$4*F24 | G40: =IFERROR(INDEX(Inputs!$D$98:$D$107,MATCH(G$23,Inputs!$A$98:$A$107,0)),0)*$B$4*G24 | H40: =IFERROR(INDEX(Inputs!$D$98:$D$107,MATCH(H$23,Inputs!$A$98:$A$107,0)),0)*$B$4*H24 | I40: =IFERROR(INDEX(Inputs!$D$98:$D$107,MATCH(I$23,Inputs!$A$98:$A$107,0)),0)*$B$4*I24 | J40: =IFERROR(INDEX(Inputs!$D$98:$D$107,MATCH(J$23,Inputs!$A$98:$A$107,0)),0)*$B$4*J24 | ... Q40: =IFERROR(INDEX(Inputs!$D$98:$D$107,MATCH(Q$23,Inputs!$A$98:$A$107,0)),0)*$B$4*Q24 | R40: =SUM(C40:Q40)
A41: Active store accounts, end of month | C41: =C40 | D41: =C41*(1-in_StoreChurn)+D40 | E41: =D41*(1-in_StoreChurn)+E40 | F41: =E41*(1-in_StoreChurn)+F40 | G41: =F41*(1-in_StoreChurn)+G40 | H41: =G41*(1-in_StoreChurn)+H40 | I41: =H41*(1-in_StoreChurn)+I40 | J41: =I41*(1-in_StoreChurn)+J40 | K41: =J41*(1-in_StoreChurn)+K40 | ... Q41: =P41*(1-in_StoreChurn)+Q40
A42: Wholesale pouches shipped | C42: =C41*in_PouchPerStore | D42: =D41*in_PouchPerStore | E42: =E41*in_PouchPerStore | F42: =F41*in_PouchPerStore | G42: =G41*in_PouchPerStore | H42: =H41*in_PouchPerStore | I42: =I41*in_PouchPerStore | J42: =J41*in_PouchPerStore | ... Q42: =Q41*in_PouchPerStore | R42: =SUM(C42:Q42)
A43: Wholesale sticks shipped | C43: =C41*in_StickPerStore | D43: =D41*in_StickPerStore | E43: =E41*in_StickPerStore | F43: =F41*in_StickPerStore | G43: =G41*in_StickPerStore | H43: =H41*in_StickPerStore | I43: =I41*in_StickPerStore | J43: =J41*in_StickPerStore | ... Q43: =Q41*in_StickPerStore | R43: =SUM(C43:Q43)
A45: Pouch inventory (units)
A46: Pouch demand | C46: =C36*in_PouchPerOrder+C42 | D46: =D36*in_PouchPerOrder+D42 | E46: =E36*in_PouchPerOrder+E42 | F46: =F36*in_PouchPerOrder+F42 | G46: =G36*in_PouchPerOrder+G42 | H46: =H36*in_PouchPerOrder+H42 | I46: =I36*in_PouchPerOrder+I42 | J46: =J36*in_PouchPerOrder+J42 | ... Q46: =Q36*in_PouchPerOrder+Q42 | R46: =SUM(C46:Q46)
A47: Opening stock | C47: =0 | D47: =C55 | E47: =D55 | F47: =E55 | G47: =F55 | H47: =G55 | I47: =H55 | J47: =I55 | K47: =J55 | ... Q47: =P55
A48: First run received | C48: =IF(EOMONTH(in_FirstShip,0)=EOMONTH(C$23,0),$B$8,0) | D48: =IF(EOMONTH(in_FirstShip,0)=EOMONTH(D$23,0),$B$8,0) | E48: =IF(EOMONTH(in_FirstShip,0)=EOMONTH(E$23,0),$B$8,0) | F48: =IF(EOMONTH(in_FirstShip,0)=EOMONTH(F$23,0),$B$8,0) | G48: =IF(EOMONTH(in_FirstShip,0)=EOMONTH(G$23,0),$B$8,0) | H48: =IF(EOMONTH(in_FirstShip,0)=EOMONTH(H$23,0),$B$8,0) | I48: =IF(EOMONTH(in_FirstShip,0)=EOMONTH(I$23,0),$B$8,0) | J48: =IF(EOMONTH(in_FirstShip,0)=EOMONTH(J$23,0),$B$8,0) | ... Q48: =IF(EOMONTH(in_FirstShip,0)=EOMONTH(Q$23,0),$B$8,0) | R48: =SUM(C48:Q48)
A49: Second flavour first run received | C49: =IF(AND(in_Flavor2On=1,EOMONTH(in_Flavor2Run,0)=EOMONTH(C$23,0)),$B$8,0) | D49: =IF(AND(in_Flavor2On=1,EOMONTH(in_Flavor2Run,0)=EOMONTH(D$23,0)),$B$8,0) | E49: =IF(AND(in_Flavor2On=1,EOMONTH(in_Flavor2Run,0)=EOMONTH(E$23,0)),$B$8,0) | F49: =IF(AND(in_Flavor2On=1,EOMONTH(in_Flavor2Run,0)=EOMONTH(F$23,0)),$B$8,0) | G49: =IF(AND(in_Flavor2On=1,EOMONTH(in_Flavor2Run,0)=EOMONTH(G$23,0)),$B$8,0) | H49: =IF(AND(in_Flavor2On=1,EOMONTH(in_Flavor2Run,0)=EOMONTH(H$23,0)),$B$8,0) | I49: =IF(AND(in_Flavor2On=1,EOMONTH(in_Flavor2Run,0)=EOMONTH(I$23,0)),$B$8,0) | J49: =IF(AND(in_Flavor2On=1,EOMONTH(in_Flavor2Run,0)=EOMONTH(J$23,0)),$B$8,0) | ... Q49: =IF(AND(in_Flavor2On=1,EOMONTH(in_Flavor2Run,0)=EOMONTH(Q$23,0)),$B$8,0) | R49: =SUM(C49:Q49)
A50: Reorders received (placed lead-time months earlier) | B50: Lead-time input | C50: =IF(in_Lead=1,0,IF(in_Lead=2,0,IF(in_Lead=3,0,0))) | D50: =IF(in_Lead=1,C52,IF(in_Lead=2,0,IF(in_Lead=3,0,0))) | E50: =IF(in_Lead=1,D52,IF(in_Lead=2,C52,IF(in_Lead=3,0,0))) | F50: =IF(in_Lead=1,E52,IF(in_Lead=2,D52,IF(in_Lead=3,C52,0))) | G50: =IF(in_Lead=1,F52,IF(in_Lead=2,E52,IF(in_Lead=3,D52,0))) | H50: =IF(in_Lead=1,G52,IF(in_Lead=2,F52,IF(in_Lead=3,E52,0))) | I50: =IF(in_Lead=1,H52,IF(in_Lead=2,G52,IF(in_Lead=3,F52,0))) | J50: =IF(in_Lead=1,I52,IF(in_Lead=2,H52,IF(in_Lead=3,G52,0))) | K50: =IF(in_Lead=1,J52,IF(in_Lead=2,I52,IF(in_Lead=3,H52,0))) | L50: =IF(in_Lead=1,K52,IF(in_Lead=2,J52,IF(in_Lead=3,I52,0))) | M50: =IF(in_Lead=1,L52,IF(in_Lead=2,K52,IF(in_Lead=3,J52,0))) | ... Q50: =IF(in_Lead=1,P52,IF(in_Lead=2,O52,IF(in_Lead=3,N52,0))) | R50: =SUM(C50:Q50)
A51: On order, still in transit after this month | C51: =IF(in_Lead>=2,0,0)+IF(in_Lead>=3,0,0) | D51: =IF(in_Lead>=2,C52,0)+IF(in_Lead>=3,0,0) | E51: =IF(in_Lead>=2,D52,0)+IF(in_Lead>=3,C52,0) | F51: =IF(in_Lead>=2,E52,0)+IF(in_Lead>=3,D52,0) | G51: =IF(in_Lead>=2,F52,0)+IF(in_Lead>=3,E52,0) | H51: =IF(in_Lead>=2,G52,0)+IF(in_Lead>=3,F52,0) | I51: =IF(in_Lead>=2,H52,0)+IF(in_Lead>=3,G52,0) | J51: =IF(in_Lead>=2,I52,0)+IF(in_Lead>=3,H52,0) | K51: =IF(in_Lead>=2,J52,0)+IF(in_Lead>=3,I52,0) | L51: =IF(in_Lead>=2,K52,0)+IF(in_Lead>=3,J52,0) | ... Q51: =IF(in_Lead>=2,P52,0)+IF(in_Lead>=3,O52,0)
A52: Reorder placed and paid (stock + on order below reorder point) | B52: Paid when placed | C52: =IF(C24=1,IF(C47+C48+C49+C50+C51<C46*in_Cover,ROUNDUP((C46*in_Cover-(C47+C48+C49+C50+C51))/$B$8,0)*$B$8,0),0) | D52: =IF(D24=1,IF(D47+D48+D49+D50+D51<D46*in_Cover,ROUNDUP((D46*in_Cover-(D47+D48+D49+D50+D51))/$B$8,0)*$B$8,0),0) | E52: =IF(E24=1,IF(E47+E48+E49+E50+E51<E46*in_Cover,ROUNDUP((E46*in_Cover-(E47+E48+E49+E50+E51))/$B$8,0)*$B$8,0),0) | F52: =IF(F24=1,IF(F47+F48+F49+F50+F51<F46*in_Cover,ROUNDUP((F46*in_Cover-(F47+F48+F49+F50+F51))/$B$8,0)*$B$8,0),0) | G52: =IF(G24=1,IF(G47+G48+G49+G50+G51<G46*in_Cover,ROUNDUP((G46*in_Cover-(G47+G48+G49+G50+G51))/$B$8,0)*$B$8,0),0) | H52: =IF(H24=1,IF(H47+H48+H49+H50+H51<H46*in_Cover,ROUNDUP((H46*in_Cover-(H47+H48+H49+H50+H51))/$B$8,0)*$B$8,0),0) | I52: =IF(I24=1,IF(I47+I48+I49+I50+I51<I46*in_Cover,ROUNDUP((I46*in_Cover-(I47+I48+I49+I50+I51))/$B$8,0)*$B$8,0),0) | J52: =IF(J24=1,IF(J47+J48+J49+J50+J51<J46*in_Cover,ROUNDUP((J46*in_Cover-(J47+J48+J49+J50+J51))/$B$8,0)*$B$8,0),0) | ... Q52: =IF(Q24=1,IF(Q47+Q48+Q49+Q50+Q51<Q46*in_Cover,ROUNDUP((Q46*in_Cover-(Q47+Q48+Q49+Q50+Q51))/$B$8,0)*$B$8,0),0) | R52: =SUM(C52:Q52)
A53: Pouches sold | C53: =MIN(C46,C47+C48+C49+C50) | D53: =MIN(D46,D47+D48+D49+D50) | E53: =MIN(E46,E47+E48+E49+E50) | F53: =MIN(F46,F47+F48+F49+F50) | G53: =MIN(G46,G47+G48+G49+G50) | H53: =MIN(H46,H47+H48+H49+H50) | I53: =MIN(I46,I47+I48+I49+I50) | J53: =MIN(J46,J47+J48+J49+J50) | ... Q53: =MIN(Q46,Q47+Q48+Q49+Q50) | R53: =SUM(C53:Q53)
A54: Pouch shortfall (check: should be 0) | B54: Must stay 0 | C54: =C46-C53 | D54: =D46-D53 | E54: =E46-E53 | F54: =F46-F53 | G54: =G46-G53 | H54: =H46-H53 | I54: =I46-I53 | J54: =J46-J53 | ... Q54: =Q46-Q53 | R54: =SUM(C54:Q54)
A55: Closing stock | C55: =C47+C48+C49+C50-C53 | D55: =D47+D48+D49+D50-D53 | E55: =E47+E48+E49+E50-E53 | F55: =F47+F48+F49+F50-F53 | G55: =G47+G48+G49+G50-G53 | H55: =H47+H48+H49+H50-H53 | I55: =I47+I48+I49+I50-I53 | J55: =J47+J48+J49+J50-J53 | ... Q55: =Q47+Q48+Q49+Q50-Q53
A57: Protein stick inventory (units)
A58: Stick demand | C58: =C37*in_SticksPerBox+C43 | D58: =D37*in_SticksPerBox+D43 | E58: =E37*in_SticksPerBox+E43 | F58: =F37*in_SticksPerBox+F43 | G58: =G37*in_SticksPerBox+G43 | H58: =H37*in_SticksPerBox+H43 | I58: =I37*in_SticksPerBox+I43 | J58: =J37*in_SticksPerBox+J43 | ... Q58: =Q37*in_SticksPerBox+Q43 | R58: =SUM(C58:Q58)
A59: Opening stock | C59: =0 | D59: =C66 | E59: =D66 | F59: =E66 | G59: =F66 | H59: =G66 | I59: =H66 | J59: =I66 | K59: =J66 | ... Q59: =P66
A60: First run received | C60: =IF(EOMONTH(in_FirstShip,0)=EOMONTH(C$23,0),$B$9,0) | D60: =IF(EOMONTH(in_FirstShip,0)=EOMONTH(D$23,0),$B$9,0) | E60: =IF(EOMONTH(in_FirstShip,0)=EOMONTH(E$23,0),$B$9,0) | F60: =IF(EOMONTH(in_FirstShip,0)=EOMONTH(F$23,0),$B$9,0) | G60: =IF(EOMONTH(in_FirstShip,0)=EOMONTH(G$23,0),$B$9,0) | H60: =IF(EOMONTH(in_FirstShip,0)=EOMONTH(H$23,0),$B$9,0) | I60: =IF(EOMONTH(in_FirstShip,0)=EOMONTH(I$23,0),$B$9,0) | J60: =IF(EOMONTH(in_FirstShip,0)=EOMONTH(J$23,0),$B$9,0) | ... Q60: =IF(EOMONTH(in_FirstShip,0)=EOMONTH(Q$23,0),$B$9,0) | R60: =SUM(C60:Q60)
A61: Reorders received (placed lead-time months earlier) | C61: =IF(in_Lead=1,0,IF(in_Lead=2,0,IF(in_Lead=3,0,0))) | D61: =IF(in_Lead=1,C63,IF(in_Lead=2,0,IF(in_Lead=3,0,0))) | E61: =IF(in_Lead=1,D63,IF(in_Lead=2,C63,IF(in_Lead=3,0,0))) | F61: =IF(in_Lead=1,E63,IF(in_Lead=2,D63,IF(in_Lead=3,C63,0))) | G61: =IF(in_Lead=1,F63,IF(in_Lead=2,E63,IF(in_Lead=3,D63,0))) | H61: =IF(in_Lead=1,G63,IF(in_Lead=2,F63,IF(in_Lead=3,E63,0))) | I61: =IF(in_Lead=1,H63,IF(in_Lead=2,G63,IF(in_Lead=3,F63,0))) | J61: =IF(in_Lead=1,I63,IF(in_Lead=2,H63,IF(in_Lead=3,G63,0))) | K61: =IF(in_Lead=1,J63,IF(in_Lead=2,I63,IF(in_Lead=3,H63,0))) | L61: =IF(in_Lead=1,K63,IF(in_Lead=2,J63,IF(in_Lead=3,I63,0))) | M61: =IF(in_Lead=1,L63,IF(in_Lead=2,K63,IF(in_Lead=3,J63,0))) | ... Q61: =IF(in_Lead=1,P63,IF(in_Lead=2,O63,IF(in_Lead=3,N63,0))) | R61: =SUM(C61:Q61)
A62: On order, still in transit after this month | C62: =IF(in_Lead>=2,0,0)+IF(in_Lead>=3,0,0) | D62: =IF(in_Lead>=2,C63,0)+IF(in_Lead>=3,0,0) | E62: =IF(in_Lead>=2,D63,0)+IF(in_Lead>=3,C63,0) | F62: =IF(in_Lead>=2,E63,0)+IF(in_Lead>=3,D63,0) | G62: =IF(in_Lead>=2,F63,0)+IF(in_Lead>=3,E63,0) | H62: =IF(in_Lead>=2,G63,0)+IF(in_Lead>=3,F63,0) | I62: =IF(in_Lead>=2,H63,0)+IF(in_Lead>=3,G63,0) | J62: =IF(in_Lead>=2,I63,0)+IF(in_Lead>=3,H63,0) | K62: =IF(in_Lead>=2,J63,0)+IF(in_Lead>=3,I63,0) | L62: =IF(in_Lead>=2,K63,0)+IF(in_Lead>=3,J63,0) | ... Q62: =IF(in_Lead>=2,P63,0)+IF(in_Lead>=3,O63,0)
A63: Reorder placed and paid | C63: =IF(C24=1,IF(C59+C60+C61+C62<C58*in_Cover,ROUNDUP((C58*in_Cover-(C59+C60+C61+C62))/$B$9,0)*$B$9,0),0) | D63: =IF(D24=1,IF(D59+D60+D61+D62<D58*in_Cover,ROUNDUP((D58*in_Cover-(D59+D60+D61+D62))/$B$9,0)*$B$9,0),0) | E63: =IF(E24=1,IF(E59+E60+E61+E62<E58*in_Cover,ROUNDUP((E58*in_Cover-(E59+E60+E61+E62))/$B$9,0)*$B$9,0),0) | F63: =IF(F24=1,IF(F59+F60+F61+F62<F58*in_Cover,ROUNDUP((F58*in_Cover-(F59+F60+F61+F62))/$B$9,0)*$B$9,0),0) | G63: =IF(G24=1,IF(G59+G60+G61+G62<G58*in_Cover,ROUNDUP((G58*in_Cover-(G59+G60+G61+G62))/$B$9,0)*$B$9,0),0) | H63: =IF(H24=1,IF(H59+H60+H61+H62<H58*in_Cover,ROUNDUP((H58*in_Cover-(H59+H60+H61+H62))/$B$9,0)*$B$9,0),0) | I63: =IF(I24=1,IF(I59+I60+I61+I62<I58*in_Cover,ROUNDUP((I58*in_Cover-(I59+I60+I61+I62))/$B$9,0)*$B$9,0),0) | J63: =IF(J24=1,IF(J59+J60+J61+J62<J58*in_Cover,ROUNDUP((J58*in_Cover-(J59+J60+J61+J62))/$B$9,0)*$B$9,0),0) | ... Q63: =IF(Q24=1,IF(Q59+Q60+Q61+Q62<Q58*in_Cover,ROUNDUP((Q58*in_Cover-(Q59+Q60+Q61+Q62))/$B$9,0)*$B$9,0),0) | R63: =SUM(C63:Q63)
A64: Sticks sold | C64: =MIN(C58,C59+C60+C61) | D64: =MIN(D58,D59+D60+D61) | E64: =MIN(E58,E59+E60+E61) | F64: =MIN(F58,F59+F60+F61) | G64: =MIN(G58,G59+G60+G61) | H64: =MIN(H58,H59+H60+H61) | I64: =MIN(I58,I59+I60+I61) | J64: =MIN(J58,J59+J60+J61) | ... Q64: =MIN(Q58,Q59+Q60+Q61) | R64: =SUM(C64:Q64)
A65: Stick shortfall (check: should be 0) | B65: Must stay 0 | C65: =C58-C64 | D65: =D58-D64 | E65: =E58-E64 | F65: =F58-F64 | G65: =G58-G64 | H65: =H58-H64 | I65: =I58-I64 | J65: =J58-J64 | ... Q65: =Q58-Q64 | R65: =SUM(C65:Q65)
A66: Closing stock | C66: =C59+C60+C61-C64 | D66: =D59+D60+D61-D64 | E66: =E59+E60+E61-E64 | F66: =F59+F60+F61-F64 | G66: =G59+G60+G61-G64 | H66: =H59+H60+H61-H64 | I66: =I59+I60+I61-I64 | J66: =J59+J60+J61-J64 | ... Q66: =Q59+Q60+Q61-Q64
A68: Cash in
A69: DTC one-off pouches | C69: =C35*in_PricePouch | D69: =D35*in_PricePouch | E69: =E35*in_PricePouch | F69: =F35*in_PricePouch | G69: =G35*in_PricePouch | H69: =H35*in_PricePouch | I69: =I35*in_PricePouch | J69: =J35*in_PricePouch | ... Q69: =Q35*in_PricePouch | R69: =SUM(C69:Q69)
A70: DTC subscription pouches | C70: =C32*in_PricePouch*(1-in_SubDisc) | D70: =D32*in_PricePouch*(1-in_SubDisc) | E70: =E32*in_PricePouch*(1-in_SubDisc) | F70: =F32*in_PricePouch*(1-in_SubDisc) | G70: =G32*in_PricePouch*(1-in_SubDisc) | H70: =H32*in_PricePouch*(1-in_SubDisc) | I70: =I32*in_PricePouch*(1-in_SubDisc) | J70: =J32*in_PricePouch*(1-in_SubDisc) | ... Q70: =Q32*in_PricePouch*(1-in_SubDisc) | R70: =SUM(C70:Q70)
A71: Founding offer discount (waitlist first orders) | C71: =-C27*in_PricePouch*in_FoundDisc | D71: =-D27*in_PricePouch*in_FoundDisc | E71: =-E27*in_PricePouch*in_FoundDisc | F71: =-F27*in_PricePouch*in_FoundDisc | G71: =-G27*in_PricePouch*in_FoundDisc | H71: =-H27*in_PricePouch*in_FoundDisc | I71: =-I27*in_PricePouch*in_FoundDisc | J71: =-J27*in_PricePouch*in_FoundDisc | ... Q71: =-Q27*in_PricePouch*in_FoundDisc | R71: =SUM(C71:Q71)
A72: DTC stick boxes | C72: =C37*in_PriceStickBox | D72: =D37*in_PriceStickBox | E72: =E37*in_PriceStickBox | F72: =F37*in_PriceStickBox | G72: =G37*in_PriceStickBox | H72: =H37*in_PriceStickBox | I72: =I37*in_PriceStickBox | J72: =J37*in_PriceStickBox | ... Q72: =Q37*in_PriceStickBox | R72: =SUM(C72:Q72)
A73: Shipping charged to customers | C73: =IF(in_FreeShip=1,0,(C36+C37)*in_ShipCharge) | D73: =IF(in_FreeShip=1,0,(D36+D37)*in_ShipCharge) | E73: =IF(in_FreeShip=1,0,(E36+E37)*in_ShipCharge) | F73: =IF(in_FreeShip=1,0,(F36+F37)*in_ShipCharge) | G73: =IF(in_FreeShip=1,0,(G36+G37)*in_ShipCharge) | H73: =IF(in_FreeShip=1,0,(H36+H37)*in_ShipCharge) | I73: =IF(in_FreeShip=1,0,(I36+I37)*in_ShipCharge) | J73: =IF(in_FreeShip=1,0,(J36+J37)*in_ShipCharge) | ... Q73: =IF(in_FreeShip=1,0,(Q36+Q37)*in_ShipCharge) | R73: =SUM(C73:Q73)
A74: DTC revenue | C74: =SUM(C69:C73) | D74: =SUM(D69:D73) | E74: =SUM(E69:E73) | F74: =SUM(F69:F73) | G74: =SUM(G69:G73) | H74: =SUM(H69:H73) | I74: =SUM(I69:I73) | J74: =SUM(J69:J73) | ... Q74: =SUM(Q69:Q73) | R74: =SUM(C74:Q74)
A75: Wholesale invoiced (pouches + sticks) | C75: =C42*in_WsPouch+C43*in_WsStick | D75: =D42*in_WsPouch+D43*in_WsStick | E75: =E42*in_WsPouch+E43*in_WsStick | F75: =F42*in_WsPouch+F43*in_WsStick | G75: =G42*in_WsPouch+G43*in_WsStick | H75: =H42*in_WsPouch+H43*in_WsStick | I75: =I42*in_WsPouch+I43*in_WsStick | J75: =J42*in_WsPouch+J43*in_WsStick | ... Q75: =Q42*in_WsPouch+Q43*in_WsStick | R75: =SUM(C75:Q75)
A76: Wholesale cash collected | B76: Net 30 toggle | C76: =IF(in_Net30=1,0,C75) | D76: =IF(in_Net30=1,C75,D75) | E76: =IF(in_Net30=1,D75,E75) | F76: =IF(in_Net30=1,E75,F75) | G76: =IF(in_Net30=1,F75,G75) | H76: =IF(in_Net30=1,G75,H75) | I76: =IF(in_Net30=1,H75,I75) | J76: =IF(in_Net30=1,I75,J75) | K76: =IF(in_Net30=1,J75,K75) | ... Q76: =IF(in_Net30=1,P75,Q75) | R76: =SUM(C76:Q76)
A77: Total cash in | C77: =C74+C76 | D77: =D74+D76 | E77: =E74+E76 | F77: =F74+F76 | G77: =G74+G76 | H77: =H74+H76 | I77: =I74+I76 | J77: =J74+J76 | ... Q77: =Q74+Q76 | R77: =SUM(C77:Q77)
A79: Inventory purchases (cash out)
A80: First pouch run (deposit, then balance; less sample credit) | B80: Mode-dependent | C80: =$B$8*$B$6*(IF(EOMONTH(in_PODate,0)=EOMONTH(C$23,0),in_Deposit,0)+IF(EOMONTH(in_BalanceDate,0)=EOMONTH(C$23,0),1-in_Deposit,0))-IF(EOMONTH(in_PODate,0)=EOMONTH(C$23,0),$B$10,0) | D80: =$B$8*$B$6*(IF(EOMONTH(in_PODate,0)=EOMONTH(D$23,0),in_Deposit,0)+IF(EOMONTH(in_BalanceDate,0)=EOMONTH(D$23,0),1-in_Deposit,0))-IF(EOMONTH(in_PODate,0)=EOMONTH(D$23,0),$B$10,0) | E80: =$B$8*$B$6*(IF(EOMONTH(in_PODate,0)=EOMONTH(E$23,0),in_Deposit,0)+IF(EOMONTH(in_BalanceDate,0)=EOMONTH(E$23,0),1-in_Deposit,0))-IF(EOMONTH(in_PODate,0)=EOMONTH(E$23,0),$B$10,0) | F80: =$B$8*$B$6*(IF(EOMONTH(in_PODate,0)=EOMONTH(F$23,0),in_Deposit,0)+IF(EOMONTH(in_BalanceDate,0)=EOMONTH(F$23,0),1-in_Deposit,0))-IF(EOMONTH(in_PODate,0)=EOMONTH(F$23,0),$B$10,0) | G80: =$B$8*$B$6*(IF(EOMONTH(in_PODate,0)=EOMONTH(G$23,0),in_Deposit,0)+IF(EOMONTH(in_BalanceDate,0)=EOMONTH(G$23,0),1-in_Deposit,0))-IF(EOMONTH(in_PODate,0)=EOMONTH(G$23,0),$B$10,0) | H80: =$B$8*$B$6*(IF(EOMONTH(in_PODate,0)=EOMONTH(H$23,0),in_Deposit,0)+IF(EOMONTH(in_BalanceDate,0)=EOMONTH(H$23,0),1-in_Deposit,0))-IF(EOMONTH(in_PODate,0)=EOMONTH(H$23,0),$B$10,0) | I80: =$B$8*$B$6*(IF(EOMONTH(in_PODate,0)=EOMONTH(I$23,0),in_Deposit,0)+IF(EOMONTH(in_BalanceDate,0)=EOMONTH(I$23,0),1-in_Deposit,0))-IF(EOMONTH(in_PODate,0)=EOMONTH(I$23,0),$B$10,0) | J80: =$B$8*$B$6*(IF(EOMONTH(in_PODate,0)=EOMONTH(J$23,0),in_Deposit,0)+IF(EOMONTH(in_BalanceDate,0)=EOMONTH(J$23,0),1-in_Deposit,0))-IF(EOMONTH(in_PODate,0)=EOMONTH(J$23,0),$B$10,0) | ... Q80: =$B$8*$B$6*(IF(EOMONTH(in_PODate,0)=EOMONTH(Q$23,0),in_Deposit,0)+IF(EOMONTH(in_BalanceDate,0)=EOMONTH(Q$23,0),1-in_Deposit,0))-IF(EOMONTH(in_PODate,0)=EOMONTH(Q$23,0),$B$10,0) | R80: =SUM(C80:Q80)
A81: First protein stick run (deposit, then balance) | C81: =$B$9*$B$7*(IF(EOMONTH(in_PODate,0)=EOMONTH(C$23,0),in_Deposit,0)+IF(EOMONTH(in_BalanceDate,0)=EOMONTH(C$23,0),1-in_Deposit,0)) | D81: =$B$9*$B$7*(IF(EOMONTH(in_PODate,0)=EOMONTH(D$23,0),in_Deposit,0)+IF(EOMONTH(in_BalanceDate,0)=EOMONTH(D$23,0),1-in_Deposit,0)) | E81: =$B$9*$B$7*(IF(EOMONTH(in_PODate,0)=EOMONTH(E$23,0),in_Deposit,0)+IF(EOMONTH(in_BalanceDate,0)=EOMONTH(E$23,0),1-in_Deposit,0)) | F81: =$B$9*$B$7*(IF(EOMONTH(in_PODate,0)=EOMONTH(F$23,0),in_Deposit,0)+IF(EOMONTH(in_BalanceDate,0)=EOMONTH(F$23,0),1-in_Deposit,0)) | G81: =$B$9*$B$7*(IF(EOMONTH(in_PODate,0)=EOMONTH(G$23,0),in_Deposit,0)+IF(EOMONTH(in_BalanceDate,0)=EOMONTH(G$23,0),1-in_Deposit,0)) | H81: =$B$9*$B$7*(IF(EOMONTH(in_PODate,0)=EOMONTH(H$23,0),in_Deposit,0)+IF(EOMONTH(in_BalanceDate,0)=EOMONTH(H$23,0),1-in_Deposit,0)) | I81: =$B$9*$B$7*(IF(EOMONTH(in_PODate,0)=EOMONTH(I$23,0),in_Deposit,0)+IF(EOMONTH(in_BalanceDate,0)=EOMONTH(I$23,0),1-in_Deposit,0)) | J81: =$B$9*$B$7*(IF(EOMONTH(in_PODate,0)=EOMONTH(J$23,0),in_Deposit,0)+IF(EOMONTH(in_BalanceDate,0)=EOMONTH(J$23,0),1-in_Deposit,0)) | ... Q81: =$B$9*$B$7*(IF(EOMONTH(in_PODate,0)=EOMONTH(Q$23,0),in_Deposit,0)+IF(EOMONTH(in_BalanceDate,0)=EOMONTH(Q$23,0),1-in_Deposit,0)) | R81: =SUM(C81:Q81)
A82: Second flavour first run | C82: =C49*$B$6 | D82: =D49*$B$6 | E82: =E49*$B$6 | F82: =F49*$B$6 | G82: =G49*$B$6 | H82: =H49*$B$6 | I82: =I49*$B$6 | J82: =J49*$B$6 | ... Q82: =Q49*$B$6 | R82: =SUM(C82:Q82)
A83: Reorders placed (pouches and sticks, paid in full when placed) | C83: =C52*$B$6+C63*$B$7 | D83: =D52*$B$6+D63*$B$7 | E83: =E52*$B$6+E63*$B$7 | F83: =F52*$B$6+F63*$B$7 | G83: =G52*$B$6+G63*$B$7 | H83: =H52*$B$6+H63*$B$7 | I83: =I52*$B$6+I63*$B$7 | J83: =J52*$B$6+J63*$B$7 | ... Q83: =Q52*$B$6+Q63*$B$7 | R83: =SUM(C83:Q83)
A84: Total inventory purchases | C84: =SUM(C80:C83) | D84: =SUM(D80:D83) | E84: =SUM(E80:E83) | F84: =SUM(F80:F83) | G84: =SUM(G80:G83) | H84: =SUM(H80:H83) | I84: =SUM(I80:I83) | J84: =SUM(J80:J83) | ... Q84: =SUM(Q80:Q83) | R84: =SUM(C84:Q84)
A86: Variable costs (cash out)
A87: DTC shipping and packing | C87: =(C36+C37)*in_ShipOrder | D87: =(D36+D37)*in_ShipOrder | E87: =(E36+E37)*in_ShipOrder | F87: =(F36+F37)*in_ShipOrder | G87: =(G36+G37)*in_ShipOrder | H87: =(H36+H37)*in_ShipOrder | I87: =(I36+I37)*in_ShipOrder | J87: =(J36+J37)*in_ShipOrder | ... Q87: =(Q36+Q37)*in_ShipOrder | R87: =SUM(C87:Q87)
A88: Freight to stores | C88: =C42*in_FreightPouch+C43*in_FreightStick | D88: =D42*in_FreightPouch+D43*in_FreightStick | E88: =E42*in_FreightPouch+E43*in_FreightStick | F88: =F42*in_FreightPouch+F43*in_FreightStick | G88: =G42*in_FreightPouch+G43*in_FreightStick | H88: =H42*in_FreightPouch+H43*in_FreightStick | I88: =I42*in_FreightPouch+I43*in_FreightStick | J88: =J42*in_FreightPouch+J43*in_FreightStick | ... Q88: =Q42*in_FreightPouch+Q43*in_FreightStick | R88: =SUM(C88:Q88)
A89: Card fees | C89: =C74*in_CardPct+(C36+C37)*in_CardFixed | D89: =D74*in_CardPct+(D36+D37)*in_CardFixed | E89: =E74*in_CardPct+(E36+E37)*in_CardFixed | F89: =F74*in_CardPct+(F36+F37)*in_CardFixed | G89: =G74*in_CardPct+(G36+G37)*in_CardFixed | H89: =H74*in_CardPct+(H36+H37)*in_CardFixed | I89: =I74*in_CardPct+(I36+I37)*in_CardFixed | J89: =J74*in_CardPct+(J36+J37)*in_CardFixed | ... Q89: =Q74*in_CardPct+(Q36+Q37)*in_CardFixed | R89: =SUM(C89:Q89)
A90: Founding offer free shakers | C90: =C27*in_ShakerCost | D90: =D27*in_ShakerCost | E90: =E27*in_ShakerCost | F90: =F27*in_ShakerCost | G90: =G27*in_ShakerCost | H90: =H27*in_ShakerCost | I90: =I27*in_ShakerCost | J90: =J27*in_ShakerCost | ... Q90: =Q27*in_ShakerCost | R90: =SUM(C90:Q90)
A91: Total variable costs | C91: =SUM(C87:C90) | D91: =SUM(D87:D90) | E91: =SUM(E87:E90) | F91: =SUM(F87:F90) | G91: =SUM(G87:G90) | H91: =SUM(H87:H90) | I91: =SUM(I87:I90) | J91: =SUM(J87:J90) | ... Q91: =SUM(Q87:Q90) | R91: =SUM(C91:Q91)
A93: Marketing (cash out)
A94: Paid acquisition (paid new customers x CAC) | C94: =C29*in_CAC | D94: =D29*in_CAC | E94: =E29*in_CAC | F94: =F29*in_CAC | G94: =G29*in_CAC | H94: =H29*in_CAC | I94: =I29*in_CAC | J94: =J29*in_CAC | ... Q94: =Q29*in_CAC | R94: =SUM(C94:Q94)
A95: Sampling and content | C95: =IF(C$23>=DATE(YEAR(in_SampleStart),MONTH(in_SampleStart),1),in_SampleBudget,0) | D95: =IF(D$23>=DATE(YEAR(in_SampleStart),MONTH(in_SampleStart),1),in_SampleBudget,0) | E95: =IF(E$23>=DATE(YEAR(in_SampleStart),MONTH(in_SampleStart),1),in_SampleBudget,0) | F95: =IF(F$23>=DATE(YEAR(in_SampleStart),MONTH(in_SampleStart),1),in_SampleBudget,0) | G95: =IF(G$23>=DATE(YEAR(in_SampleStart),MONTH(in_SampleStart),1),in_SampleBudget,0) | H95: =IF(H$23>=DATE(YEAR(in_SampleStart),MONTH(in_SampleStart),1),in_SampleBudget,0) | I95: =IF(I$23>=DATE(YEAR(in_SampleStart),MONTH(in_SampleStart),1),in_SampleBudget,0) | J95: =IF(J$23>=DATE(YEAR(in_SampleStart),MONTH(in_SampleStart),1),in_SampleBudget,0) | ... Q95: =IF(Q$23>=DATE(YEAR(in_SampleStart),MONTH(in_SampleStart),1),in_SampleBudget,0) | R95: =SUM(C95:Q95)
A96: Total marketing | C96: =C94+C95 | D96: =D94+D95 | E96: =E94+E95 | F96: =F94+F95 | G96: =G94+G95 | H96: =H94+H95 | I96: =I94+I95 | J96: =J94+J95 | ... Q96: =Q94+Q95 | R96: =SUM(C96:Q96)
A98: Fixed costs (cash out)
A99: Shopify Basic | C99: =IF(C$23>=DATE(YEAR(in_FxShopify_Start),MONTH(in_FxShopify_Start),1),in_FxShopify,0) | D99: =IF(D$23>=DATE(YEAR(in_FxShopify_Start),MONTH(in_FxShopify_Start),1),in_FxShopify,0) | E99: =IF(E$23>=DATE(YEAR(in_FxShopify_Start),MONTH(in_FxShopify_Start),1),in_FxShopify,0) | F99: =IF(F$23>=DATE(YEAR(in_FxShopify_Start),MONTH(in_FxShopify_Start),1),in_FxShopify,0) | G99: =IF(G$23>=DATE(YEAR(in_FxShopify_Start),MONTH(in_FxShopify_Start),1),in_FxShopify,0) | H99: =IF(H$23>=DATE(YEAR(in_FxShopify_Start),MONTH(in_FxShopify_Start),1),in_FxShopify,0) | I99: =IF(I$23>=DATE(YEAR(in_FxShopify_Start),MONTH(in_FxShopify_Start),1),in_FxShopify,0) | J99: =IF(J$23>=DATE(YEAR(in_FxShopify_Start),MONTH(in_FxShopify_Start),1),in_FxShopify,0) | ... Q99: =IF(Q$23>=DATE(YEAR(in_FxShopify_Start),MONTH(in_FxShopify_Start),1),in_FxShopify,0) | R99: =SUM(C99:Q99)
A100: Klaviyo email | C100: =IF(C$23>=DATE(YEAR(in_FxKlaviyo_Start),MONTH(in_FxKlaviyo_Start),1),in_FxKlaviyo,0) | D100: =IF(D$23>=DATE(YEAR(in_FxKlaviyo_Start),MONTH(in_FxKlaviyo_Start),1),in_FxKlaviyo,0) | E100: =IF(E$23>=DATE(YEAR(in_FxKlaviyo_Start),MONTH(in_FxKlaviyo_Start),1),in_FxKlaviyo,0) | F100: =IF(F$23>=DATE(YEAR(in_FxKlaviyo_Start),MONTH(in_FxKlaviyo_Start),1),in_FxKlaviyo,0) | G100: =IF(G$23>=DATE(YEAR(in_FxKlaviyo_Start),MONTH(in_FxKlaviyo_Start),1),in_FxKlaviyo,0) | H100: =IF(H$23>=DATE(YEAR(in_FxKlaviyo_Start),MONTH(in_FxKlaviyo_Start),1),in_FxKlaviyo,0) | I100: =IF(I$23>=DATE(YEAR(in_FxKlaviyo_Start),MONTH(in_FxKlaviyo_Start),1),in_FxKlaviyo,0) | J100: =IF(J$23>=DATE(YEAR(in_FxKlaviyo_Start),MONTH(in_FxKlaviyo_Start),1),in_FxKlaviyo,0) | ... Q100: =IF(Q$23>=DATE(YEAR(in_FxKlaviyo_Start),MONTH(in_FxKlaviyo_Start),1),in_FxKlaviyo,0) | R100: =SUM(C100:Q100)
A101: Product liability insurance | C101: =IF(C$23>=DATE(YEAR(in_FxInsurance_Start),MONTH(in_FxInsurance_Start),1),in_FxInsurance,0) | D101: =IF(D$23>=DATE(YEAR(in_FxInsurance_Start),MONTH(in_FxInsurance_Start),1),in_FxInsurance,0) | E101: =IF(E$23>=DATE(YEAR(in_FxInsurance_Start),MONTH(in_FxInsurance_Start),1),in_FxInsurance,0) | F101: =IF(F$23>=DATE(YEAR(in_FxInsurance_Start),MONTH(in_FxInsurance_Start),1),in_FxInsurance,0) | G101: =IF(G$23>=DATE(YEAR(in_FxInsurance_Start),MONTH(in_FxInsurance_Start),1),in_FxInsurance,0) | H101: =IF(H$23>=DATE(YEAR(in_FxInsurance_Start),MONTH(in_FxInsurance_Start),1),in_FxInsurance,0) | I101: =IF(I$23>=DATE(YEAR(in_FxInsurance_Start),MONTH(in_FxInsurance_Start),1),in_FxInsurance,0) | J101: =IF(J$23>=DATE(YEAR(in_FxInsurance_Start),MONTH(in_FxInsurance_Start),1),in_FxInsurance,0) | ... Q101: =IF(Q$23>=DATE(YEAR(in_FxInsurance_Start),MONTH(in_FxInsurance_Start),1),in_FxInsurance,0) | R101: =SUM(C101:Q101)
A102: Other software (SMS credits, apps) | C102: =IF(C$23>=DATE(YEAR(in_FxSoftware_Start),MONTH(in_FxSoftware_Start),1),in_FxSoftware,0) | D102: =IF(D$23>=DATE(YEAR(in_FxSoftware_Start),MONTH(in_FxSoftware_Start),1),in_FxSoftware,0) | E102: =IF(E$23>=DATE(YEAR(in_FxSoftware_Start),MONTH(in_FxSoftware_Start),1),in_FxSoftware,0) | F102: =IF(F$23>=DATE(YEAR(in_FxSoftware_Start),MONTH(in_FxSoftware_Start),1),in_FxSoftware,0) | G102: =IF(G$23>=DATE(YEAR(in_FxSoftware_Start),MONTH(in_FxSoftware_Start),1),in_FxSoftware,0) | H102: =IF(H$23>=DATE(YEAR(in_FxSoftware_Start),MONTH(in_FxSoftware_Start),1),in_FxSoftware,0) | I102: =IF(I$23>=DATE(YEAR(in_FxSoftware_Start),MONTH(in_FxSoftware_Start),1),in_FxSoftware,0) | J102: =IF(J$23>=DATE(YEAR(in_FxSoftware_Start),MONTH(in_FxSoftware_Start),1),in_FxSoftware,0) | ... Q102: =IF(Q$23>=DATE(YEAR(in_FxSoftware_Start),MONTH(in_FxSoftware_Start),1),in_FxSoftware,0) | R102: =SUM(C102:Q102)
A103: Bookkeeping | C103: =IF(C$23>=DATE(YEAR(in_FxBooks_Start),MONTH(in_FxBooks_Start),1),in_FxBooks,0) | D103: =IF(D$23>=DATE(YEAR(in_FxBooks_Start),MONTH(in_FxBooks_Start),1),in_FxBooks,0) | E103: =IF(E$23>=DATE(YEAR(in_FxBooks_Start),MONTH(in_FxBooks_Start),1),in_FxBooks,0) | F103: =IF(F$23>=DATE(YEAR(in_FxBooks_Start),MONTH(in_FxBooks_Start),1),in_FxBooks,0) | G103: =IF(G$23>=DATE(YEAR(in_FxBooks_Start),MONTH(in_FxBooks_Start),1),in_FxBooks,0) | H103: =IF(H$23>=DATE(YEAR(in_FxBooks_Start),MONTH(in_FxBooks_Start),1),in_FxBooks,0) | I103: =IF(I$23>=DATE(YEAR(in_FxBooks_Start),MONTH(in_FxBooks_Start),1),in_FxBooks,0) | J103: =IF(J$23>=DATE(YEAR(in_FxBooks_Start),MONTH(in_FxBooks_Start),1),in_FxBooks,0) | ... Q103: =IF(Q$23>=DATE(YEAR(in_FxBooks_Start),MONTH(in_FxBooks_Start),1),in_FxBooks,0) | R103: =SUM(C103:Q103)
A104: Amazon Professional plan | C104: =IF(C$23>=DATE(YEAR(in_FxAmazon_Start),MONTH(in_FxAmazon_Start),1),in_FxAmazon,0) | D104: =IF(D$23>=DATE(YEAR(in_FxAmazon_Start),MONTH(in_FxAmazon_Start),1),in_FxAmazon,0) | E104: =IF(E$23>=DATE(YEAR(in_FxAmazon_Start),MONTH(in_FxAmazon_Start),1),in_FxAmazon,0) | F104: =IF(F$23>=DATE(YEAR(in_FxAmazon_Start),MONTH(in_FxAmazon_Start),1),in_FxAmazon,0) | G104: =IF(G$23>=DATE(YEAR(in_FxAmazon_Start),MONTH(in_FxAmazon_Start),1),in_FxAmazon,0) | H104: =IF(H$23>=DATE(YEAR(in_FxAmazon_Start),MONTH(in_FxAmazon_Start),1),in_FxAmazon,0) | I104: =IF(I$23>=DATE(YEAR(in_FxAmazon_Start),MONTH(in_FxAmazon_Start),1),in_FxAmazon,0) | J104: =IF(J$23>=DATE(YEAR(in_FxAmazon_Start),MONTH(in_FxAmazon_Start),1),in_FxAmazon,0) | ... Q104: =IF(Q$23>=DATE(YEAR(in_FxAmazon_Start),MONTH(in_FxAmazon_Start),1),in_FxAmazon,0) | R104: =SUM(C104:Q104)
A105: Total fixed costs | C105: =SUM(C99:C104) | D105: =SUM(D99:D104) | E105: =SUM(E99:E104) | F105: =SUM(F99:F104) | G105: =SUM(G99:G104) | H105: =SUM(H99:H104) | I105: =SUM(I99:I104) | J105: =SUM(J99:J104) | ... Q105: =SUM(Q99:Q104) | R105: =SUM(C105:Q105)
A107: One-time launch costs (cash out)
A108: Company, trademark, lawyer review, insurance setup | C108: =IF(EOMONTH(in_OtCompany_D,0)=EOMONTH(C$23,0),IF($B$3="Lean",in_OtCompany_L,in_OtCompany_S),0) | D108: =IF(EOMONTH(in_OtCompany_D,0)=EOMONTH(D$23,0),IF($B$3="Lean",in_OtCompany_L,in_OtCompany_S),0) | E108: =IF(EOMONTH(in_OtCompany_D,0)=EOMONTH(E$23,0),IF($B$3="Lean",in_OtCompany_L,in_OtCompany_S),0) | F108: =IF(EOMONTH(in_OtCompany_D,0)=EOMONTH(F$23,0),IF($B$3="Lean",in_OtCompany_L,in_OtCompany_S),0) | G108: =IF(EOMONTH(in_OtCompany_D,0)=EOMONTH(G$23,0),IF($B$3="Lean",in_OtCompany_L,in_OtCompany_S),0) | H108: =IF(EOMONTH(in_OtCompany_D,0)=EOMONTH(H$23,0),IF($B$3="Lean",in_OtCompany_L,in_OtCompany_S),0) | I108: =IF(EOMONTH(in_OtCompany_D,0)=EOMONTH(I$23,0),IF($B$3="Lean",in_OtCompany_L,in_OtCompany_S),0) | J108: =IF(EOMONTH(in_OtCompany_D,0)=EOMONTH(J$23,0),IF($B$3="Lean",in_OtCompany_L,in_OtCompany_S),0) | ... Q108: =IF(EOMONTH(in_OtCompany_D,0)=EOMONTH(Q$23,0),IF($B$3="Lean",in_OtCompany_L,in_OtCompany_S),0) | R108: =SUM(C108:Q108)
A109: Samples and flavour development (Strawberry) | C109: =IF(EOMONTH(in_OtSamples_D,0)=EOMONTH(C$23,0),IF($B$3="Lean",in_OtSamples_L,in_OtSamples_S),0) | D109: =IF(EOMONTH(in_OtSamples_D,0)=EOMONTH(D$23,0),IF($B$3="Lean",in_OtSamples_L,in_OtSamples_S),0) | E109: =IF(EOMONTH(in_OtSamples_D,0)=EOMONTH(E$23,0),IF($B$3="Lean",in_OtSamples_L,in_OtSamples_S),0) | F109: =IF(EOMONTH(in_OtSamples_D,0)=EOMONTH(F$23,0),IF($B$3="Lean",in_OtSamples_L,in_OtSamples_S),0) | G109: =IF(EOMONTH(in_OtSamples_D,0)=EOMONTH(G$23,0),IF($B$3="Lean",in_OtSamples_L,in_OtSamples_S),0) | H109: =IF(EOMONTH(in_OtSamples_D,0)=EOMONTH(H$23,0),IF($B$3="Lean",in_OtSamples_L,in_OtSamples_S),0) | I109: =IF(EOMONTH(in_OtSamples_D,0)=EOMONTH(I$23,0),IF($B$3="Lean",in_OtSamples_L,in_OtSamples_S),0) | J109: =IF(EOMONTH(in_OtSamples_D,0)=EOMONTH(J$23,0),IF($B$3="Lean",in_OtSamples_L,in_OtSamples_S),0) | ... Q109: =IF(EOMONTH(in_OtSamples_D,0)=EOMONTH(Q$23,0),IF($B$3="Lean",in_OtSamples_L,in_OtSamples_S),0) | R109: =SUM(C109:Q109)
A110: Label and regulatory review | C110: =IF(EOMONTH(in_OtLabel_D,0)=EOMONTH(C$23,0),IF($B$3="Lean",in_OtLabel_L,in_OtLabel_S),0) | D110: =IF(EOMONTH(in_OtLabel_D,0)=EOMONTH(D$23,0),IF($B$3="Lean",in_OtLabel_L,in_OtLabel_S),0) | E110: =IF(EOMONTH(in_OtLabel_D,0)=EOMONTH(E$23,0),IF($B$3="Lean",in_OtLabel_L,in_OtLabel_S),0) | F110: =IF(EOMONTH(in_OtLabel_D,0)=EOMONTH(F$23,0),IF($B$3="Lean",in_OtLabel_L,in_OtLabel_S),0) | G110: =IF(EOMONTH(in_OtLabel_D,0)=EOMONTH(G$23,0),IF($B$3="Lean",in_OtLabel_L,in_OtLabel_S),0) | H110: =IF(EOMONTH(in_OtLabel_D,0)=EOMONTH(H$23,0),IF($B$3="Lean",in_OtLabel_L,in_OtLabel_S),0) | I110: =IF(EOMONTH(in_OtLabel_D,0)=EOMONTH(I$23,0),IF($B$3="Lean",in_OtLabel_L,in_OtLabel_S),0) | J110: =IF(EOMONTH(in_OtLabel_D,0)=EOMONTH(J$23,0),IF($B$3="Lean",in_OtLabel_L,in_OtLabel_S),0) | ... Q110: =IF(EOMONTH(in_OtLabel_D,0)=EOMONTH(Q$23,0),IF($B$3="Lean",in_OtLabel_L,in_OtLabel_S),0) | R110: =SUM(C110:Q110)
A111: Launch kit: shakers, display, sampling supplies, apps | C111: =IF(EOMONTH(in_OtKit_D,0)=EOMONTH(C$23,0),IF($B$3="Lean",in_OtKit_L,in_OtKit_S),0) | D111: =IF(EOMONTH(in_OtKit_D,0)=EOMONTH(D$23,0),IF($B$3="Lean",in_OtKit_L,in_OtKit_S),0) | E111: =IF(EOMONTH(in_OtKit_D,0)=EOMONTH(E$23,0),IF($B$3="Lean",in_OtKit_L,in_OtKit_S),0) | F111: =IF(EOMONTH(in_OtKit_D,0)=EOMONTH(F$23,0),IF($B$3="Lean",in_OtKit_L,in_OtKit_S),0) | G111: =IF(EOMONTH(in_OtKit_D,0)=EOMONTH(G$23,0),IF($B$3="Lean",in_OtKit_L,in_OtKit_S),0) | H111: =IF(EOMONTH(in_OtKit_D,0)=EOMONTH(H$23,0),IF($B$3="Lean",in_OtKit_L,in_OtKit_S),0) | I111: =IF(EOMONTH(in_OtKit_D,0)=EOMONTH(I$23,0),IF($B$3="Lean",in_OtKit_L,in_OtKit_S),0) | J111: =IF(EOMONTH(in_OtKit_D,0)=EOMONTH(J$23,0),IF($B$3="Lean",in_OtKit_L,in_OtKit_S),0) | ... Q111: =IF(EOMONTH(in_OtKit_D,0)=EOMONTH(Q$23,0),IF($B$3="Lean",in_OtKit_L,in_OtKit_S),0) | R111: =SUM(C111:Q111)
A112: Real Fruit Hydration sticks (development and first run) | C112: =IF(EOMONTH(in_OtHydra_D,0)=EOMONTH(C$23,0),IF($B$3="Lean",in_OtHydra_L,in_OtHydra_S),0)*in_HydraOn | D112: =IF(EOMONTH(in_OtHydra_D,0)=EOMONTH(D$23,0),IF($B$3="Lean",in_OtHydra_L,in_OtHydra_S),0)*in_HydraOn | E112: =IF(EOMONTH(in_OtHydra_D,0)=EOMONTH(E$23,0),IF($B$3="Lean",in_OtHydra_L,in_OtHydra_S),0)*in_HydraOn | F112: =IF(EOMONTH(in_OtHydra_D,0)=EOMONTH(F$23,0),IF($B$3="Lean",in_OtHydra_L,in_OtHydra_S),0)*in_HydraOn | G112: =IF(EOMONTH(in_OtHydra_D,0)=EOMONTH(G$23,0),IF($B$3="Lean",in_OtHydra_L,in_OtHydra_S),0)*in_HydraOn | H112: =IF(EOMONTH(in_OtHydra_D,0)=EOMONTH(H$23,0),IF($B$3="Lean",in_OtHydra_L,in_OtHydra_S),0)*in_HydraOn | I112: =IF(EOMONTH(in_OtHydra_D,0)=EOMONTH(I$23,0),IF($B$3="Lean",in_OtHydra_L,in_OtHydra_S),0)*in_HydraOn | J112: =IF(EOMONTH(in_OtHydra_D,0)=EOMONTH(J$23,0),IF($B$3="Lean",in_OtHydra_L,in_OtHydra_S),0)*in_HydraOn | ... Q112: =IF(EOMONTH(in_OtHydra_D,0)=EOMONTH(Q$23,0),IF($B$3="Lean",in_OtHydra_L,in_OtHydra_S),0)*in_HydraOn | R112: =SUM(C112:Q112)
...

Sheet calc_Lean_Base
A1: Calculation copy: Lean runs, Base demand (feeds Scenarios; do not edit)
A2: Months Oct 2026 to Dec 2027. All figures are projections from the Inputs sheet, not actual results. Cash view: inventory is a cash outflow when bought; COGS appears only in the operating view at the bottom.
A3: Run-size mode | B3: ="Lean"
A4: Demand multiplier | B4: =in_MultBase
A5: Demand case | B5: ="Base"
A6: Pouch cost of goods (by mode) | B6: =IF($B$3="Lean",in_CogsLean,in_CogsStd)
A7: Stick cost of goods (by mode) | B7: =IF($B$3="Lean",in_StickCogsLean,in_StickCogsStd)
A8: Pouch run size (by mode) | B8: =IF($B$3="Lean",in_RunLean,in_RunStd)
A9: Stick run size (by mode) | B9: =IF($B$3="Lean",in_StickRunLean,in_StickRunStd)
A10: Sample credit on first order (by mode) | B10: =IF($B$3="Lean",in_SampleCreditLean,in_SampleCreditStd)
A12: Summary for this sheet's mode and case
A13: Lowest cash balance | B13: =MIN($C$120:$Q$120)
A14: Month of lowest cash balance | B14: =INDEX($C$23:$Q$23,MATCH(MIN($C$120:$Q$120),$C$120:$Q$120,0))
A15: Peak funding need (lowest cumulative net cash flow) | B15: =MIN(0,MIN($C$119:$Q$119))
A16: Operating break-even month (first month operating profit >= 0) | B16: =IFERROR(INDEX($C$23:$Q$23,MATCH(1,$C$127:$Q$127,0)),"Not by Dec 2027")
A17: Cash payback month (cumulative net cash flow back to >= 0) | B17: =IFERROR(INDEX($C$23:$Q$23,MATCH(1,$C$128:$Q$128,0)),"Not by Dec 2027")
A18: Cash balance, end of Jun 2027 | B18: =IFERROR(INDEX($C$120:$Q$120,MATCH(DATE(2027,6,1),$C$23:$Q$23,0)),"n/a")
A19: Cash balance, end of Dec 2027 | B19: =IFERROR(INDEX($C$120:$Q$120,MATCH(DATE(2027,12,1),$C$23:$Q$23,0)),"n/a")
A20: Stockout check (pouch + stick units short; should be 0) | B20: =SUM($C$54:$Q$54)+SUM($C$65:$Q$65)
A21: Operating profit, Oct 2026 to Dec 2027 (launch costs excluded) | B21: =SUM($C$126:$Q$126)
A23: Line | B23: Note | C23: =DATE(YEAR(in_ModelStart),MONTH(in_ModelStart),1) | D23: =EDATE(C23,1) | E23: =EDATE(D23,1) | F23: =EDATE(E23,1) | G23: =EDATE(F23,1) | H23: =EDATE(G23,1) | I23: =EDATE(H23,1) | J23: =EDATE(I23,1) | K23: =EDATE(J23,1) | ... Q23: =EDATE(P23,1) | R23: Total
A24: Selling? (1 from the first ship month) | C24: =IF(C$23>=DATE(YEAR(in_FirstShip),MONTH(in_FirstShip),1),1,0) | D24: =IF(D$23>=DATE(YEAR(in_FirstShip),MONTH(in_FirstShip),1),1,0) | E24: =IF(E$23>=DATE(YEAR(in_FirstShip),MONTH(in_FirstShip),1),1,0) | F24: =IF(F$23>=DATE(YEAR(in_FirstShip),MONTH(in_FirstShip),1),1,0) | G24: =IF(G$23>=DATE(YEAR(in_FirstShip),MONTH(in_FirstShip),1),1,0) | H24: =IF(H$23>=DATE(YEAR(in_FirstShip),MONTH(in_FirstShip),1),1,0) | I24: =IF(I$23>=DATE(YEAR(in_FirstShip),MONTH(in_FirstShip),1),1,0) | J24: =IF(J$23>=DATE(YEAR(in_FirstShip),MONTH(in_FirstShip),1),1,0) | ... Q24: =IF(Q$23>=DATE(YEAR(in_FirstShip),MONTH(in_FirstShip),1),1,0)
A26: DTC customers and orders
A27: Waitlist first orders (first ship month only) | B27: Waitlist x conversion | C27: =IF(EOMONTH(in_FirstShip,0)=EOMONTH(C$23,0),in_WaitSize*in_WaitConv*$B$4,0) | D27: =IF(EOMONTH(in_FirstShip,0)=EOMONTH(D$23,0),in_WaitSize*in_WaitConv*$B$4,0) | E27: =IF(EOMONTH(in_FirstShip,0)=EOMONTH(E$23,0),in_WaitSize*in_WaitConv*$B$4,0) | F27: =IF(EOMONTH(in_FirstShip,0)=EOMONTH(F$23,0),in_WaitSize*in_WaitConv*$B$4,0) | G27: =IF(EOMONTH(in_FirstShip,0)=EOMONTH(G$23,0),in_WaitSize*in_WaitConv*$B$4,0) | H27: =IF(EOMONTH(in_FirstShip,0)=EOMONTH(H$23,0),in_WaitSize*in_WaitConv*$B$4,0) | I27: =IF(EOMONTH(in_FirstShip,0)=EOMONTH(I$23,0),in_WaitSize*in_WaitConv*$B$4,0) | J27: =IF(EOMONTH(in_FirstShip,0)=EOMONTH(J$23,0),in_WaitSize*in_WaitConv*$B$4,0) | ... Q27: =IF(EOMONTH(in_FirstShip,0)=EOMONTH(Q$23,0),in_WaitSize*in_WaitConv*$B$4,0) | R27: =SUM(C27:Q27)
A28: Organic new customers | C28: =IFERROR(INDEX(Inputs!$B$98:$B$107,MATCH(C$23,Inputs!$A$98:$A$107,0)),0)*$B$4*C24 | D28: =IFERROR(INDEX(Inputs!$B$98:$B$107,MATCH(D$23,Inputs!$A$98:$A$107,0)),0)*$B$4*D24 | E28: =IFERROR(INDEX(Inputs!$B$98:$B$107,MATCH(E$23,Inputs!$A$98:$A$107,0)),0)*$B$4*E24 | F28: =IFERROR(INDEX(Inputs!$B$98:$B$107,MATCH(F$23,Inputs!$A$98:$A$107,0)),0)*$B$4*F24 | G28: =IFERROR(INDEX(Inputs!$B$98:$B$107,MATCH(G$23,Inputs!$A$98:$A$107,0)),0)*$B$4*G24 | H28: =IFERROR(INDEX(Inputs!$B$98:$B$107,MATCH(H$23,Inputs!$A$98:$A$107,0)),0)*$B$4*H24 | I28: =IFERROR(INDEX(Inputs!$B$98:$B$107,MATCH(I$23,Inputs!$A$98:$A$107,0)),0)*$B$4*I24 | J28: =IFERROR(INDEX(Inputs!$B$98:$B$107,MATCH(J$23,Inputs!$A$98:$A$107,0)),0)*$B$4*J24 | ... Q28: =IFERROR(INDEX(Inputs!$B$98:$B$107,MATCH(Q$23,Inputs!$A$98:$A$107,0)),0)*$B$4*Q24 | R28: =SUM(C28:Q28)
A29: Paid new customers | C29: =IFERROR(INDEX(Inputs!$C$98:$C$107,MATCH(C$23,Inputs!$A$98:$A$107,0)),0)*$B$4*C24 | D29: =IFERROR(INDEX(Inputs!$C$98:$C$107,MATCH(D$23,Inputs!$A$98:$A$107,0)),0)*$B$4*D24 | E29: =IFERROR(INDEX(Inputs!$C$98:$C$107,MATCH(E$23,Inputs!$A$98:$A$107,0)),0)*$B$4*E24 | F29: =IFERROR(INDEX(Inputs!$C$98:$C$107,MATCH(F$23,Inputs!$A$98:$A$107,0)),0)*$B$4*F24 | G29: =IFERROR(INDEX(Inputs!$C$98:$C$107,MATCH(G$23,Inputs!$A$98:$A$107,0)),0)*$B$4*G24 | H29: =IFERROR(INDEX(Inputs!$C$98:$C$107,MATCH(H$23,Inputs!$A$98:$A$107,0)),0)*$B$4*H24 | I29: =IFERROR(INDEX(Inputs!$C$98:$C$107,MATCH(I$23,Inputs!$A$98:$A$107,0)),0)*$B$4*I24 | J29: =IFERROR(INDEX(Inputs!$C$98:$C$107,MATCH(J$23,Inputs!$A$98:$A$107,0)),0)*$B$4*J24 | ... Q29: =IFERROR(INDEX(Inputs!$C$98:$C$107,MATCH(Q$23,Inputs!$A$98:$A$107,0)),0)*$B$4*Q24 | R29: =SUM(C29:Q29)
A30: Total new DTC customers | C30: =C27+C28+C29 | D30: =D27+D28+D29 | E30: =E27+E28+E29 | F30: =F27+F28+F29 | G30: =G27+G28+G29 | H30: =H27+H28+H29 | I30: =I27+I28+I29 | J30: =J27+J28+J29 | ... Q30: =Q27+Q28+Q29 | R30: =SUM(C30:Q30)
A31: New subscribers | C31: =C30*in_SubShare | D31: =D30*in_SubShare | E31: =E30*in_SubShare | F31: =F30*in_SubShare | G31: =G30*in_SubShare | H31: =H30*in_SubShare | I31: =I30*in_SubShare | J31: =J30*in_SubShare | ... Q31: =Q30*in_SubShare | R31: =SUM(C31:Q31)
A32: Active subscribers, end of month (= subscription orders) | B32: 1 pouch/month each | C32: =C31 | D32: =C32*(1-in_SubChurn)+D31 | E32: =D32*(1-in_SubChurn)+E31 | F32: =E32*(1-in_SubChurn)+F31 | G32: =F32*(1-in_SubChurn)+G31 | H32: =G32*(1-in_SubChurn)+H31 | I32: =H32*(1-in_SubChurn)+I31 | J32: =I32*(1-in_SubChurn)+J31 | K32: =J32*(1-in_SubChurn)+K31 | ... Q32: =P32*(1-in_SubChurn)+Q31
A33: One-off first orders | C33: =C30*(1-in_SubShare) | D33: =D30*(1-in_SubShare) | E33: =E30*(1-in_SubShare) | F33: =F30*(1-in_SubShare) | G33: =G30*(1-in_SubShare) | H33: =H30*(1-in_SubShare) | I33: =I30*(1-in_SubShare) | J33: =J30*(1-in_SubShare) | ... Q33: =Q30*(1-in_SubShare) | R33: =SUM(C33:Q33)
A34: One-off repeat orders | C34: =0 | D34: =C35*in_Repeat | E34: =D35*in_Repeat | F34: =E35*in_Repeat | G34: =F35*in_Repeat | H34: =G35*in_Repeat | I34: =H35*in_Repeat | J34: =I35*in_Repeat | K34: =J35*in_Repeat | ... Q34: =P35*in_Repeat | R34: =SUM(C34:Q34)
A35: Total one-off pouch orders | C35: =C33+C34 | D35: =D33+D34 | E35: =E33+E34 | F35: =F33+F34 | G35: =G33+G34 | H35: =H33+H34 | I35: =I33+I34 | J35: =J33+J34 | ... Q35: =Q33+Q34 | R35: =SUM(C35:Q35)
A36: Total DTC pouch orders (one-off + subscription) | C36: =C35+C32 | D36: =D35+D32 | E36: =E35+E32 | F36: =F35+F32 | G36: =G35+G32 | H36: =H35+H32 | I36: =I35+I32 | J36: =J35+J32 | ... Q36: =Q35+Q32 | R36: =SUM(C36:Q36)
A37: DTC stick-box orders | C37: =C36*in_StickAttach | D37: =D36*in_StickAttach | E37: =E36*in_StickAttach | F37: =F36*in_StickAttach | G37: =G36*in_StickAttach | H37: =H36*in_StickAttach | I37: =I36*in_StickAttach | J37: =J36*in_StickAttach | ... Q37: =Q36*in_StickAttach | R37: =SUM(C37:Q37)
A39: Wholesale (direct to stores)
A40: New store accounts | C40: =IFERROR(INDEX(Inputs!$D$98:$D$107,MATCH(C$23,Inputs!$A$98:$A$107,0)),0)*$B$4*C24 | D40: =IFERROR(INDEX(Inputs!$D$98:$D$107,MATCH(D$23,Inputs!$A$98:$A$107,0)),0)*$B$4*D24 | E40: =IFERROR(INDEX(Inputs!$D$98:$D$107,MATCH(E$23,Inputs!$A$98:$A$107,0)),0)*$B$4*E24 | F40: =IFERROR(INDEX(Inputs!$D$98:$D$107,MATCH(F$23,Inputs!$A$98:$A$107,0)),0)*$B$4*F24 | G40: =IFERROR(INDEX(Inputs!$D$98:$D$107,MATCH(G$23,Inputs!$A$98:$A$107,0)),0)*$B$4*G24 | H40: =IFERROR(INDEX(Inputs!$D$98:$D$107,MATCH(H$23,Inputs!$A$98:$A$107,0)),0)*$B$4*H24 | I40: =IFERROR(INDEX(Inputs!$D$98:$D$107,MATCH(I$23,Inputs!$A$98:$A$107,0)),0)*$B$4*I24 | J40: =IFERROR(INDEX(Inputs!$D$98:$D$107,MATCH(J$23,Inputs!$A$98:$A$107,0)),0)*$B$4*J24 | ... Q40: =IFERROR(INDEX(Inputs!$D$98:$D$107,MATCH(Q$23,Inputs!$A$98:$A$107,0)),0)*$B$4*Q24 | R40: =SUM(C40:Q40)
A41: Active store accounts, end of month | C41: =C40 | D41: =C41*(1-in_StoreChurn)+D40 | E41: =D41*(1-in_StoreChurn)+E40 | F41: =E41*(1-in_StoreChurn)+F40 | G41: =F41*(1-in_StoreChurn)+G40 | H41: =G41*(1-in_StoreChurn)+H40 | I41: =H41*(1-in_StoreChurn)+I40 | J41: =I41*(1-in_StoreChurn)+J40 | K41: =J41*(1-in_StoreChurn)+K40 | ... Q41: =P41*(1-in_StoreChurn)+Q40
A42: Wholesale pouches shipped | C42: =C41*in_PouchPerStore | D42: =D41*in_PouchPerStore | E42: =E41*in_PouchPerStore | F42: =F41*in_PouchPerStore | G42: =G41*in_PouchPerStore | H42: =H41*in_PouchPerStore | I42: =I41*in_PouchPerStore | J42: =J41*in_PouchPerStore | ... Q42: =Q41*in_PouchPerStore | R42: =SUM(C42:Q42)
A43: Wholesale sticks shipped | C43: =C41*in_StickPerStore | D43: =D41*in_StickPerStore | E43: =E41*in_StickPerStore | F43: =F41*in_StickPerStore | G43: =G41*in_StickPerStore | H43: =H41*in_StickPerStore | I43: =I41*in_StickPerStore | J43: =J41*in_StickPerStore | ... Q43: =Q41*in_StickPerStore | R43: =SUM(C43:Q43)
A45: Pouch inventory (units)
A46: Pouch demand | C46: =C36*in_PouchPerOrder+C42 | D46: =D36*in_PouchPerOrder+D42 | E46: =E36*in_PouchPerOrder+E42 | F46: =F36*in_PouchPerOrder+F42 | G46: =G36*in_PouchPerOrder+G42 | H46: =H36*in_PouchPerOrder+H42 | I46: =I36*in_PouchPerOrder+I42 | J46: =J36*in_PouchPerOrder+J42 | ... Q46: =Q36*in_PouchPerOrder+Q42 | R46: =SUM(C46:Q46)
A47: Opening stock | C47: =0 | D47: =C55 | E47: =D55 | F47: =E55 | G47: =F55 | H47: =G55 | I47: =H55 | J47: =I55 | K47: =J55 | ... Q47: =P55
A48: First run received | C48: =IF(EOMONTH(in_FirstShip,0)=EOMONTH(C$23,0),$B$8,0) | D48: =IF(EOMONTH(in_FirstShip,0)=EOMONTH(D$23,0),$B$8,0) | E48: =IF(EOMONTH(in_FirstShip,0)=EOMONTH(E$23,0),$B$8,0) | F48: =IF(EOMONTH(in_FirstShip,0)=EOMONTH(F$23,0),$B$8,0) | G48: =IF(EOMONTH(in_FirstShip,0)=EOMONTH(G$23,0),$B$8,0) | H48: =IF(EOMONTH(in_FirstShip,0)=EOMONTH(H$23,0),$B$8,0) | I48: =IF(EOMONTH(in_FirstShip,0)=EOMONTH(I$23,0),$B$8,0) | J48: =IF(EOMONTH(in_FirstShip,0)=EOMONTH(J$23,0),$B$8,0) | ... Q48: =IF(EOMONTH(in_FirstShip,0)=EOMONTH(Q$23,0),$B$8,0) | R48: =SUM(C48:Q48)
A49: Second flavour first run received | C49: =IF(AND(in_Flavor2On=1,EOMONTH(in_Flavor2Run,0)=EOMONTH(C$23,0)),$B$8,0) | D49: =IF(AND(in_Flavor2On=1,EOMONTH(in_Flavor2Run,0)=EOMONTH(D$23,0)),$B$8,0) | E49: =IF(AND(in_Flavor2On=1,EOMONTH(in_Flavor2Run,0)=EOMONTH(E$23,0)),$B$8,0) | F49: =IF(AND(in_Flavor2On=1,EOMONTH(in_Flavor2Run,0)=EOMONTH(F$23,0)),$B$8,0) | G49: =IF(AND(in_Flavor2On=1,EOMONTH(in_Flavor2Run,0)=EOMONTH(G$23,0)),$B$8,0) | H49: =IF(AND(in_Flavor2On=1,EOMONTH(in_Flavor2Run,0)=EOMONTH(H$23,0)),$B$8,0) | I49: =IF(AND(in_Flavor2On=1,EOMONTH(in_Flavor2Run,0)=EOMONTH(I$23,0)),$B$8,0) | J49: =IF(AND(in_Flavor2On=1,EOMONTH(in_Flavor2Run,0)=EOMONTH(J$23,0)),$B$8,0) | ... Q49: =IF(AND(in_Flavor2On=1,EOMONTH(in_Flavor2Run,0)=EOMONTH(Q$23,0)),$B$8,0) | R49: =SUM(C49:Q49)
A50: Reorders received (placed lead-time months earlier) | B50: Lead-time input | C50: =IF(in_Lead=1,0,IF(in_Lead=2,0,IF(in_Lead=3,0,0))) | D50: =IF(in_Lead=1,C52,IF(in_Lead=2,0,IF(in_Lead=3,0,0))) | E50: =IF(in_Lead=1,D52,IF(in_Lead=2,C52,IF(in_Lead=3,0,0))) | F50: =IF(in_Lead=1,E52,IF(in_Lead=2,D52,IF(in_Lead=3,C52,0))) | G50: =IF(in_Lead=1,F52,IF(in_Lead=2,E52,IF(in_Lead=3,D52,0))) | H50: =IF(in_Lead=1,G52,IF(in_Lead=2,F52,IF(in_Lead=3,E52,0))) | I50: =IF(in_Lead=1,H52,IF(in_Lead=2,G52,IF(in_Lead=3,F52,0))) | J50: =IF(in_Lead=1,I52,IF(in_Lead=2,H52,IF(in_Lead=3,G52,0))) | K50: =IF(in_Lead=1,J52,IF(in_Lead=2,I52,IF(in_Lead=3,H52,0))) | L50: =IF(in_Lead=1,K52,IF(in_Lead=2,J52,IF(in_Lead=3,I52,0))) | M50: =IF(in_Lead=1,L52,IF(in_Lead=2,K52,IF(in_Lead=3,J52,0))) | ... Q50: =IF(in_Lead=1,P52,IF(in_Lead=2,O52,IF(in_Lead=3,N52,0))) | R50: =SUM(C50:Q50)
A51: On order, still in transit after this month | C51: =IF(in_Lead>=2,0,0)+IF(in_Lead>=3,0,0) | D51: =IF(in_Lead>=2,C52,0)+IF(in_Lead>=3,0,0) | E51: =IF(in_Lead>=2,D52,0)+IF(in_Lead>=3,C52,0) | F51: =IF(in_Lead>=2,E52,0)+IF(in_Lead>=3,D52,0) | G51: =IF(in_Lead>=2,F52,0)+IF(in_Lead>=3,E52,0) | H51: =IF(in_Lead>=2,G52,0)+IF(in_Lead>=3,F52,0) | I51: =IF(in_Lead>=2,H52,0)+IF(in_Lead>=3,G52,0) | J51: =IF(in_Lead>=2,I52,0)+IF(in_Lead>=3,H52,0) | K51: =IF(in_Lead>=2,J52,0)+IF(in_Lead>=3,I52,0) | L51: =IF(in_Lead>=2,K52,0)+IF(in_Lead>=3,J52,0) | ... Q51: =IF(in_Lead>=2,P52,0)+IF(in_Lead>=3,O52,0)
A52: Reorder placed and paid (stock + on order below reorder point) | B52: Paid when placed | C52: =IF(C24=1,IF(C47+C48+C49+C50+C51<C46*in_Cover,ROUNDUP((C46*in_Cover-(C47+C48+C49+C50+C51))/$B$8,0)*$B$8,0),0) | D52: =IF(D24=1,IF(D47+D48+D49+D50+D51<D46*in_Cover,ROUNDUP((D46*in_Cover-(D47+D48+D49+D50+D51))/$B$8,0)*$B$8,0),0) | E52: =IF(E24=1,IF(E47+E48+E49+E50+E51<E46*in_Cover,ROUNDUP((E46*in_Cover-(E47+E48+E49+E50+E51))/$B$8,0)*$B$8,0),0) | F52: =IF(F24=1,IF(F47+F48+F49+F50+F51<F46*in_Cover,ROUNDUP((F46*in_Cover-(F47+F48+F49+F50+F51))/$B$8,0)*$B$8,0),0) | G52: =IF(G24=1,IF(G47+G48+G49+G50+G51<G46*in_Cover,ROUNDUP((G46*in_Cover-(G47+G48+G49+G50+G51))/$B$8,0)*$B$8,0),0) | H52: =IF(H24=1,IF(H47+H48+H49+H50+H51<H46*in_Cover,ROUNDUP((H46*in_Cover-(H47+H48+H49+H50+H51))/$B$8,0)*$B$8,0),0) | I52: =IF(I24=1,IF(I47+I48+I49+I50+I51<I46*in_Cover,ROUNDUP((I46*in_Cover-(I47+I48+I49+I50+I51))/$B$8,0)*$B$8,0),0) | J52: =IF(J24=1,IF(J47+J48+J49+J50+J51<J46*in_Cover,ROUNDUP((J46*in_Cover-(J47+J48+J49+J50+J51))/$B$8,0)*$B$8,0),0) | ... Q52: =IF(Q24=1,IF(Q47+Q48+Q49+Q50+Q51<Q46*in_Cover,ROUNDUP((Q46*in_Cover-(Q47+Q48+Q49+Q50+Q51))/$B$8,0)*$B$8,0),0) | R52: =SUM(C52:Q52)
A53: Pouches sold | C53: =MIN(C46,C47+C48+C49+C50) | D53: =MIN(D46,D47+D48+D49+D50) | E53: =MIN(E46,E47+E48+E49+E50) | F53: =MIN(F46,F47+F48+F49+F50) | G53: =MIN(G46,G47+G48+G49+G50) | H53: =MIN(H46,H47+H48+H49+H50) | I53: =MIN(I46,I47+I48+I49+I50) | J53: =MIN(J46,J47+J48+J49+J50) | ... Q53: =MIN(Q46,Q47+Q48+Q49+Q50) | R53: =SUM(C53:Q53)
A54: Pouch shortfall (check: should be 0) | B54: Must stay 0 | C54: =C46-C53 | D54: =D46-D53 | E54: =E46-E53 | F54: =F46-F53 | G54: =G46-G53 | H54: =H46-H53 | I54: =I46-I53 | J54: =J46-J53 | ... Q54: =Q46-Q53 | R54: =SUM(C54:Q54)
A55: Closing stock | C55: =C47+C48+C49+C50-C53 | D55: =D47+D48+D49+D50-D53 | E55: =E47+E48+E49+E50-E53 | F55: =F47+F48+F49+F50-F53 | G55: =G47+G48+G49+G50-G53 | H55: =H47+H48+H49+H50-H53 | I55: =I47+I48+I49+I50-I53 | J55: =J47+J48+J49+J50-J53 | ... Q55: =Q47+Q48+Q49+Q50-Q53
A57: Protein stick inventory (units)
A58: Stick demand | C58: =C37*in_SticksPerBox+C43 | D58: =D37*in_SticksPerBox+D43 | E58: =E37*in_SticksPerBox+E43 | F58: =F37*in_SticksPerBox+F43 | G58: =G37*in_SticksPerBox+G43 | H58: =H37*in_SticksPerBox+H43 | I58: =I37*in_SticksPerBox+I43 | J58: =J37*in_SticksPerBox+J43 | ... Q58: =Q37*in_SticksPerBox+Q43 | R58: =SUM(C58:Q58)
A59: Opening stock | C59: =0 | D59: =C66 | E59: =D66 | F59: =E66 | G59: =F66 | H59: =G66 | I59: =H66 | J59: =I66 | K59: =J66 | ... Q59: =P66
A60: First run received | C60: =IF(EOMONTH(in_FirstShip,0)=EOMONTH(C$23,0),$B$9,0) | D60: =IF(EOMONTH(in_FirstShip,0)=EOMONTH(D$23,0),$B$9,0) | E60: =IF(EOMONTH(in_FirstShip,0)=EOMONTH(E$23,0),$B$9,0) | F60: =IF(EOMONTH(in_FirstShip,0)=EOMONTH(F$23,0),$B$9,0) | G60: =IF(EOMONTH(in_FirstShip,0)=EOMONTH(G$23,0),$B$9,0) | H60: =IF(EOMONTH(in_FirstShip,0)=EOMONTH(H$23,0),$B$9,0) | I60: =IF(EOMONTH(in_FirstShip,0)=EOMONTH(I$23,0),$B$9,0) | J60: =IF(EOMONTH(in_FirstShip,0)=EOMONTH(J$23,0),$B$9,0) | ... Q60: =IF(EOMONTH(in_FirstShip,0)=EOMONTH(Q$23,0),$B$9,0) | R60: =SUM(C60:Q60)
A61: Reorders received (placed lead-time months earlier) | C61: =IF(in_Lead=1,0,IF(in_Lead=2,0,IF(in_Lead=3,0,0))) | D61: =IF(in_Lead=1,C63,IF(in_Lead=2,0,IF(in_Lead=3,0,0))) | E61: =IF(in_Lead=1,D63,IF(in_Lead=2,C63,IF(in_Lead=3,0,0))) | F61: =IF(in_Lead=1,E63,IF(in_Lead=2,D63,IF(in_Lead=3,C63,0))) | G61: =IF(in_Lead=1,F63,IF(in_Lead=2,E63,IF(in_Lead=3,D63,0))) | H61: =IF(in_Lead=1,G63,IF(in_Lead=2,F63,IF(in_Lead=3,E63,0))) | I61: =IF(in_Lead=1,H63,IF(in_Lead=2,G63,IF(in_Lead=3,F63,0))) | J61: =IF(in_Lead=1,I63,IF(in_Lead=2,H63,IF(in_Lead=3,G63,0))) | K61: =IF(in_Lead=1,J63,IF(in_Lead=2,I63,IF(in_Lead=3,H63,0))) | L61: =IF(in_Lead=1,K63,IF(in_Lead=2,J63,IF(in_Lead=3,I63,0))) | M61: =IF(in_Lead=1,L63,IF(in_Lead=2,K63,IF(in_Lead=3,J63,0))) | ... Q61: =IF(in_Lead=1,P63,IF(in_Lead=2,O63,IF(in_Lead=3,N63,0))) | R61: =SUM(C61:Q61)
A62: On order, still in transit after this month | C62: =IF(in_Lead>=2,0,0)+IF(in_Lead>=3,0,0) | D62: =IF(in_Lead>=2,C63,0)+IF(in_Lead>=3,0,0) | E62: =IF(in_Lead>=2,D63,0)+IF(in_Lead>=3,C63,0) | F62: =IF(in_Lead>=2,E63,0)+IF(in_Lead>=3,D63,0) | G62: =IF(in_Lead>=2,F63,0)+IF(in_Lead>=3,E63,0) | H62: =IF(in_Lead>=2,G63,0)+IF(in_Lead>=3,F63,0) | I62: =IF(in_Lead>=2,H63,0)+IF(in_Lead>=3,G63,0) | J62: =IF(in_Lead>=2,I63,0)+IF(in_Lead>=3,H63,0) | K62: =IF(in_Lead>=2,J63,0)+IF(in_Lead>=3,I63,0) | L62: =IF(in_Lead>=2,K63,0)+IF(in_Lead>=3,J63,0) | ... Q62: =IF(in_Lead>=2,P63,0)+IF(in_Lead>=3,O63,0)
A63: Reorder placed and paid | C63: =IF(C24=1,IF(C59+C60+C61+C62<C58*in_Cover,ROUNDUP((C58*in_Cover-(C59+C60+C61+C62))/$B$9,0)*$B$9,0),0) | D63: =IF(D24=1,IF(D59+D60+D61+D62<D58*in_Cover,ROUNDUP((D58*in_Cover-(D59+D60+D61+D62))/$B$9,0)*$B$9,0),0) | E63: =IF(E24=1,IF(E59+E60+E61+E62<E58*in_Cover,ROUNDUP((E58*in_Cover-(E59+E60+E61+E62))/$B$9,0)*$B$9,0),0) | F63: =IF(F24=1,IF(F59+F60+F61+F62<F58*in_Cover,ROUNDUP((F58*in_Cover-(F59+F60+F61+F62))/$B$9,0)*$B$9,0),0) | G63: =IF(G24=1,IF(G59+G60+G61+G62<G58*in_Cover,ROUNDUP((G58*in_Cover-(G59+G60+G61+G62))/$B$9,0)*$B$9,0),0) | H63: =IF(H24=1,IF(H59+H60+H61+H62<H58*in_Cover,ROUNDUP((H58*in_Cover-(H59+H60+H61+H62))/$B$9,0)*$B$9,0),0) | I63: =IF(I24=1,IF(I59+I60+I61+I62<I58*in_Cover,ROUNDUP((I58*in_Cover-(I59+I60+I61+I62))/$B$9,0)*$B$9,0),0) | J63: =IF(J24=1,IF(J59+J60+J61+J62<J58*in_Cover,ROUNDUP((J58*in_Cover-(J59+J60+J61+J62))/$B$9,0)*$B$9,0),0) | ... Q63: =IF(Q24=1,IF(Q59+Q60+Q61+Q62<Q58*in_Cover,ROUNDUP((Q58*in_Cover-(Q59+Q60+Q61+Q62))/$B$9,0)*$B$9,0),0) | R63: =SUM(C63:Q63)
A64: Sticks sold | C64: =MIN(C58,C59+C60+C61) | D64: =MIN(D58,D59+D60+D61) | E64: =MIN(E58,E59+E60+E61) | F64: =MIN(F58,F59+F60+F61) | G64: =MIN(G58,G59+G60+G61) | H64: =MIN(H58,H59+H60+H61) | I64: =MIN(I58,I59+I60+I61) | J64: =MIN(J58,J59+J60+J61) | ... Q64: =MIN(Q58,Q59+Q60+Q61) | R64: =SUM(C64:Q64)
A65: Stick shortfall (check: should be 0) | B65: Must stay 0 | C65: =C58-C64 | D65: =D58-D64 | E65: =E58-E64 | F65: =F58-F64 | G65: =G58-G64 | H65: =H58-H64 | I65: =I58-I64 | J65: =J58-J64 | ... Q65: =Q58-Q64 | R65: =SUM(C65:Q65)
A66: Closing stock | C66: =C59+C60+C61-C64 | D66: =D59+D60+D61-D64 | E66: =E59+E60+E61-E64 | F66: =F59+F60+F61-F64 | G66: =G59+G60+G61-G64 | H66: =H59+H60+H61-H64 | I66: =I59+I60+I61-I64 | J66: =J59+J60+J61-J64 | ... Q66: =Q59+Q60+Q61-Q64
A68: Cash in
A69: DTC one-off pouches | C69: =C35*in_PricePouch | D69: =D35*in_PricePouch | E69: =E35*in_PricePouch | F69: =F35*in_PricePouch | G69: =G35*in_PricePouch | H69: =H35*in_PricePouch | I69: =I35*in_PricePouch | J69: =J35*in_PricePouch | ... Q69: =Q35*in_PricePouch | R69: =SUM(C69:Q69)
A70: DTC subscription pouches | C70: =C32*in_PricePouch*(1-in_SubDisc) | D70: =D32*in_PricePouch*(1-in_SubDisc) | E70: =E32*in_PricePouch*(1-in_SubDisc) | F70: =F32*in_PricePouch*(1-in_SubDisc) | G70: =G32*in_PricePouch*(1-in_SubDisc) | H70: =H32*in_PricePouch*(1-in_SubDisc) | I70: =I32*in_PricePouch*(1-in_SubDisc) | J70: =J32*in_PricePouch*(1-in_SubDisc) | ... Q70: =Q32*in_PricePouch*(1-in_SubDisc) | R70: =SUM(C70:Q70)
A71: Founding offer discount (waitlist first orders) | C71: =-C27*in_PricePouch*in_FoundDisc | D71: =-D27*in_PricePouch*in_FoundDisc | E71: =-E27*in_PricePouch*in_FoundDisc | F71: =-F27*in_PricePouch*in_FoundDisc | G71: =-G27*in_PricePouch*in_FoundDisc | H71: =-H27*in_PricePouch*in_FoundDisc | I71: =-I27*in_PricePouch*in_FoundDisc | J71: =-J27*in_PricePouch*in_FoundDisc | ... Q71: =-Q27*in_PricePouch*in_FoundDisc | R71: =SUM(C71:Q71)
A72: DTC stick boxes | C72: =C37*in_PriceStickBox | D72: =D37*in_PriceStickBox | E72: =E37*in_PriceStickBox | F72: =F37*in_PriceStickBox | G72: =G37*in_PriceStickBox | H72: =H37*in_PriceStickBox | I72: =I37*in_PriceStickBox | J72: =J37*in_PriceStickBox | ... Q72: =Q37*in_PriceStickBox | R72: =SUM(C72:Q72)
A73: Shipping charged to customers | C73: =IF(in_FreeShip=1,0,(C36+C37)*in_ShipCharge) | D73: =IF(in_FreeShip=1,0,(D36+D37)*in_ShipCharge) | E73: =IF(in_FreeShip=1,0,(E36+E37)*in_ShipCharge) | F73: =IF(in_FreeShip=1,0,(F36+F37)*in_ShipCharge) | G73: =IF(in_FreeShip=1,0,(G36+G37)*in_ShipCharge) | H73: =IF(in_FreeShip=1,0,(H36+H37)*in_ShipCharge) | I73: =IF(in_FreeShip=1,0,(I36+I37)*in_ShipCharge) | J73: =IF(in_FreeShip=1,0,(J36+J37)*in_ShipCharge) | ... Q73: =IF(in_FreeShip=1,0,(Q36+Q37)*in_ShipCharge) | R73: =SUM(C73:Q73)
A74: DTC revenue | C74: =SUM(C69:C73) | D74: =SUM(D69:D73) | E74: =SUM(E69:E73) | F74: =SUM(F69:F73) | G74: =SUM(G69:G73) | H74: =SUM(H69:H73) | I74: =SUM(I69:I73) | J74: =SUM(J69:J73) | ... Q74: =SUM(Q69:Q73) | R74: =SUM(C74:Q74)
A75: Wholesale invoiced (pouches + sticks) | C75: =C42*in_WsPouch+C43*in_WsStick | D75: =D42*in_WsPouch+D43*in_WsStick | E75: =E42*in_WsPouch+E43*in_WsStick | F75: =F42*in_WsPouch+F43*in_WsStick | G75: =G42*in_WsPouch+G43*in_WsStick | H75: =H42*in_WsPouch+H43*in_WsStick | I75: =I42*in_WsPouch+I43*in_WsStick | J75: =J42*in_WsPouch+J43*in_WsStick | ... Q75: =Q42*in_WsPouch+Q43*in_WsStick | R75: =SUM(C75:Q75)
A76: Wholesale cash collected | B76: Net 30 toggle | C76: =IF(in_Net30=1,0,C75) | D76: =IF(in_Net30=1,C75,D75) | E76: =IF(in_Net30=1,D75,E75) | F76: =IF(in_Net30=1,E75,F75) | G76: =IF(in_Net30=1,F75,G75) | H76: =IF(in_Net30=1,G75,H75) | I76: =IF(in_Net30=1,H75,I75) | J76: =IF(in_Net30=1,I75,J75) | K76: =IF(in_Net30=1,J75,K75) | ... Q76: =IF(in_Net30=1,P75,Q75) | R76: =SUM(C76:Q76)
A77: Total cash in | C77: =C74+C76 | D77: =D74+D76 | E77: =E74+E76 | F77: =F74+F76 | G77: =G74+G76 | H77: =H74+H76 | I77: =I74+I76 | J77: =J74+J76 | ... Q77: =Q74+Q76 | R77: =SUM(C77:Q77)
A79: Inventory purchases (cash out)
A80: First pouch run (deposit, then balance; less sample credit) | B80: Mode-dependent | C80: =$B$8*$B$6*(IF(EOMONTH(in_PODate,0)=EOMONTH(C$23,0),in_Deposit,0)+IF(EOMONTH(in_BalanceDate,0)=EOMONTH(C$23,0),1-in_Deposit,0))-IF(EOMONTH(in_PODate,0)=EOMONTH(C$23,0),$B$10,0) | D80: =$B$8*$B$6*(IF(EOMONTH(in_PODate,0)=EOMONTH(D$23,0),in_Deposit,0)+IF(EOMONTH(in_BalanceDate,0)=EOMONTH(D$23,0),1-in_Deposit,0))-IF(EOMONTH(in_PODate,0)=EOMONTH(D$23,0),$B$10,0) | E80: =$B$8*$B$6*(IF(EOMONTH(in_PODate,0)=EOMONTH(E$23,0),in_Deposit,0)+IF(EOMONTH(in_BalanceDate,0)=EOMONTH(E$23,0),1-in_Deposit,0))-IF(EOMONTH(in_PODate,0)=EOMONTH(E$23,0),$B$10,0) | F80: =$B$8*$B$6*(IF(EOMONTH(in_PODate,0)=EOMONTH(F$23,0),in_Deposit,0)+IF(EOMONTH(in_BalanceDate,0)=EOMONTH(F$23,0),1-in_Deposit,0))-IF(EOMONTH(in_PODate,0)=EOMONTH(F$23,0),$B$10,0) | G80: =$B$8*$B$6*(IF(EOMONTH(in_PODate,0)=EOMONTH(G$23,0),in_Deposit,0)+IF(EOMONTH(in_BalanceDate,0)=EOMONTH(G$23,0),1-in_Deposit,0))-IF(EOMONTH(in_PODate,0)=EOMONTH(G$23,0),$B$10,0) | H80: =$B$8*$B$6*(IF(EOMONTH(in_PODate,0)=EOMONTH(H$23,0),in_Deposit,0)+IF(EOMONTH(in_BalanceDate,0)=EOMONTH(H$23,0),1-in_Deposit,0))-IF(EOMONTH(in_PODate,0)=EOMONTH(H$23,0),$B$10,0) | I80: =$B$8*$B$6*(IF(EOMONTH(in_PODate,0)=EOMONTH(I$23,0),in_Deposit,0)+IF(EOMONTH(in_BalanceDate,0)=EOMONTH(I$23,0),1-in_Deposit,0))-IF(EOMONTH(in_PODate,0)=EOMONTH(I$23,0),$B$10,0) | J80: =$B$8*$B$6*(IF(EOMONTH(in_PODate,0)=EOMONTH(J$23,0),in_Deposit,0)+IF(EOMONTH(in_BalanceDate,0)=EOMONTH(J$23,0),1-in_Deposit,0))-IF(EOMONTH(in_PODate,0)=EOMONTH(J$23,0),$B$10,0) | ... Q80: =$B$8*$B$6*(IF(EOMONTH(in_PODate,0)=EOMONTH(Q$23,0),in_Deposit,0)+IF(EOMONTH(in_BalanceDate,0)=EOMONTH(Q$23,0),1-in_Deposit,0))-IF(EOMONTH(in_PODate,0)=EOMONTH(Q$23,0),$B$10,0) | R80: =SUM(C80:Q80)
A81: First protein stick run (deposit, then balance) | C81: =$B$9*$B$7*(IF(EOMONTH(in_PODate,0)=EOMONTH(C$23,0),in_Deposit,0)+IF(EOMONTH(in_BalanceDate,0)=EOMONTH(C$23,0),1-in_Deposit,0)) | D81: =$B$9*$B$7*(IF(EOMONTH(in_PODate,0)=EOMONTH(D$23,0),in_Deposit,0)+IF(EOMONTH(in_BalanceDate,0)=EOMONTH(D$23,0),1-in_Deposit,0)) | E81: =$B$9*$B$7*(IF(EOMONTH(in_PODate,0)=EOMONTH(E$23,0),in_Deposit,0)+IF(EOMONTH(in_BalanceDate,0)=EOMONTH(E$23,0),1-in_Deposit,0)) | F81: =$B$9*$B$7*(IF(EOMONTH(in_PODate,0)=EOMONTH(F$23,0),in_Deposit,0)+IF(EOMONTH(in_BalanceDate,0)=EOMONTH(F$23,0),1-in_Deposit,0)) | G81: =$B$9*$B$7*(IF(EOMONTH(in_PODate,0)=EOMONTH(G$23,0),in_Deposit,0)+IF(EOMONTH(in_BalanceDate,0)=EOMONTH(G$23,0),1-in_Deposit,0)) | H81: =$B$9*$B$7*(IF(EOMONTH(in_PODate,0)=EOMONTH(H$23,0),in_Deposit,0)+IF(EOMONTH(in_BalanceDate,0)=EOMONTH(H$23,0),1-in_Deposit,0)) | I81: =$B$9*$B$7*(IF(EOMONTH(in_PODate,0)=EOMONTH(I$23,0),in_Deposit,0)+IF(EOMONTH(in_BalanceDate,0)=EOMONTH(I$23,0),1-in_Deposit,0)) | J81: =$B$9*$B$7*(IF(EOMONTH(in_PODate,0)=EOMONTH(J$23,0),in_Deposit,0)+IF(EOMONTH(in_BalanceDate,0)=EOMONTH(J$23,0),1-in_Deposit,0)) | ... Q81: =$B$9*$B$7*(IF(EOMONTH(in_PODate,0)=EOMONTH(Q$23,0),in_Deposit,0)+IF(EOMONTH(in_BalanceDate,0)=EOMONTH(Q$23,0),1-in_Deposit,0)) | R81: =SUM(C81:Q81)
A82: Second flavour first run | C82: =C49*$B$6 | D82: =D49*$B$6 | E82: =E49*$B$6 | F82: =F49*$B$6 | G82: =G49*$B$6 | H82: =H49*$B$6 | I82: =I49*$B$6 | J82: =J49*$B$6 | ... Q82: =Q49*$B$6 | R82: =SUM(C82:Q82)
A83: Reorders placed (pouches and sticks, paid in full when placed) | C83: =C52*$B$6+C63*$B$7 | D83: =D52*$B$6+D63*$B$7 | E83: =E52*$B$6+E63*$B$7 | F83: =F52*$B$6+F63*$B$7 | G83: =G52*$B$6+G63*$B$7 | H83: =H52*$B$6+H63*$B$7 | I83: =I52*$B$6+I63*$B$7 | J83: =J52*$B$6+J63*$B$7 | ... Q83: =Q52*$B$6+Q63*$B$7 | R83: =SUM(C83:Q83)
A84: Total inventory purchases | C84: =SUM(C80:C83) | D84: =SUM(D80:D83) | E84: =SUM(E80:E83) | F84: =SUM(F80:F83) | G84: =SUM(G80:G83) | H84: =SUM(H80:H83) | I84: =SUM(I80:I83) | J84: =SUM(J80:J83) | ... Q84: =SUM(Q80:Q83) | R84: =SUM(C84:Q84)
A86: Variable costs (cash out)
A87: DTC shipping and packing | C87: =(C36+C37)*in_ShipOrder | D87: =(D36+D37)*in_ShipOrder | E87: =(E36+E37)*in_ShipOrder | F87: =(F36+F37)*in_ShipOrder | G87: =(G36+G37)*in_ShipOrder | H87: =(H36+H37)*in_ShipOrder | I87: =(I36+I37)*in_ShipOrder | J87: =(J36+J37)*in_ShipOrder | ... Q87: =(Q36+Q37)*in_ShipOrder | R87: =SUM(C87:Q87)
A88: Freight to stores | C88: =C42*in_FreightPouch+C43*in_FreightStick | D88: =D42*in_FreightPouch+D43*in_FreightStick | E88: =E42*in_FreightPouch+E43*in_FreightStick | F88: =F42*in_FreightPouch+F43*in_FreightStick | G88: =G42*in_FreightPouch+G43*in_FreightStick | H88: =H42*in_FreightPouch+H43*in_FreightStick | I88: =I42*in_FreightPouch+I43*in_FreightStick | J88: =J42*in_FreightPouch+J43*in_FreightStick | ... Q88: =Q42*in_FreightPouch+Q43*in_FreightStick | R88: =SUM(C88:Q88)
A89: Card fees | C89: =C74*in_CardPct+(C36+C37)*in_CardFixed | D89: =D74*in_CardPct+(D36+D37)*in_CardFixed | E89: =E74*in_CardPct+(E36+E37)*in_CardFixed | F89: =F74*in_CardPct+(F36+F37)*in_CardFixed | G89: =G74*in_CardPct+(G36+G37)*in_CardFixed | H89: =H74*in_CardPct+(H36+H37)*in_CardFixed | I89: =I74*in_CardPct+(I36+I37)*in_CardFixed | J89: =J74*in_CardPct+(J36+J37)*in_CardFixed | ... Q89: =Q74*in_CardPct+(Q36+Q37)*in_CardFixed | R89: =SUM(C89:Q89)
A90: Founding offer free shakers | C90: =C27*in_ShakerCost | D90: =D27*in_ShakerCost | E90: =E27*in_ShakerCost | F90: =F27*in_ShakerCost | G90: =G27*in_ShakerCost | H90: =H27*in_ShakerCost | I90: =I27*in_ShakerCost | J90: =J27*in_ShakerCost | ... Q90: =Q27*in_ShakerCost | R90: =SUM(C90:Q90)
A91: Total variable costs | C91: =SUM(C87:C90) | D91: =SUM(D87:D90) | E91: =SUM(E87:E90) | F91: =SUM(F87:F90) | G91: =SUM(G87:G90) | H91: =SUM(H87:H90) | I91: =SUM(I87:I90) | J91: =SUM(J87:J90) | ... Q91: =SUM(Q87:Q90) | R91: =SUM(C91:Q91)
A93: Marketing (cash out)
A94: Paid acquisition (paid new customers x CAC) | C94: =C29*in_CAC | D94: =D29*in_CAC | E94: =E29*in_CAC | F94: =F29*in_CAC | G94: =G29*in_CAC | H94: =H29*in_CAC | I94: =I29*in_CAC | J94: =J29*in_CAC | ... Q94: =Q29*in_CAC | R94: =SUM(C94:Q94)
A95: Sampling and content | C95: =IF(C$23>=DATE(YEAR(in_SampleStart),MONTH(in_SampleStart),1),in_SampleBudget,0) | D95: =IF(D$23>=DATE(YEAR(in_SampleStart),MONTH(in_SampleStart),1),in_SampleBudget,0) | E95: =IF(E$23>=DATE(YEAR(in_SampleStart),MONTH(in_SampleStart),1),in_SampleBudget,0) | F95: =IF(F$23>=DATE(YEAR(in_SampleStart),MONTH(in_SampleStart),1),in_SampleBudget,0) | G95: =IF(G$23>=DATE(YEAR(in_SampleStart),MONTH(in_SampleStart),1),in_SampleBudget,0) | H95: =IF(H$23>=DATE(YEAR(in_SampleStart),MONTH(in_SampleStart),1),in_SampleBudget,0) | I95: =IF(I$23>=DATE(YEAR(in_SampleStart),MONTH(in_SampleStart),1),in_SampleBudget,0) | J95: =IF(J$23>=DATE(YEAR(in_SampleStart),MONTH(in_SampleStart),1),in_SampleBudget,0) | ... Q95: =IF(Q$23>=DATE(YEAR(in_SampleStart),MONTH(in_SampleStart),1),in_SampleBudget,0) | R95: =SUM(C95:Q95)
A96: Total marketing | C96: =C94+C95 | D96: =D94+D95 | E96: =E94+E95 | F96: =F94+F95 | G96: =G94+G95 | H96: =H94+H95 | I96: =I94+I95 | J96: =J94+J95 | ... Q96: =Q94+Q95 | R96: =SUM(C96:Q96)
A98: Fixed costs (cash out)
A99: Shopify Basic | C99: =IF(C$23>=DATE(YEAR(in_FxShopify_Start),MONTH(in_FxShopify_Start),1),in_FxShopify,0) | D99: =IF(D$23>=DATE(YEAR(in_FxShopify_Start),MONTH(in_FxShopify_Start),1),in_FxShopify,0) | E99: =IF(E$23>=DATE(YEAR(in_FxShopify_Start),MONTH(in_FxShopify_Start),1),in_FxShopify,0) | F99: =IF(F$23>=DATE(YEAR(in_FxShopify_Start),MONTH(in_FxShopify_Start),1),in_FxShopify,0) | G99: =IF(G$23>=DATE(YEAR(in_FxShopify_Start),MONTH(in_FxShopify_Start),1),in_FxShopify,0) | H99: =IF(H$23>=DATE(YEAR(in_FxShopify_Start),MONTH(in_FxShopify_Start),1),in_FxShopify,0) | I99: =IF(I$23>=DATE(YEAR(in_FxShopify_Start),MONTH(in_FxShopify_Start),1),in_FxShopify,0) | J99: =IF(J$23>=DATE(YEAR(in_FxShopify_Start),MONTH(in_FxShopify_Start),1),in_FxShopify,0) | ... Q99: =IF(Q$23>=DATE(YEAR(in_FxShopify_Start),MONTH(in_FxShopify_Start),1),in_FxShopify,0) | R99: =SUM(C99:Q99)
A100: Klaviyo email | C100: =IF(C$23>=DATE(YEAR(in_FxKlaviyo_Start),MONTH(in_FxKlaviyo_Start),1),in_FxKlaviyo,0) | D100: =IF(D$23>=DATE(YEAR(in_FxKlaviyo_Start),MONTH(in_FxKlaviyo_Start),1),in_FxKlaviyo,0) | E100: =IF(E$23>=DATE(YEAR(in_FxKlaviyo_Start),MONTH(in_FxKlaviyo_Start),1),in_FxKlaviyo,0) | F100: =IF(F$23>=DATE(YEAR(in_FxKlaviyo_Start),MONTH(in_FxKlaviyo_Start),1),in_FxKlaviyo,0) | G100: =IF(G$23>=DATE(YEAR(in_FxKlaviyo_Start),MONTH(in_FxKlaviyo_Start),1),in_FxKlaviyo,0) | H100: =IF(H$23>=DATE(YEAR(in_FxKlaviyo_Start),MONTH(in_FxKlaviyo_Start),1),in_FxKlaviyo,0) | I100: =IF(I$23>=DATE(YEAR(in_FxKlaviyo_Start),MONTH(in_FxKlaviyo_Start),1),in_FxKlaviyo,0) | J100: =IF(J$23>=DATE(YEAR(in_FxKlaviyo_Start),MONTH(in_FxKlaviyo_Start),1),in_FxKlaviyo,0) | ... Q100: =IF(Q$23>=DATE(YEAR(in_FxKlaviyo_Start),MONTH(in_FxKlaviyo_Start),1),in_FxKlaviyo,0) | R100: =SUM(C100:Q100)
A101: Product liability insurance | C101: =IF(C$23>=DATE(YEAR(in_FxInsurance_Start),MONTH(in_FxInsurance_Start),1),in_FxInsurance,0) | D101: =IF(D$23>=DATE(YEAR(in_FxInsurance_Start),MONTH(in_FxInsurance_Start),1),in_FxInsurance,0) | E101: =IF(E$23>=DATE(YEAR(in_FxInsurance_Start),MONTH(in_FxInsurance_Start),1),in_FxInsurance,0) | F101: =IF(F$23>=DATE(YEAR(in_FxInsurance_Start),MONTH(in_FxInsurance_Start),1),in_FxInsurance,0) | G101: =IF(G$23>=DATE(YEAR(in_FxInsurance_Start),MONTH(in_FxInsurance_Start),1),in_FxInsurance,0) | H101: =IF(H$23>=DATE(YEAR(in_FxInsurance_Start),MONTH(in_FxInsurance_Start),1),in_FxInsurance,0) | I101: =IF(I$23>=DATE(YEAR(in_FxInsurance_Start),MONTH(in_FxInsurance_Start),1),in_FxInsurance,0) | J101: =IF(J$23>=DATE(YEAR(in_FxInsurance_Start),MONTH(in_FxInsurance_Start),1),in_FxInsurance,0) | ... Q101: =IF(Q$23>=DATE(YEAR(in_FxInsurance_Start),MONTH(in_FxInsurance_Start),1),in_FxInsurance,0) | R101: =SUM(C101:Q101)
A102: Other software (SMS credits, apps) | C102: =IF(C$23>=DATE(YEAR(in_FxSoftware_Start),MONTH(in_FxSoftware_Start),1),in_FxSoftware,0) | D102: =IF(D$23>=DATE(YEAR(in_FxSoftware_Start),MONTH(in_FxSoftware_Start),1),in_FxSoftware,0) | E102: =IF(E$23>=DATE(YEAR(in_FxSoftware_Start),MONTH(in_FxSoftware_Start),1),in_FxSoftware,0) | F102: =IF(F$23>=DATE(YEAR(in_FxSoftware_Start),MONTH(in_FxSoftware_Start),1),in_FxSoftware,0) | G102: =IF(G$23>=DATE(YEAR(in_FxSoftware_Start),MONTH(in_FxSoftware_Start),1),in_FxSoftware,0) | H102: =IF(H$23>=DATE(YEAR(in_FxSoftware_Start),MONTH(in_FxSoftware_Start),1),in_FxSoftware,0) | I102: =IF(I$23>=DATE(YEAR(in_FxSoftware_Start),MONTH(in_FxSoftware_Start),1),in_FxSoftware,0) | J102: =IF(J$23>=DATE(YEAR(in_FxSoftware_Start),MONTH(in_FxSoftware_Start),1),in_FxSoftware,0) | ... Q102: =IF(Q$23>=DATE(YEAR(in_FxSoftware_Start),MONTH(in_FxSoftware_Start),1),in_FxSoftware,0) | R102: =SUM(C102:Q102)
A103: Bookkeeping | C103: =IF(C$23>=DATE(YEAR(in_FxBooks_Start),MONTH(in_FxBooks_Start),1),in_FxBooks,0) | D103: =IF(D$23>=DATE(YEAR(in_FxBooks_Start),MONTH(in_FxBooks_Start),1),in_FxBooks,0) | E103: =IF(E$23>=DATE(YEAR(in_FxBooks_Start),MONTH(in_FxBooks_Start),1),in_FxBooks,0) | F103: =IF(F$23>=DATE(YEAR(in_FxBooks_Start),MONTH(in_FxBooks_Start),1),in_FxBooks,0) | G103: =IF(G$23>=DATE(YEAR(in_FxBooks_Start),MONTH(in_FxBooks_Start),1),in_FxBooks,0) | H103: =IF(H$23>=DATE(YEAR(in_FxBooks_Start),MONTH(in_FxBooks_Start),1),in_FxBooks,0) | I103: =IF(I$23>=DATE(YEAR(in_FxBooks_Start),MONTH(in_FxBooks_Start),1),in_FxBooks,0) | J103: =IF(J$23>=DATE(YEAR(in_FxBooks_Start),MONTH(in_FxBooks_Start),1),in_FxBooks,0) | ... Q103: =IF(Q$23>=DATE(YEAR(in_FxBooks_Start),MONTH(in_FxBooks_Start),1),in_FxBooks,0) | R103: =SUM(C103:Q103)
A104: Amazon Professional plan | C104: =IF(C$23>=DATE(YEAR(in_FxAmazon_Start),MONTH(in_FxAmazon_Start),1),in_FxAmazon,0) | D104: =IF(D$23>=DATE(YEAR(in_FxAmazon_Start),MONTH(in_FxAmazon_Start),1),in_FxAmazon,0) | E104: =IF(E$23>=DATE(YEAR(in_FxAmazon_Start),MONTH(in_FxAmazon_Start),1),in_FxAmazon,0) | F104: =IF(F$23>=DATE(YEAR(in_FxAmazon_Start),MONTH(in_FxAmazon_Start),1),in_FxAmazon,0) | G104: =IF(G$23>=DATE(YEAR(in_FxAmazon_Start),MONTH(in_FxAmazon_Start),1),in_FxAmazon,0) | H104: =IF(H$23>=DATE(YEAR(in_FxAmazon_Start),MONTH(in_FxAmazon_Start),1),in_FxAmazon,0) | I104: =IF(I$23>=DATE(YEAR(in_FxAmazon_Start),MONTH(in_FxAmazon_Start),1),in_FxAmazon,0) | J104: =IF(J$23>=DATE(YEAR(in_FxAmazon_Start),MONTH(in_FxAmazon_Start),1),in_FxAmazon,0) | ... Q104: =IF(Q$23>=DATE(YEAR(in_FxAmazon_Start),MONTH(in_FxAmazon_Start),1),in_FxAmazon,0) | R104: =SUM(C104:Q104)
A105: Total fixed costs | C105: =SUM(C99:C104) | D105: =SUM(D99:D104) | E105: =SUM(E99:E104) | F105: =SUM(F99:F104) | G105: =SUM(G99:G104) | H105: =SUM(H99:H104) | I105: =SUM(I99:I104) | J105: =SUM(J99:J104) | ... Q105: =SUM(Q99:Q104) | R105: =SUM(C105:Q105)
A107: One-time launch costs (cash out)
A108: Company, trademark, lawyer review, insurance setup | C108: =IF(EOMONTH(in_OtCompany_D,0)=EOMONTH(C$23,0),IF($B$3="Lean",in_OtCompany_L,in_OtCompany_S),0) | D108: =IF(EOMONTH(in_OtCompany_D,0)=EOMONTH(D$23,0),IF($B$3="Lean",in_OtCompany_L,in_OtCompany_S),0) | E108: =IF(EOMONTH(in_OtCompany_D,0)=EOMONTH(E$23,0),IF($B$3="Lean",in_OtCompany_L,in_OtCompany_S),0) | F108: =IF(EOMONTH(in_OtCompany_D,0)=EOMONTH(F$23,0),IF($B$3="Lean",in_OtCompany_L,in_OtCompany_S),0) | G108: =IF(EOMONTH(in_OtCompany_D,0)=EOMONTH(G$23,0),IF($B$3="Lean",in_OtCompany_L,in_OtCompany_S),0) | H108: =IF(EOMONTH(in_OtCompany_D,0)=EOMONTH(H$23,0),IF($B$3="Lean",in_OtCompany_L,in_OtCompany_S),0) | I108: =IF(EOMONTH(in_OtCompany_D,0)=EOMONTH(I$23,0),IF($B$3="Lean",in_OtCompany_L,in_OtCompany_S),0) | J108: =IF(EOMONTH(in_OtCompany_D,0)=EOMONTH(J$23,0),IF($B$3="Lean",in_OtCompany_L,in_OtCompany_S),0) | ... Q108: =IF(EOMONTH(in_OtCompany_D,0)=EOMONTH(Q$23,0),IF($B$3="Lean",in_OtCompany_L,in_OtCompany_S),0) | R108: =SUM(C108:Q108)
A109: Samples and flavour development (Strawberry) | C109: =IF(EOMONTH(in_OtSamples_D,0)=EOMONTH(C$23,0),IF($B$3="Lean",in_OtSamples_L,in_OtSamples_S),0) | D109: =IF(EOMONTH(in_OtSamples_D,0)=EOMONTH(D$23,0),IF($B$3="Lean",in_OtSamples_L,in_OtSamples_S),0) | E109: =IF(EOMONTH(in_OtSamples_D,0)=EOMONTH(E$23,0),IF($B$3="Lean",in_OtSamples_L,in_OtSamples_S),0) | F109: =IF(EOMONTH(in_OtSamples_D,0)=EOMONTH(F$23,0),IF($B$3="Lean",in_OtSamples_L,in_OtSamples_S),0) | G109: =IF(EOMONTH(in_OtSamples_D,0)=EOMONTH(G$23,0),IF($B$3="Lean",in_OtSamples_L,in_OtSamples_S),0) | H109: =IF(EOMONTH(in_OtSamples_D,0)=EOMONTH(H$23,0),IF($B$3="Lean",in_OtSamples_L,in_OtSamples_S),0) | I109: =IF(EOMONTH(in_OtSamples_D,0)=EOMONTH(I$23,0),IF($B$3="Lean",in_OtSamples_L,in_OtSamples_S),0) | J109: =IF(EOMONTH(in_OtSamples_D,0)=EOMONTH(J$23,0),IF($B$3="Lean",in_OtSamples_L,in_OtSamples_S),0) | ... Q109: =IF(EOMONTH(in_OtSamples_D,0)=EOMONTH(Q$23,0),IF($B$3="Lean",in_OtSamples_L,in_OtSamples_S),0) | R109: =SUM(C109:Q109)
A110: Label and regulatory review | C110: =IF(EOMONTH(in_OtLabel_D,0)=EOMONTH(C$23,0),IF($B$3="Lean",in_OtLabel_L,in_OtLabel_S),0) | D110: =IF(EOMONTH(in_OtLabel_D,0)=EOMONTH(D$23,0),IF($B$3="Lean",in_OtLabel_L,in_OtLabel_S),0) | E110: =IF(EOMONTH(in_OtLabel_D,0)=EOMONTH(E$23,0),IF($B$3="Lean",in_OtLabel_L,in_OtLabel_S),0) | F110: =IF(EOMONTH(in_OtLabel_D,0)=EOMONTH(F$23,0),IF($B$3="Lean",in_OtLabel_L,in_OtLabel_S),0) | G110: =IF(EOMONTH(in_OtLabel_D,0)=EOMONTH(G$23,0),IF($B$3="Lean",in_OtLabel_L,in_OtLabel_S),0) | H110: =IF(EOMONTH(in_OtLabel_D,0)=EOMONTH(H$23,0),IF($B$3="Lean",in_OtLabel_L,in_OtLabel_S),0) | I110: =IF(EOMONTH(in_OtLabel_D,0)=EOMONTH(I$23,0),IF($B$3="Lean",in_OtLabel_L,in_OtLabel_S),0) | J110: =IF(EOMONTH(in_OtLabel_D,0)=EOMONTH(J$23,0),IF($B$3="Lean",in_OtLabel_L,in_OtLabel_S),0) | ... Q110: =IF(EOMONTH(in_OtLabel_D,0)=EOMONTH(Q$23,0),IF($B$3="Lean",in_OtLabel_L,in_OtLabel_S),0) | R110: =SUM(C110:Q110)
A111: Launch kit: shakers, display, sampling supplies, apps | C111: =IF(EOMONTH(in_OtKit_D,0)=EOMONTH(C$23,0),IF($B$3="Lean",in_OtKit_L,in_OtKit_S),0) | D111: =IF(EOMONTH(in_OtKit_D,0)=EOMONTH(D$23,0),IF($B$3="Lean",in_OtKit_L,in_OtKit_S),0) | E111: =IF(EOMONTH(in_OtKit_D,0)=EOMONTH(E$23,0),IF($B$3="Lean",in_OtKit_L,in_OtKit_S),0) | F111: =IF(EOMONTH(in_OtKit_D,0)=EOMONTH(F$23,0),IF($B$3="Lean",in_OtKit_L,in_OtKit_S),0) | G111: =IF(EOMONTH(in_OtKit_D,0)=EOMONTH(G$23,0),IF($B$3="Lean",in_OtKit_L,in_OtKit_S),0) | H111: =IF(EOMONTH(in_OtKit_D,0)=EOMONTH(H$23,0),IF($B$3="Lean",in_OtKit_L,in_OtKit_S),0) | I111: =IF(EOMONTH(in_OtKit_D,0)=EOMONTH(I$23,0),IF($B$3="Lean",in_OtKit_L,in_OtKit_S),0) | J111: =IF(EOMONTH(in_OtKit_D,0)=EOMONTH(J$23,0),IF($B$3="Lean",in_OtKit_L,in_OtKit_S),0) | ... Q111: =IF(EOMONTH(in_OtKit_D,0)=EOMONTH(Q$23,0),IF($B$3="Lean",in_OtKit_L,in_OtKit_S),0) | R111: =SUM(C111:Q111)
A112: Real Fruit Hydration sticks (development and first run) | C112: =IF(EOMONTH(in_OtHydra_D,0)=EOMONTH(C$23,0),IF($B$3="Lean",in_OtHydra_L,in_OtHydra_S),0)*in_HydraOn | D112: =IF(EOMONTH(in_OtHydra_D,0)=EOMONTH(D$23,0),IF($B$3="Lean",in_OtHydra_L,in_OtHydra_S),0)*in_HydraOn | E112: =IF(EOMONTH(in_OtHydra_D,0)=EOMONTH(E$23,0),IF($B$3="Lean",in_OtHydra_L,in_OtHydra_S),0)*in_HydraOn | F112: =IF(EOMONTH(in_OtHydra_D,0)=EOMONTH(F$23,0),IF($B$3="Lean",in_OtHydra_L,in_OtHydra_S),0)*in_HydraOn | G112: =IF(EOMONTH(in_OtHydra_D,0)=EOMONTH(G$23,0),IF($B$3="Lean",in_OtHydra_L,in_OtHydra_S),0)*in_HydraOn | H112: =IF(EOMONTH(in_OtHydra_D,0)=EOMONTH(H$23,0),IF($B$3="Lean",in_OtHydra_L,in_OtHydra_S),0)*in_HydraOn | I112: =IF(EOMONTH(in_OtHydra_D,0)=EOMONTH(I$23,0),IF($B$3="Lean",in_OtHydra_L,in_OtHydra_S),0)*in_HydraOn | J112: =IF(EOMONTH(in_OtHydra_D,0)=EOMONTH(J$23,0),IF($B$3="Lean",in_OtHydra_L,in_OtHydra_S),0)*in_HydraOn | ... Q112: =IF(EOMONTH(in_OtHydra_D,0)=EOMONTH(Q$23,0),IF($B$3="Lean",in_OtHydra_L,in_OtHydra_S),0)*in_HydraOn | R112: =SUM(C112:Q112)
...

Sheet calc_Lean_High
A1: Calculation copy: Lean runs, High demand (feeds Scenarios; do not edit)
A2: Months Oct 2026 to Dec 2027. All figures are projections from the Inputs sheet, not actual results. Cash view: inventory is a cash outflow when bought; COGS appears only in the operating view at the bottom.
A3: Run-size mode | B3: ="Lean"
A4: Demand multiplier | B4: =in_MultHigh
A5: Demand case | B5: ="High"
A6: Pouch cost of goods (by mode) | B6: =IF($B$3="Lean",in_CogsLean,in_CogsStd)
A7: Stick cost of goods (by mode) | B7: =IF($B$3="Lean",in_StickCogsLean,in_StickCogsStd)
A8: Pouch run size (by mode) | B8: =IF($B$3="Lean",in_RunLean,in_RunStd)
A9: Stick run size (by mode) | B9: =IF($B$3="Lean",in_StickRunLean,in_StickRunStd)
A10: Sample credit on first order (by mode) | B10: =IF($B$3="Lean",in_SampleCreditLean,in_SampleCreditStd)
A12: Summary for this sheet's mode and case
A13: Lowest cash balance | B13: =MIN($C$120:$Q$120)
A14: Month of lowest cash balance | B14: =INDEX($C$23:$Q$23,MATCH(MIN($C$120:$Q$120),$C$120:$Q$120,0))
A15: Peak funding need (lowest cumulative net cash flow) | B15: =MIN(0,MIN($C$119:$Q$119))
A16: Operating break-even month (first month operating profit >= 0) | B16: =IFERROR(INDEX($C$23:$Q$23,MATCH(1,$C$127:$Q$127,0)),"Not by Dec 2027")
A17: Cash payback month (cumulative net cash flow back to >= 0) | B17: =IFERROR(INDEX($C$23:$Q$23,MATCH(1,$C$128:$Q$128,0)),"Not by Dec 2027")
A18: Cash balance, end of Jun 2027 | B18: =IFERROR(INDEX($C$120:$Q$120,MATCH(DATE(2027,6,1),$C$23:$Q$23,0)),"n/a")
A19: Cash balance, end of Dec 2027 | B19: =IFERROR(INDEX($C$120:$Q$120,MATCH(DATE(2027,12,1),$C$23:$Q$23,0)),"n/a")
A20: Stockout check (pouch + stick units short; should be 0) | B20: =SUM($C$54:$Q$54)+SUM($C$65:$Q$65)
A21: Operating profit, Oct 2026 to Dec 2027 (launch costs excluded) | B21: =SUM($C$126:$Q$126)
A23: Line | B23: Note | C23: =DATE(YEAR(in_ModelStart),MONTH(in_ModelStart),1) | D23: =EDATE(C23,1) | E23: =EDATE(D23,1) | F23: =EDATE(E23,1) | G23: =EDATE(F23,1) | H23: =EDATE(G23,1) | I23: =EDATE(H23,1) | J23: =EDATE(I23,1) | K23: =EDATE(J23,1) | ... Q23: =EDATE(P23,1) | R23: Total
A24: Selling? (1 from the first ship month) | C24: =IF(C$23>=DATE(YEAR(in_FirstShip),MONTH(in_FirstShip),1),1,0) | D24: =IF(D$23>=DATE(YEAR(in_FirstShip),MONTH(in_FirstShip),1),1,0) | E24: =IF(E$23>=DATE(YEAR(in_FirstShip),MONTH(in_FirstShip),1),1,0) | F24: =IF(F$23>=DATE(YEAR(in_FirstShip),MONTH(in_FirstShip),1),1,0) | G24: =IF(G$23>=DATE(YEAR(in_FirstShip),MONTH(in_FirstShip),1),1,0) | H24: =IF(H$23>=DATE(YEAR(in_FirstShip),MONTH(in_FirstShip),1),1,0) | I24: =IF(I$23>=DATE(YEAR(in_FirstShip),MONTH(in_FirstShip),1),1,0) | J24: =IF(J$23>=DATE(YEAR(in_FirstShip),MONTH(in_FirstShip),1),1,0) | ... Q24: =IF(Q$23>=DATE(YEAR(in_FirstShip),MONTH(in_FirstShip),1),1,0)
A26: DTC customers and orders
A27: Waitlist first orders (first ship month only) | B27: Waitlist x conversion | C27: =IF(EOMONTH(in_FirstShip,0)=EOMONTH(C$23,0),in_WaitSize*in_WaitConv*$B$4,0) | D27: =IF(EOMONTH(in_FirstShip,0)=EOMONTH(D$23,0),in_WaitSize*in_WaitConv*$B$4,0) | E27: =IF(EOMONTH(in_FirstShip,0)=EOMONTH(E$23,0),in_WaitSize*in_WaitConv*$B$4,0) | F27: =IF(EOMONTH(in_FirstShip,0)=EOMONTH(F$23,0),in_WaitSize*in_WaitConv*$B$4,0) | G27: =IF(EOMONTH(in_FirstShip,0)=EOMONTH(G$23,0),in_WaitSize*in_WaitConv*$B$4,0) | H27: =IF(EOMONTH(in_FirstShip,0)=EOMONTH(H$23,0),in_WaitSize*in_WaitConv*$B$4,0) | I27: =IF(EOMONTH(in_FirstShip,0)=EOMONTH(I$23,0),in_WaitSize*in_WaitConv*$B$4,0) | J27: =IF(EOMONTH(in_FirstShip,0)=EOMONTH(J$23,0),in_WaitSize*in_WaitConv*$B$4,0) | ... Q27: =IF(EOMONTH(in_FirstShip,0)=EOMONTH(Q$23,0),in_WaitSize*in_WaitConv*$B$4,0) | R27: =SUM(C27:Q27)
A28: Organic new customers | C28: =IFERROR(INDEX(Inputs!$B$98:$B$107,MATCH(C$23,Inputs!$A$98:$A$107,0)),0)*$B$4*C24 | D28: =IFERROR(INDEX(Inputs!$B$98:$B$107,MATCH(D$23,Inputs!$A$98:$A$107,0)),0)*$B$4*D24 | E28: =IFERROR(INDEX(Inputs!$B$98:$B$107,MATCH(E$23,Inputs!$A$98:$A$107,0)),0)*$B$4*E24 | F28: =IFERROR(INDEX(Inputs!$B$98:$B$107,MATCH(F$23,Inputs!$A$98:$A$107,0)),0)*$B$4*F24 | G28: =IFERROR(INDEX(Inputs!$B$98:$B$107,MATCH(G$23,Inputs!$A$98:$A$107,0)),0)*$B$4*G24 | H28: =IFERROR(INDEX(Inputs!$B$98:$B$107,MATCH(H$23,Inputs!$A$98:$A$107,0)),0)*$B$4*H24 | I28: =IFERROR(INDEX(Inputs!$B$98:$B$107,MATCH(I$23,Inputs!$A$98:$A$107,0)),0)*$B$4*I24 | J28: =IFERROR(INDEX(Inputs!$B$98:$B$107,MATCH(J$23,Inputs!$A$98:$A$107,0)),0)*$B$4*J24 | ... Q28: =IFERROR(INDEX(Inputs!$B$98:$B$107,MATCH(Q$23,Inputs!$A$98:$A$107,0)),0)*$B$4*Q24 | R28: =SUM(C28:Q28)
A29: Paid new customers | C29: =IFERROR(INDEX(Inputs!$C$98:$C$107,MATCH(C$23,Inputs!$A$98:$A$107,0)),0)*$B$4*C24 | D29: =IFERROR(INDEX(Inputs!$C$98:$C$107,MATCH(D$23,Inputs!$A$98:$A$107,0)),0)*$B$4*D24 | E29: =IFERROR(INDEX(Inputs!$C$98:$C$107,MATCH(E$23,Inputs!$A$98:$A$107,0)),0)*$B$4*E24 | F29: =IFERROR(INDEX(Inputs!$C$98:$C$107,MATCH(F$23,Inputs!$A$98:$A$107,0)),0)*$B$4*F24 | G29: =IFERROR(INDEX(Inputs!$C$98:$C$107,MATCH(G$23,Inputs!$A$98:$A$107,0)),0)*$B$4*G24 | H29: =IFERROR(INDEX(Inputs!$C$98:$C$107,MATCH(H$23,Inputs!$A$98:$A$107,0)),0)*$B$4*H24 | I29: =IFERROR(INDEX(Inputs!$C$98:$C$107,MATCH(I$23,Inputs!$A$98:$A$107,0)),0)*$B$4*I24 | J29: =IFERROR(INDEX(Inputs!$C$98:$C$107,MATCH(J$23,Inputs!$A$98:$A$107,0)),0)*$B$4*J24 | ... Q29: =IFERROR(INDEX(Inputs!$C$98:$C$107,MATCH(Q$23,Inputs!$A$98:$A$107,0)),0)*$B$4*Q24 | R29: =SUM(C29:Q29)
A30: Total new DTC customers | C30: =C27+C28+C29 | D30: =D27+D28+D29 | E30: =E27+E28+E29 | F30: =F27+F28+F29 | G30: =G27+G28+G29 | H30: =H27+H28+H29 | I30: =I27+I28+I29 | J30: =J27+J28+J29 | ... Q30: =Q27+Q28+Q29 | R30: =SUM(C30:Q30)
A31: New subscribers | C31: =C30*in_SubShare | D31: =D30*in_SubShare | E31: =E30*in_SubShare | F31: =F30*in_SubShare | G31: =G30*in_SubShare | H31: =H30*in_SubShare | I31: =I30*in_SubShare | J31: =J30*in_SubShare | ... Q31: =Q30*in_SubShare | R31: =SUM(C31:Q31)
A32: Active subscribers, end of month (= subscription orders) | B32: 1 pouch/month each | C32: =C31 | D32: =C32*(1-in_SubChurn)+D31 | E32: =D32*(1-in_SubChurn)+E31 | F32: =E32*(1-in_SubChurn)+F31 | G32: =F32*(1-in_SubChurn)+G31 | H32: =G32*(1-in_SubChurn)+H31 | I32: =H32*(1-in_SubChurn)+I31 | J32: =I32*(1-in_SubChurn)+J31 | K32: =J32*(1-in_SubChurn)+K31 | ... Q32: =P32*(1-in_SubChurn)+Q31
A33: One-off first orders | C33: =C30*(1-in_SubShare) | D33: =D30*(1-in_SubShare) | E33: =E30*(1-in_SubShare) | F33: =F30*(1-in_SubShare) | G33: =G30*(1-in_SubShare) | H33: =H30*(1-in_SubShare) | I33: =I30*(1-in_SubShare) | J33: =J30*(1-in_SubShare) | ... Q33: =Q30*(1-in_SubShare) | R33: =SUM(C33:Q33)
A34: One-off repeat orders | C34: =0 | D34: =C35*in_Repeat | E34: =D35*in_Repeat | F34: =E35*in_Repeat | G34: =F35*in_Repeat | H34: =G35*in_Repeat | I34: =H35*in_Repeat | J34: =I35*in_Repeat | K34: =J35*in_Repeat | ... Q34: =P35*in_Repeat | R34: =SUM(C34:Q34)
A35: Total one-off pouch orders | C35: =C33+C34 | D35: =D33+D34 | E35: =E33+E34 | F35: =F33+F34 | G35: =G33+G34 | H35: =H33+H34 | I35: =I33+I34 | J35: =J33+J34 | ... Q35: =Q33+Q34 | R35: =SUM(C35:Q35)
A36: Total DTC pouch orders (one-off + subscription) | C36: =C35+C32 | D36: =D35+D32 | E36: =E35+E32 | F36: =F35+F32 | G36: =G35+G32 | H36: =H35+H32 | I36: =I35+I32 | J36: =J35+J32 | ... Q36: =Q35+Q32 | R36: =SUM(C36:Q36)
A37: DTC stick-box orders | C37: =C36*in_StickAttach | D37: =D36*in_StickAttach | E37: =E36*in_StickAttach | F37: =F36*in_StickAttach | G37: =G36*in_StickAttach | H37: =H36*in_StickAttach | I37: =I36*in_StickAttach | J37: =J36*in_StickAttach | ... Q37: =Q36*in_StickAttach | R37: =SUM(C37:Q37)
A39: Wholesale (direct to stores)
A40: New store accounts | C40: =IFERROR(INDEX(Inputs!$D$98:$D$107,MATCH(C$23,Inputs!$A$98:$A$107,0)),0)*$B$4*C24 | D40: =IFERROR(INDEX(Inputs!$D$98:$D$107,MATCH(D$23,Inputs!$A$98:$A$107,0)),0)*$B$4*D24 | E40: =IFERROR(INDEX(Inputs!$D$98:$D$107,MATCH(E$23,Inputs!$A$98:$A$107,0)),0)*$B$4*E24 | F40: =IFERROR(INDEX(Inputs!$D$98:$D$107,MATCH(F$23,Inputs!$A$98:$A$107,0)),0)*$B$4*F24 | G40: =IFERROR(INDEX(Inputs!$D$98:$D$107,MATCH(G$23,Inputs!$A$98:$A$107,0)),0)*$B$4*G24 | H40: =IFERROR(INDEX(Inputs!$D$98:$D$107,MATCH(H$23,Inputs!$A$98:$A$107,0)),0)*$B$4*H24 | I40: =IFERROR(INDEX(Inputs!$D$98:$D$107,MATCH(I$23,Inputs!$A$98:$A$107,0)),0)*$B$4*I24 | J40: =IFERROR(INDEX(Inputs!$D$98:$D$107,MATCH(J$23,Inputs!$A$98:$A$107,0)),0)*$B$4*J24 | ... Q40: =IFERROR(INDEX(Inputs!$D$98:$D$107,MATCH(Q$23,Inputs!$A$98:$A$107,0)),0)*$B$4*Q24 | R40: =SUM(C40:Q40)
A41: Active store accounts, end of month | C41: =C40 | D41: =C41*(1-in_StoreChurn)+D40 | E41: =D41*(1-in_StoreChurn)+E40 | F41: =E41*(1-in_StoreChurn)+F40 | G41: =F41*(1-in_StoreChurn)+G40 | H41: =G41*(1-in_StoreChurn)+H40 | I41: =H41*(1-in_StoreChurn)+I40 | J41: =I41*(1-in_StoreChurn)+J40 | K41: =J41*(1-in_StoreChurn)+K40 | ... Q41: =P41*(1-in_StoreChurn)+Q40
A42: Wholesale pouches shipped | C42: =C41*in_PouchPerStore | D42: =D41*in_PouchPerStore | E42: =E41*in_PouchPerStore | F42: =F41*in_PouchPerStore | G42: =G41*in_PouchPerStore | H42: =H41*in_PouchPerStore | I42: =I41*in_PouchPerStore | J42: =J41*in_PouchPerStore | ... Q42: =Q41*in_PouchPerStore | R42: =SUM(C42:Q42)
A43: Wholesale sticks shipped | C43: =C41*in_StickPerStore | D43: =D41*in_StickPerStore | E43: =E41*in_StickPerStore | F43: =F41*in_StickPerStore | G43: =G41*in_StickPerStore | H43: =H41*in_StickPerStore | I43: =I41*in_StickPerStore | J43: =J41*in_StickPerStore | ... Q43: =Q41*in_StickPerStore | R43: =SUM(C43:Q43)
A45: Pouch inventory (units)
A46: Pouch demand | C46: =C36*in_PouchPerOrder+C42 | D46: =D36*in_PouchPerOrder+D42 | E46: =E36*in_PouchPerOrder+E42 | F46: =F36*in_PouchPerOrder+F42 | G46: =G36*in_PouchPerOrder+G42 | H46: =H36*in_PouchPerOrder+H42 | I46: =I36*in_PouchPerOrder+I42 | J46: =J36*in_PouchPerOrder+J42 | ... Q46: =Q36*in_PouchPerOrder+Q42 | R46: =SUM(C46:Q46)
A47: Opening stock | C47: =0 | D47: =C55 | E47: =D55 | F47: =E55 | G47: =F55 | H47: =G55 | I47: =H55 | J47: =I55 | K47: =J55 | ... Q47: =P55
A48: First run received | C48: =IF(EOMONTH(in_FirstShip,0)=EOMONTH(C$23,0),$B$8,0) | D48: =IF(EOMONTH(in_FirstShip,0)=EOMONTH(D$23,0),$B$8,0) | E48: =IF(EOMONTH(in_FirstShip,0)=EOMONTH(E$23,0),$B$8,0) | F48: =IF(EOMONTH(in_FirstShip,0)=EOMONTH(F$23,0),$B$8,0) | G48: =IF(EOMONTH(in_FirstShip,0)=EOMONTH(G$23,0),$B$8,0) | H48: =IF(EOMONTH(in_FirstShip,0)=EOMONTH(H$23,0),$B$8,0) | I48: =IF(EOMONTH(in_FirstShip,0)=EOMONTH(I$23,0),$B$8,0) | J48: =IF(EOMONTH(in_FirstShip,0)=EOMONTH(J$23,0),$B$8,0) | ... Q48: =IF(EOMONTH(in_FirstShip,0)=EOMONTH(Q$23,0),$B$8,0) | R48: =SUM(C48:Q48)
A49: Second flavour first run received | C49: =IF(AND(in_Flavor2On=1,EOMONTH(in_Flavor2Run,0)=EOMONTH(C$23,0)),$B$8,0) | D49: =IF(AND(in_Flavor2On=1,EOMONTH(in_Flavor2Run,0)=EOMONTH(D$23,0)),$B$8,0) | E49: =IF(AND(in_Flavor2On=1,EOMONTH(in_Flavor2Run,0)=EOMONTH(E$23,0)),$B$8,0) | F49: =IF(AND(in_Flavor2On=1,EOMONTH(in_Flavor2Run,0)=EOMONTH(F$23,0)),$B$8,0) | G49: =IF(AND(in_Flavor2On=1,EOMONTH(in_Flavor2Run,0)=EOMONTH(G$23,0)),$B$8,0) | H49: =IF(AND(in_Flavor2On=1,EOMONTH(in_Flavor2Run,0)=EOMONTH(H$23,0)),$B$8,0) | I49: =IF(AND(in_Flavor2On=1,EOMONTH(in_Flavor2Run,0)=EOMONTH(I$23,0)),$B$8,0) | J49: =IF(AND(in_Flavor2On=1,EOMONTH(in_Flavor2Run,0)=EOMONTH(J$23,0)),$B$8,0) | ... Q49: =IF(AND(in_Flavor2On=1,EOMONTH(in_Flavor2Run,0)=EOMONTH(Q$23,0)),$B$8,0) | R49: =SUM(C49:Q49)
A50: Reorders received (placed lead-time months earlier) | B50: Lead-time input | C50: =IF(in_Lead=1,0,IF(in_Lead=2,0,IF(in_Lead=3,0,0))) | D50: =IF(in_Lead=1,C52,IF(in_Lead=2,0,IF(in_Lead=3,0,0))) | E50: =IF(in_Lead=1,D52,IF(in_Lead=2,C52,IF(in_Lead=3,0,0))) | F50: =IF(in_Lead=1,E52,IF(in_Lead=2,D52,IF(in_Lead=3,C52,0))) | G50: =IF(in_Lead=1,F52,IF(in_Lead=2,E52,IF(in_Lead=3,D52,0))) | H50: =IF(in_Lead=1,G52,IF(in_Lead=2,F52,IF(in_Lead=3,E52,0))) | I50: =IF(in_Lead=1,H52,IF(in_Lead=2,G52,IF(in_Lead=3,F52,0))) | J50: =IF(in_Lead=1,I52,IF(in_Lead=2,H52,IF(in_Lead=3,G52,0))) | K50: =IF(in_Lead=1,J52,IF(in_Lead=2,I52,IF(in_Lead=3,H52,0))) | L50: =IF(in_Lead=1,K52,IF(in_Lead=2,J52,IF(in_Lead=3,I52,0))) | M50: =IF(in_Lead=1,L52,IF(in_Lead=2,K52,IF(in_Lead=3,J52,0))) | ... Q50: =IF(in_Lead=1,P52,IF(in_Lead=2,O52,IF(in_Lead=3,N52,0))) | R50: =SUM(C50:Q50)
A51: On order, still in transit after this month | C51: =IF(in_Lead>=2,0,0)+IF(in_Lead>=3,0,0) | D51: =IF(in_Lead>=2,C52,0)+IF(in_Lead>=3,0,0) | E51: =IF(in_Lead>=2,D52,0)+IF(in_Lead>=3,C52,0) | F51: =IF(in_Lead>=2,E52,0)+IF(in_Lead>=3,D52,0) | G51: =IF(in_Lead>=2,F52,0)+IF(in_Lead>=3,E52,0) | H51: =IF(in_Lead>=2,G52,0)+IF(in_Lead>=3,F52,0) | I51: =IF(in_Lead>=2,H52,0)+IF(in_Lead>=3,G52,0) | J51: =IF(in_Lead>=2,I52,0)+IF(in_Lead>=3,H52,0) | K51: =IF(in_Lead>=2,J52,0)+IF(in_Lead>=3,I52,0) | L51: =IF(in_Lead>=2,K52,0)+IF(in_Lead>=3,J52,0) | ... Q51: =IF(in_Lead>=2,P52,0)+IF(in_Lead>=3,O52,0)
A52: Reorder placed and paid (stock + on order below reorder point) | B52: Paid when placed | C52: =IF(C24=1,IF(C47+C48+C49+C50+C51<C46*in_Cover,ROUNDUP((C46*in_Cover-(C47+C48+C49+C50+C51))/$B$8,0)*$B$8,0),0) | D52: =IF(D24=1,IF(D47+D48+D49+D50+D51<D46*in_Cover,ROUNDUP((D46*in_Cover-(D47+D48+D49+D50+D51))/$B$8,0)*$B$8,0),0) | E52: =IF(E24=1,IF(E47+E48+E49+E50+E51<E46*in_Cover,ROUNDUP((E46*in_Cover-(E47+E48+E49+E50+E51))/$B$8,0)*$B$8,0),0) | F52: =IF(F24=1,IF(F47+F48+F49+F50+F51<F46*in_Cover,ROUNDUP((F46*in_Cover-(F47+F48+F49+F50+F51))/$B$8,0)*$B$8,0),0) | G52: =IF(G24=1,IF(G47+G48+G49+G50+G51<G46*in_Cover,ROUNDUP((G46*in_Cover-(G47+G48+G49+G50+G51))/$B$8,0)*$B$8,0),0) | H52: =IF(H24=1,IF(H47+H48+H49+H50+H51<H46*in_Cover,ROUNDUP((H46*in_Cover-(H47+H48+H49+H50+H51))/$B$8,0)*$B$8,0),0) | I52: =IF(I24=1,IF(I47+I48+I49+I50+I51<I46*in_Cover,ROUNDUP((I46*in_Cover-(I47+I48+I49+I50+I51))/$B$8,0)*$B$8,0),0) | J52: =IF(J24=1,IF(J47+J48+J49+J50+J51<J46*in_Cover,ROUNDUP((J46*in_Cover-(J47+J48+J49+J50+J51))/$B$8,0)*$B$8,0),0) | ... Q52: =IF(Q24=1,IF(Q47+Q48+Q49+Q50+Q51<Q46*in_Cover,ROUNDUP((Q46*in_Cover-(Q47+Q48+Q49+Q50+Q51))/$B$8,0)*$B$8,0),0) | R52: =SUM(C52:Q52)
A53: Pouches sold | C53: =MIN(C46,C47+C48+C49+C50) | D53: =MIN(D46,D47+D48+D49+D50) | E53: =MIN(E46,E47+E48+E49+E50) | F53: =MIN(F46,F47+F48+F49+F50) | G53: =MIN(G46,G47+G48+G49+G50) | H53: =MIN(H46,H47+H48+H49+H50) | I53: =MIN(I46,I47+I48+I49+I50) | J53: =MIN(J46,J47+J48+J49+J50) | ... Q53: =MIN(Q46,Q47+Q48+Q49+Q50) | R53: =SUM(C53:Q53)
A54: Pouch shortfall (check: should be 0) | B54: Must stay 0 | C54: =C46-C53 | D54: =D46-D53 | E54: =E46-E53 | F54: =F46-F53 | G54: =G46-G53 | H54: =H46-H53 | I54: =I46-I53 | J54: =J46-J53 | ... Q54: =Q46-Q53 | R54: =SUM(C54:Q54)
A55: Closing stock | C55: =C47+C48+C49+C50-C53 | D55: =D47+D48+D49+D50-D53 | E55: =E47+E48+E49+E50-E53 | F55: =F47+F48+F49+F50-F53 | G55: =G47+G48+G49+G50-G53 | H55: =H47+H48+H49+H50-H53 | I55: =I47+I48+I49+I50-I53 | J55: =J47+J48+J49+J50-J53 | ... Q55: =Q47+Q48+Q49+Q50-Q53
A57: Protein stick inventory (units)
A58: Stick demand | C58: =C37*in_SticksPerBox+C43 | D58: =D37*in_SticksPerBox+D43 | E58: =E37*in_SticksPerBox+E43 | F58: =F37*in_SticksPerBox+F43 | G58: =G37*in_SticksPerBox+G43 | H58: =H37*in_SticksPerBox+H43 | I58: =I37*in_SticksPerBox+I43 | J58: =J37*in_SticksPerBox+J43 | ... Q58: =Q37*in_SticksPerBox+Q43 | R58: =SUM(C58:Q58)
A59: Opening stock | C59: =0 | D59: =C66 | E59: =D66 | F59: =E66 | G59: =F66 | H59: =G66 | I59: =H66 | J59: =I66 | K59: =J66 | ... Q59: =P66
A60: First run received | C60: =IF(EOMONTH(in_FirstShip,0)=EOMONTH(C$23,0),$B$9,0) | D60: =IF(EOMONTH(in_FirstShip,0)=EOMONTH(D$23,0),$B$9,0) | E60: =IF(EOMONTH(in_FirstShip,0)=EOMONTH(E$23,0),$B$9,0) | F60: =IF(EOMONTH(in_FirstShip,0)=EOMONTH(F$23,0),$B$9,0) | G60: =IF(EOMONTH(in_FirstShip,0)=EOMONTH(G$23,0),$B$9,0) | H60: =IF(EOMONTH(in_FirstShip,0)=EOMONTH(H$23,0),$B$9,0) | I60: =IF(EOMONTH(in_FirstShip,0)=EOMONTH(I$23,0),$B$9,0) | J60: =IF(EOMONTH(in_FirstShip,0)=EOMONTH(J$23,0),$B$9,0) | ... Q60: =IF(EOMONTH(in_FirstShip,0)=EOMONTH(Q$23,0),$B$9,0) | R60: =SUM(C60:Q60)
A61: Reorders received (placed lead-time months earlier) | C61: =IF(in_Lead=1,0,IF(in_Lead=2,0,IF(in_Lead=3,0,0))) | D61: =IF(in_Lead=1,C63,IF(in_Lead=2,0,IF(in_Lead=3,0,0))) | E61: =IF(in_Lead=1,D63,IF(in_Lead=2,C63,IF(in_Lead=3,0,0))) | F61: =IF(in_Lead=1,E63,IF(in_Lead=2,D63,IF(in_Lead=3,C63,0))) | G61: =IF(in_Lead=1,F63,IF(in_Lead=2,E63,IF(in_Lead=3,D63,0))) | H61: =IF(in_Lead=1,G63,IF(in_Lead=2,F63,IF(in_Lead=3,E63,0))) | I61: =IF(in_Lead=1,H63,IF(in_Lead=2,G63,IF(in_Lead=3,F63,0))) | J61: =IF(in_Lead=1,I63,IF(in_Lead=2,H63,IF(in_Lead=3,G63,0))) | K61: =IF(in_Lead=1,J63,IF(in_Lead=2,I63,IF(in_Lead=3,H63,0))) | L61: =IF(in_Lead=1,K63,IF(in_Lead=2,J63,IF(in_Lead=3,I63,0))) | M61: =IF(in_Lead=1,L63,IF(in_Lead=2,K63,IF(in_Lead=3,J63,0))) | ... Q61: =IF(in_Lead=1,P63,IF(in_Lead=2,O63,IF(in_Lead=3,N63,0))) | R61: =SUM(C61:Q61)
A62: On order, still in transit after this month | C62: =IF(in_Lead>=2,0,0)+IF(in_Lead>=3,0,0) | D62: =IF(in_Lead>=2,C63,0)+IF(in_Lead>=3,0,0) | E62: =IF(in_Lead>=2,D63,0)+IF(in_Lead>=3,C63,0) | F62: =IF(in_Lead>=2,E63,0)+IF(in_Lead>=3,D63,0) | G62: =IF(in_Lead>=2,F63,0)+IF(in_Lead>=3,E63,0) | H62: =IF(in_Lead>=2,G63,0)+IF(in_Lead>=3,F63,0) | I62: =IF(in_Lead>=2,H63,0)+IF(in_Lead>=3,G63,0) | J62: =IF(in_Lead>=2,I63,0)+IF(in_Lead>=3,H63,0) | K62: =IF(in_Lead>=2,J63,0)+IF(in_Lead>=3,I63,0) | L62: =IF(in_Lead>=2,K63,0)+IF(in_Lead>=3,J63,0) | ... Q62: =IF(in_Lead>=2,P63,0)+IF(in_Lead>=3,O63,0)
A63: Reorder placed and paid | C63: =IF(C24=1,IF(C59+C60+C61+C62<C58*in_Cover,ROUNDUP((C58*in_Cover-(C59+C60+C61+C62))/$B$9,0)*$B$9,0),0) | D63: =IF(D24=1,IF(D59+D60+D61+D62<D58*in_Cover,ROUNDUP((D58*in_Cover-(D59+D60+D61+D62))/$B$9,0)*$B$9,0),0) | E63: =IF(E24=1,IF(E59+E60+E61+E62<E58*in_Cover,ROUNDUP((E58*in_Cover-(E59+E60+E61+E62))/$B$9,0)*$B$9,0),0) | F63: =IF(F24=1,IF(F59+F60+F61+F62<F58*in_Cover,ROUNDUP((F58*in_Cover-(F59+F60+F61+F62))/$B$9,0)*$B$9,0),0) | G63: =IF(G24=1,IF(G59+G60+G61+G62<G58*in_Cover,ROUNDUP((G58*in_Cover-(G59+G60+G61+G62))/$B$9,0)*$B$9,0),0) | H63: =IF(H24=1,IF(H59+H60+H61+H62<H58*in_Cover,ROUNDUP((H58*in_Cover-(H59+H60+H61+H62))/$B$9,0)*$B$9,0),0) | I63: =IF(I24=1,IF(I59+I60+I61+I62<I58*in_Cover,ROUNDUP((I58*in_Cover-(I59+I60+I61+I62))/$B$9,0)*$B$9,0),0) | J63: =IF(J24=1,IF(J59+J60+J61+J62<J58*in_Cover,ROUNDUP((J58*in_Cover-(J59+J60+J61+J62))/$B$9,0)*$B$9,0),0) | ... Q63: =IF(Q24=1,IF(Q59+Q60+Q61+Q62<Q58*in_Cover,ROUNDUP((Q58*in_Cover-(Q59+Q60+Q61+Q62))/$B$9,0)*$B$9,0),0) | R63: =SUM(C63:Q63)
A64: Sticks sold | C64: =MIN(C58,C59+C60+C61) | D64: =MIN(D58,D59+D60+D61) | E64: =MIN(E58,E59+E60+E61) | F64: =MIN(F58,F59+F60+F61) | G64: =MIN(G58,G59+G60+G61) | H64: =MIN(H58,H59+H60+H61) | I64: =MIN(I58,I59+I60+I61) | J64: =MIN(J58,J59+J60+J61) | ... Q64: =MIN(Q58,Q59+Q60+Q61) | R64: =SUM(C64:Q64)
A65: Stick shortfall (check: should be 0) | B65: Must stay 0 | C65: =C58-C64 | D65: =D58-D64 | E65: =E58-E64 | F65: =F58-F64 | G65: =G58-G64 | H65: =H58-H64 | I65: =I58-I64 | J65: =J58-J64 | ... Q65: =Q58-Q64 | R65: =SUM(C65:Q65)
A66: Closing stock | C66: =C59+C60+C61-C64 | D66: =D59+D60+D61-D64 | E66: =E59+E60+E61-E64 | F66: =F59+F60+F61-F64 | G66: =G59+G60+G61-G64 | H66: =H59+H60+H61-H64 | I66: =I59+I60+I61-I64 | J66: =J59+J60+J61-J64 | ... Q66: =Q59+Q60+Q61-Q64
A68: Cash in
A69: DTC one-off pouches | C69: =C35*in_PricePouch | D69: =D35*in_PricePouch | E69: =E35*in_PricePouch | F69: =F35*in_PricePouch | G69: =G35*in_PricePouch | H69: =H35*in_PricePouch | I69: =I35*in_PricePouch | J69: =J35*in_PricePouch | ... Q69: =Q35*in_PricePouch | R69: =SUM(C69:Q69)
A70: DTC subscription pouches | C70: =C32*in_PricePouch*(1-in_SubDisc) | D70: =D32*in_PricePouch*(1-in_SubDisc) | E70: =E32*in_PricePouch*(1-in_SubDisc) | F70: =F32*in_PricePouch*(1-in_SubDisc) | G70: =G32*in_PricePouch*(1-in_SubDisc) | H70: =H32*in_PricePouch*(1-in_SubDisc) | I70: =I32*in_PricePouch*(1-in_SubDisc) | J70: =J32*in_PricePouch*(1-in_SubDisc) | ... Q70: =Q32*in_PricePouch*(1-in_SubDisc) | R70: =SUM(C70:Q70)
A71: Founding offer discount (waitlist first orders) | C71: =-C27*in_PricePouch*in_FoundDisc | D71: =-D27*in_PricePouch*in_FoundDisc | E71: =-E27*in_PricePouch*in_FoundDisc | F71: =-F27*in_PricePouch*in_FoundDisc | G71: =-G27*in_PricePouch*in_FoundDisc | H71: =-H27*in_PricePouch*in_FoundDisc | I71: =-I27*in_PricePouch*in_FoundDisc | J71: =-J27*in_PricePouch*in_FoundDisc | ... Q71: =-Q27*in_PricePouch*in_FoundDisc | R71: =SUM(C71:Q71)
A72: DTC stick boxes | C72: =C37*in_PriceStickBox | D72: =D37*in_PriceStickBox | E72: =E37*in_PriceStickBox | F72: =F37*in_PriceStickBox | G72: =G37*in_PriceStickBox | H72: =H37*in_PriceStickBox | I72: =I37*in_PriceStickBox | J72: =J37*in_PriceStickBox | ... Q72: =Q37*in_PriceStickBox | R72: =SUM(C72:Q72)
A73: Shipping charged to customers | C73: =IF(in_FreeShip=1,0,(C36+C37)*in_ShipCharge) | D73: =IF(in_FreeShip=1,0,(D36+D37)*in_ShipCharge) | E73: =IF(in_FreeShip=1,0,(E36+E37)*in_ShipCharge) | F73: =IF(in_FreeShip=1,0,(F36+F37)*in_ShipCharge) | G73: =IF(in_FreeShip=1,0,(G36+G37)*in_ShipCharge) | H73: =IF(in_FreeShip=1,0,(H36+H37)*in_ShipCharge) | I73: =IF(in_FreeShip=1,0,(I36+I37)*in_ShipCharge) | J73: =IF(in_FreeShip=1,0,(J36+J37)*in_ShipCharge) | ... Q73: =IF(in_FreeShip=1,0,(Q36+Q37)*in_ShipCharge) | R73: =SUM(C73:Q73)
A74: DTC revenue | C74: =SUM(C69:C73) | D74: =SUM(D69:D73) | E74: =SUM(E69:E73) | F74: =SUM(F69:F73) | G74: =SUM(G69:G73) | H74: =SUM(H69:H73) | I74: =SUM(I69:I73) | J74: =SUM(J69:J73) | ... Q74: =SUM(Q69:Q73) | R74: =SUM(C74:Q74)
A75: Wholesale invoiced (pouches + sticks) | C75: =C42*in_WsPouch+C43*in_WsStick | D75: =D42*in_WsPouch+D43*in_WsStick | E75: =E42*in_WsPouch+E43*in_WsStick | F75: =F42*in_WsPouch+F43*in_WsStick | G75: =G42*in_WsPouch+G43*in_WsStick | H75: =H42*in_WsPouch+H43*in_WsStick | I75: =I42*in_WsPouch+I43*in_WsStick | J75: =J42*in_WsPouch+J43*in_WsStick | ... Q75: =Q42*in_WsPouch+Q43*in_WsStick | R75: =SUM(C75:Q75)
A76: Wholesale cash collected | B76: Net 30 toggle | C76: =IF(in_Net30=1,0,C75) | D76: =IF(in_Net30=1,C75,D75) | E76: =IF(in_Net30=1,D75,E75) | F76: =IF(in_Net30=1,E75,F75) | G76: =IF(in_Net30=1,F75,G75) | H76: =IF(in_Net30=1,G75,H75) | I76: =IF(in_Net30=1,H75,I75) | J76: =IF(in_Net30=1,I75,J75) | K76: =IF(in_Net30=1,J75,K75) | ... Q76: =IF(in_Net30=1,P75,Q75) | R76: =SUM(C76:Q76)
A77: Total cash in | C77: =C74+C76 | D77: =D74+D76 | E77: =E74+E76 | F77: =F74+F76 | G77: =G74+G76 | H77: =H74+H76 | I77: =I74+I76 | J77: =J74+J76 | ... Q77: =Q74+Q76 | R77: =SUM(C77:Q77)
A79: Inventory purchases (cash out)
A80: First pouch run (deposit, then balance; less sample credit) | B80: Mode-dependent | C80: =$B$8*$B$6*(IF(EOMONTH(in_PODate,0)=EOMONTH(C$23,0),in_Deposit,0)+IF(EOMONTH(in_BalanceDate,0)=EOMONTH(C$23,0),1-in_Deposit,0))-IF(EOMONTH(in_PODate,0)=EOMONTH(C$23,0),$B$10,0) | D80: =$B$8*$B$6*(IF(EOMONTH(in_PODate,0)=EOMONTH(D$23,0),in_Deposit,0)+IF(EOMONTH(in_BalanceDate,0)=EOMONTH(D$23,0),1-in_Deposit,0))-IF(EOMONTH(in_PODate,0)=EOMONTH(D$23,0),$B$10,0) | E80: =$B$8*$B$6*(IF(EOMONTH(in_PODate,0)=EOMONTH(E$23,0),in_Deposit,0)+IF(EOMONTH(in_BalanceDate,0)=EOMONTH(E$23,0),1-in_Deposit,0))-IF(EOMONTH(in_PODate,0)=EOMONTH(E$23,0),$B$10,0) | F80: =$B$8*$B$6*(IF(EOMONTH(in_PODate,0)=EOMONTH(F$23,0),in_Deposit,0)+IF(EOMONTH(in_BalanceDate,0)=EOMONTH(F$23,0),1-in_Deposit,0))-IF(EOMONTH(in_PODate,0)=EOMONTH(F$23,0),$B$10,0) | G80: =$B$8*$B$6*(IF(EOMONTH(in_PODate,0)=EOMONTH(G$23,0),in_Deposit,0)+IF(EOMONTH(in_BalanceDate,0)=EOMONTH(G$23,0),1-in_Deposit,0))-IF(EOMONTH(in_PODate,0)=EOMONTH(G$23,0),$B$10,0) | H80: =$B$8*$B$6*(IF(EOMONTH(in_PODate,0)=EOMONTH(H$23,0),in_Deposit,0)+IF(EOMONTH(in_BalanceDate,0)=EOMONTH(H$23,0),1-in_Deposit,0))-IF(EOMONTH(in_PODate,0)=EOMONTH(H$23,0),$B$10,0) | I80: =$B$8*$B$6*(IF(EOMONTH(in_PODate,0)=EOMONTH(I$23,0),in_Deposit,0)+IF(EOMONTH(in_BalanceDate,0)=EOMONTH(I$23,0),1-in_Deposit,0))-IF(EOMONTH(in_PODate,0)=EOMONTH(I$23,0),$B$10,0) | J80: =$B$8*$B$6*(IF(EOMONTH(in_PODate,0)=EOMONTH(J$23,0),in_Deposit,0)+IF(EOMONTH(in_BalanceDate,0)=EOMONTH(J$23,0),1-in_Deposit,0))-IF(EOMONTH(in_PODate,0)=EOMONTH(J$23,0),$B$10,0) | ... Q80: =$B$8*$B$6*(IF(EOMONTH(in_PODate,0)=EOMONTH(Q$23,0),in_Deposit,0)+IF(EOMONTH(in_BalanceDate,0)=EOMONTH(Q$23,0),1-in_Deposit,0))-IF(EOMONTH(in_PODate,0)=EOMONTH(Q$23,0),$B$10,0) | R80: =SUM(C80:Q80)
A81: First protein stick run (deposit, then balance) | C81: =$B$9*$B$7*(IF(EOMONTH(in_PODate,0)=EOMONTH(C$23,0),in_Deposit,0)+IF(EOMONTH(in_BalanceDate,0)=EOMONTH(C$23,0),1-in_Deposit,0)) | D81: =$B$9*$B$7*(IF(EOMONTH(in_PODate,0)=EOMONTH(D$23,0),in_Deposit,0)+IF(EOMONTH(in_BalanceDate,0)=EOMONTH(D$23,0),1-in_Deposit,0)) | E81: =$B$9*$B$7*(IF(EOMONTH(in_PODate,0)=EOMONTH(E$23,0),in_Deposit,0)+IF(EOMONTH(in_BalanceDate,0)=EOMONTH(E$23,0),1-in_Deposit,0)) | F81: =$B$9*$B$7*(IF(EOMONTH(in_PODate,0)=EOMONTH(F$23,0),in_Deposit,0)+IF(EOMONTH(in_BalanceDate,0)=EOMONTH(F$23,0),1-in_Deposit,0)) | G81: =$B$9*$B$7*(IF(EOMONTH(in_PODate,0)=EOMONTH(G$23,0),in_Deposit,0)+IF(EOMONTH(in_BalanceDate,0)=EOMONTH(G$23,0),1-in_Deposit,0)) | H81: =$B$9*$B$7*(IF(EOMONTH(in_PODate,0)=EOMONTH(H$23,0),in_Deposit,0)+IF(EOMONTH(in_BalanceDate,0)=EOMONTH(H$23,0),1-in_Deposit,0)) | I81: =$B$9*$B$7*(IF(EOMONTH(in_PODate,0)=EOMONTH(I$23,0),in_Deposit,0)+IF(EOMONTH(in_BalanceDate,0)=EOMONTH(I$23,0),1-in_Deposit,0)) | J81: =$B$9*$B$7*(IF(EOMONTH(in_PODate,0)=EOMONTH(J$23,0),in_Deposit,0)+IF(EOMONTH(in_BalanceDate,0)=EOMONTH(J$23,0),1-in_Deposit,0)) | ... Q81: =$B$9*$B$7*(IF(EOMONTH(in_PODate,0)=EOMONTH(Q$23,0),in_Deposit,0)+IF(EOMONTH(in_BalanceDate,0)=EOMONTH(Q$23,0),1-in_Deposit,0)) | R81: =SUM(C81:Q81)
A82: Second flavour first run | C82: =C49*$B$6 | D82: =D49*$B$6 | E82: =E49*$B$6 | F82: =F49*$B$6 | G82: =G49*$B$6 | H82: =H49*$B$6 | I82: =I49*$B$6 | J82: =J49*$B$6 | ... Q82: =Q49*$B$6 | R82: =SUM(C82:Q82)
A83: Reorders placed (pouches and sticks, paid in full when placed) | C83: =C52*$B$6+C63*$B$7 | D83: =D52*$B$6+D63*$B$7 | E83: =E52*$B$6+E63*$B$7 | F83: =F52*$B$6+F63*$B$7 | G83: =G52*$B$6+G63*$B$7 | H83: =H52*$B$6+H63*$B$7 | I83: =I52*$B$6+I63*$B$7 | J83: =J52*$B$6+J63*$B$7 | ... Q83: =Q52*$B$6+Q63*$B$7 | R83: =SUM(C83:Q83)
A84: Total inventory purchases | C84: =SUM(C80:C83) | D84: =SUM(D80:D83) | E84: =SUM(E80:E83) | F84: =SUM(F80:F83) | G84: =SUM(G80:G83) | H84: =SUM(H80:H83) | I84: =SUM(I80:I83) | J84: =SUM(J80:J83) | ... Q84: =SUM(Q80:Q83) | R84: =SUM(C84:Q84)
A86: Variable costs (cash out)
A87: DTC shipping and packing | C87: =(C36+C37)*in_ShipOrder | D87: =(D36+D37)*in_ShipOrder | E87: =(E36+E37)*in_ShipOrder | F87: =(F36+F37)*in_ShipOrder | G87: =(G36+G37)*in_ShipOrder | H87: =(H36+H37)*in_ShipOrder | I87: =(I36+I37)*in_ShipOrder | J87: =(J36+J37)*in_ShipOrder | ... Q87: =(Q36+Q37)*in_ShipOrder | R87: =SUM(C87:Q87)
A88: Freight to stores | C88: =C42*in_FreightPouch+C43*in_FreightStick | D88: =D42*in_FreightPouch+D43*in_FreightStick | E88: =E42*in_FreightPouch+E43*in_FreightStick | F88: =F42*in_FreightPouch+F43*in_FreightStick | G88: =G42*in_FreightPouch+G43*in_FreightStick | H88: =H42*in_FreightPouch+H43*in_FreightStick | I88: =I42*in_FreightPouch+I43*in_FreightStick | J88: =J42*in_FreightPouch+J43*in_FreightStick | ... Q88: =Q42*in_FreightPouch+Q43*in_FreightStick | R88: =SUM(C88:Q88)
A89: Card fees | C89: =C74*in_CardPct+(C36+C37)*in_CardFixed | D89: =D74*in_CardPct+(D36+D37)*in_CardFixed | E89: =E74*in_CardPct+(E36+E37)*in_CardFixed | F89: =F74*in_CardPct+(F36+F37)*in_CardFixed | G89: =G74*in_CardPct+(G36+G37)*in_CardFixed | H89: =H74*in_CardPct+(H36+H37)*in_CardFixed | I89: =I74*in_CardPct+(I36+I37)*in_CardFixed | J89: =J74*in_CardPct+(J36+J37)*in_CardFixed | ... Q89: =Q74*in_CardPct+(Q36+Q37)*in_CardFixed | R89: =SUM(C89:Q89)
A90: Founding offer free shakers | C90: =C27*in_ShakerCost | D90: =D27*in_ShakerCost | E90: =E27*in_ShakerCost | F90: =F27*in_ShakerCost | G90: =G27*in_ShakerCost | H90: =H27*in_ShakerCost | I90: =I27*in_ShakerCost | J90: =J27*in_ShakerCost | ... Q90: =Q27*in_ShakerCost | R90: =SUM(C90:Q90)
A91: Total variable costs | C91: =SUM(C87:C90) | D91: =SUM(D87:D90) | E91: =SUM(E87:E90) | F91: =SUM(F87:F90) | G91: =SUM(G87:G90) | H91: =SUM(H87:H90) | I91: =SUM(I87:I90) | J91: =SUM(J87:J90) | ... Q91: =SUM(Q87:Q90) | R91: =SUM(C91:Q91)
A93: Marketing (cash out)
A94: Paid acquisition (paid new customers x CAC) | C94: =C29*in_CAC | D94: =D29*in_CAC | E94: =E29*in_CAC | F94: =F29*in_CAC | G94: =G29*in_CAC | H94: =H29*in_CAC | I94: =I29*in_CAC | J94: =J29*in_CAC | ... Q94: =Q29*in_CAC | R94: =SUM(C94:Q94)
A95: Sampling and content | C95: =IF(C$23>=DATE(YEAR(in_SampleStart),MONTH(in_SampleStart),1),in_SampleBudget,0) | D95: =IF(D$23>=DATE(YEAR(in_SampleStart),MONTH(in_SampleStart),1),in_SampleBudget,0) | E95: =IF(E$23>=DATE(YEAR(in_SampleStart),MONTH(in_SampleStart),1),in_SampleBudget,0) | F95: =IF(F$23>=DATE(YEAR(in_SampleStart),MONTH(in_SampleStart),1),in_SampleBudget,0) | G95: =IF(G$23>=DATE(YEAR(in_SampleStart),MONTH(in_SampleStart),1),in_SampleBudget,0) | H95: =IF(H$23>=DATE(YEAR(in_SampleStart),MONTH(in_SampleStart),1),in_SampleBudget,0) | I95: =IF(I$23>=DATE(YEAR(in_SampleStart),MONTH(in_SampleStart),1),in_SampleBudget,0) | J95: =IF(J$23>=DATE(YEAR(in_SampleStart),MONTH(in_SampleStart),1),in_SampleBudget,0) | ... Q95: =IF(Q$23>=DATE(YEAR(in_SampleStart),MONTH(in_SampleStart),1),in_SampleBudget,0) | R95: =SUM(C95:Q95)
A96: Total marketing | C96: =C94+C95 | D96: =D94+D95 | E96: =E94+E95 | F96: =F94+F95 | G96: =G94+G95 | H96: =H94+H95 | I96: =I94+I95 | J96: =J94+J95 | ... Q96: =Q94+Q95 | R96: =SUM(C96:Q96)
A98: Fixed costs (cash out)
A99: Shopify Basic | C99: =IF(C$23>=DATE(YEAR(in_FxShopify_Start),MONTH(in_FxShopify_Start),1),in_FxShopify,0) | D99: =IF(D$23>=DATE(YEAR(in_FxShopify_Start),MONTH(in_FxShopify_Start),1),in_FxShopify,0) | E99: =IF(E$23>=DATE(YEAR(in_FxShopify_Start),MONTH(in_FxShopify_Start),1),in_FxShopify,0) | F99: =IF(F$23>=DATE(YEAR(in_FxShopify_Start),MONTH(in_FxShopify_Start),1),in_FxShopify,0) | G99: =IF(G$23>=DATE(YEAR(in_FxShopify_Start),MONTH(in_FxShopify_Start),1),in_FxShopify,0) | H99: =IF(H$23>=DATE(YEAR(in_FxShopify_Start),MONTH(in_FxShopify_Start),1),in_FxShopify,0) | I99: =IF(I$23>=DATE(YEAR(in_FxShopify_Start),MONTH(in_FxShopify_Start),1),in_FxShopify,0) | J99: =IF(J$23>=DATE(YEAR(in_FxShopify_Start),MONTH(in_FxShopify_Start),1),in_FxShopify,0) | ... Q99: =IF(Q$23>=DATE(YEAR(in_FxShopify_Start),MONTH(in_FxShopify_Start),1),in_FxShopify,0) | R99: =SUM(C99:Q99)
A100: Klaviyo email | C100: =IF(C$23>=DATE(YEAR(in_FxKlaviyo_Start),MONTH(in_FxKlaviyo_Start),1),in_FxKlaviyo,0) | D100: =IF(D$23>=DATE(YEAR(in_FxKlaviyo_Start),MONTH(in_FxKlaviyo_Start),1),in_FxKlaviyo,0) | E100: =IF(E$23>=DATE(YEAR(in_FxKlaviyo_Start),MONTH(in_FxKlaviyo_Start),1),in_FxKlaviyo,0) | F100: =IF(F$23>=DATE(YEAR(in_FxKlaviyo_Start),MONTH(in_FxKlaviyo_Start),1),in_FxKlaviyo,0) | G100: =IF(G$23>=DATE(YEAR(in_FxKlaviyo_Start),MONTH(in_FxKlaviyo_Start),1),in_FxKlaviyo,0) | H100: =IF(H$23>=DATE(YEAR(in_FxKlaviyo_Start),MONTH(in_FxKlaviyo_Start),1),in_FxKlaviyo,0) | I100: =IF(I$23>=DATE(YEAR(in_FxKlaviyo_Start),MONTH(in_FxKlaviyo_Start),1),in_FxKlaviyo,0) | J100: =IF(J$23>=DATE(YEAR(in_FxKlaviyo_Start),MONTH(in_FxKlaviyo_Start),1),in_FxKlaviyo,0) | ... Q100: =IF(Q$23>=DATE(YEAR(in_FxKlaviyo_Start),MONTH(in_FxKlaviyo_Start),1),in_FxKlaviyo,0) | R100: =SUM(C100:Q100)
A101: Product liability insurance | C101: =IF(C$23>=DATE(YEAR(in_FxInsurance_Start),MONTH(in_FxInsurance_Start),1),in_FxInsurance,0) | D101: =IF(D$23>=DATE(YEAR(in_FxInsurance_Start),MONTH(in_FxInsurance_Start),1),in_FxInsurance,0) | E101: =IF(E$23>=DATE(YEAR(in_FxInsurance_Start),MONTH(in_FxInsurance_Start),1),in_FxInsurance,0) | F101: =IF(F$23>=DATE(YEAR(in_FxInsurance_Start),MONTH(in_FxInsurance_Start),1),in_FxInsurance,0) | G101: =IF(G$23>=DATE(YEAR(in_FxInsurance_Start),MONTH(in_FxInsurance_Start),1),in_FxInsurance,0) | H101: =IF(H$23>=DATE(YEAR(in_FxInsurance_Start),MONTH(in_FxInsurance_Start),1),in_FxInsurance,0) | I101: =IF(I$23>=DATE(YEAR(in_FxInsurance_Start),MONTH(in_FxInsurance_Start),1),in_FxInsurance,0) | J101: =IF(J$23>=DATE(YEAR(in_FxInsurance_Start),MONTH(in_FxInsurance_Start),1),in_FxInsurance,0) | ... Q101: =IF(Q$23>=DATE(YEAR(in_FxInsurance_Start),MONTH(in_FxInsurance_Start),1),in_FxInsurance,0) | R101: =SUM(C101:Q101)
A102: Other software (SMS credits, apps) | C102: =IF(C$23>=DATE(YEAR(in_FxSoftware_Start),MONTH(in_FxSoftware_Start),1),in_FxSoftware,0) | D102: =IF(D$23>=DATE(YEAR(in_FxSoftware_Start),MONTH(in_FxSoftware_Start),1),in_FxSoftware,0) | E102: =IF(E$23>=DATE(YEAR(in_FxSoftware_Start),MONTH(in_FxSoftware_Start),1),in_FxSoftware,0) | F102: =IF(F$23>=DATE(YEAR(in_FxSoftware_Start),MONTH(in_FxSoftware_Start),1),in_FxSoftware,0) | G102: =IF(G$23>=DATE(YEAR(in_FxSoftware_Start),MONTH(in_FxSoftware_Start),1),in_FxSoftware,0) | H102: =IF(H$23>=DATE(YEAR(in_FxSoftware_Start),MONTH(in_FxSoftware_Start),1),in_FxSoftware,0) | I102: =IF(I$23>=DATE(YEAR(in_FxSoftware_Start),MONTH(in_FxSoftware_Start),1),in_FxSoftware,0) | J102: =IF(J$23>=DATE(YEAR(in_FxSoftware_Start),MONTH(in_FxSoftware_Start),1),in_FxSoftware,0) | ... Q102: =IF(Q$23>=DATE(YEAR(in_FxSoftware_Start),MONTH(in_FxSoftware_Start),1),in_FxSoftware,0) | R102: =SUM(C102:Q102)
A103: Bookkeeping | C103: =IF(C$23>=DATE(YEAR(in_FxBooks_Start),MONTH(in_FxBooks_Start),1),in_FxBooks,0) | D103: =IF(D$23>=DATE(YEAR(in_FxBooks_Start),MONTH(in_FxBooks_Start),1),in_FxBooks,0) | E103: =IF(E$23>=DATE(YEAR(in_FxBooks_Start),MONTH(in_FxBooks_Start),1),in_FxBooks,0) | F103: =IF(F$23>=DATE(YEAR(in_FxBooks_Start),MONTH(in_FxBooks_Start),1),in_FxBooks,0) | G103: =IF(G$23>=DATE(YEAR(in_FxBooks_Start),MONTH(in_FxBooks_Start),1),in_FxBooks,0) | H103: =IF(H$23>=DATE(YEAR(in_FxBooks_Start),MONTH(in_FxBooks_Start),1),in_FxBooks,0) | I103: =IF(I$23>=DATE(YEAR(in_FxBooks_Start),MONTH(in_FxBooks_Start),1),in_FxBooks,0) | J103: =IF(J$23>=DATE(YEAR(in_FxBooks_Start),MONTH(in_FxBooks_Start),1),in_FxBooks,0) | ... Q103: =IF(Q$23>=DATE(YEAR(in_FxBooks_Start),MONTH(in_FxBooks_Start),1),in_FxBooks,0) | R103: =SUM(C103:Q103)
A104: Amazon Professional plan | C104: =IF(C$23>=DATE(YEAR(in_FxAmazon_Start),MONTH(in_FxAmazon_Start),1),in_FxAmazon,0) | D104: =IF(D$23>=DATE(YEAR(in_FxAmazon_Start),MONTH(in_FxAmazon_Start),1),in_FxAmazon,0) | E104: =IF(E$23>=DATE(YEAR(in_FxAmazon_Start),MONTH(in_FxAmazon_Start),1),in_FxAmazon,0) | F104: =IF(F$23>=DATE(YEAR(in_FxAmazon_Start),MONTH(in_FxAmazon_Start),1),in_FxAmazon,0) | G104: =IF(G$23>=DATE(YEAR(in_FxAmazon_Start),MONTH(in_FxAmazon_Start),1),in_FxAmazon,0) | H104: =IF(H$23>=DATE(YEAR(in_FxAmazon_Start),MONTH(in_FxAmazon_Start),1),in_FxAmazon,0) | I104: =IF(I$23>=DATE(YEAR(in_FxAmazon_Start),MONTH(in_FxAmazon_Start),1),in_FxAmazon,0) | J104: =IF(J$23>=DATE(YEAR(in_FxAmazon_Start),MONTH(in_FxAmazon_Start),1),in_FxAmazon,0) | ... Q104: =IF(Q$23>=DATE(YEAR(in_FxAmazon_Start),MONTH(in_FxAmazon_Start),1),in_FxAmazon,0) | R104: =SUM(C104:Q104)
A105: Total fixed costs | C105: =SUM(C99:C104) | D105: =SUM(D99:D104) | E105: =SUM(E99:E104) | F105: =SUM(F99:F104) | G105: =SUM(G99:G104) | H105: =SUM(H99:H104) | I105: =SUM(I99:I104) | J105: =SUM(J99:J104) | ... Q105: =SUM(Q99:Q104) | R105: =SUM(C105:Q105)
A107: One-time launch costs (cash out)
A108: Company, trademark, lawyer review, insurance setup | C108: =IF(EOMONTH(in_OtCompany_D,0)=EOMONTH(C$23,0),IF($B$3="Lean",in_OtCompany_L,in_OtCompany_S),0) | D108: =IF(EOMONTH(in_OtCompany_D,0)=EOMONTH(D$23,0),IF($B$3="Lean",in_OtCompany_L,in_OtCompany_S),0) | E108: =IF(EOMONTH(in_OtCompany_D,0)=EOMONTH(E$23,0),IF($B$3="Lean",in_OtCompany_L,in_OtCompany_S),0) | F108: =IF(EOMONTH(in_OtCompany_D,0)=EOMONTH(F$23,0),IF($B$3="Lean",in_OtCompany_L,in_OtCompany_S),0) | G108: =IF(EOMONTH(in_OtCompany_D,0)=EOMONTH(G$23,0),IF($B$3="Lean",in_OtCompany_L,in_OtCompany_S),0) | H108: =IF(EOMONTH(in_OtCompany_D,0)=EOMONTH(H$23,0),IF($B$3="Lean",in_OtCompany_L,in_OtCompany_S),0) | I108: =IF(EOMONTH(in_OtCompany_D,0)=EOMONTH(I$23,0),IF($B$3="Lean",in_OtCompany_L,in_OtCompany_S),0) | J108: =IF(EOMONTH(in_OtCompany_D,0)=EOMONTH(J$23,0),IF($B$3="Lean",in_OtCompany_L,in_OtCompany_S),0) | ... Q108: =IF(EOMONTH(in_OtCompany_D,0)=EOMONTH(Q$23,0),IF($B$3="Lean",in_OtCompany_L,in_OtCompany_S),0) | R108: =SUM(C108:Q108)
A109: Samples and flavour development (Strawberry) | C109: =IF(EOMONTH(in_OtSamples_D,0)=EOMONTH(C$23,0),IF($B$3="Lean",in_OtSamples_L,in_OtSamples_S),0) | D109: =IF(EOMONTH(in_OtSamples_D,0)=EOMONTH(D$23,0),IF($B$3="Lean",in_OtSamples_L,in_OtSamples_S),0) | E109: =IF(EOMONTH(in_OtSamples_D,0)=EOMONTH(E$23,0),IF($B$3="Lean",in_OtSamples_L,in_OtSamples_S),0) | F109: =IF(EOMONTH(in_OtSamples_D,0)=EOMONTH(F$23,0),IF($B$3="Lean",in_OtSamples_L,in_OtSamples_S),0) | G109: =IF(EOMONTH(in_OtSamples_D,0)=EOMONTH(G$23,0),IF($B$3="Lean",in_OtSamples_L,in_OtSamples_S),0) | H109: =IF(EOMONTH(in_OtSamples_D,0)=EOMONTH(H$23,0),IF($B$3="Lean",in_OtSamples_L,in_OtSamples_S),0) | I109: =IF(EOMONTH(in_OtSamples_D,0)=EOMONTH(I$23,0),IF($B$3="Lean",in_OtSamples_L,in_OtSamples_S),0) | J109: =IF(EOMONTH(in_OtSamples_D,0)=EOMONTH(J$23,0),IF($B$3="Lean",in_OtSamples_L,in_OtSamples_S),0) | ... Q109: =IF(EOMONTH(in_OtSamples_D,0)=EOMONTH(Q$23,0),IF($B$3="Lean",in_OtSamples_L,in_OtSamples_S),0) | R109: =SUM(C109:Q109)
A110: Label and regulatory review | C110: =IF(EOMONTH(in_OtLabel_D,0)=EOMONTH(C$23,0),IF($B$3="Lean",in_OtLabel_L,in_OtLabel_S),0) | D110: =IF(EOMONTH(in_OtLabel_D,0)=EOMONTH(D$23,0),IF($B$3="Lean",in_OtLabel_L,in_OtLabel_S),0) | E110: =IF(EOMONTH(in_OtLabel_D,0)=EOMONTH(E$23,0),IF($B$3="Lean",in_OtLabel_L,in_OtLabel_S),0) | F110: =IF(EOMONTH(in_OtLabel_D,0)=EOMONTH(F$23,0),IF($B$3="Lean",in_OtLabel_L,in_OtLabel_S),0) | G110: =IF(EOMONTH(in_OtLabel_D,0)=EOMONTH(G$23,0),IF($B$3="Lean",in_OtLabel_L,in_OtLabel_S),0) | H110: =IF(EOMONTH(in_OtLabel_D,0)=EOMONTH(H$23,0),IF($B$3="Lean",in_OtLabel_L,in_OtLabel_S),0) | I110: =IF(EOMONTH(in_OtLabel_D,0)=EOMONTH(I$23,0),IF($B$3="Lean",in_OtLabel_L,in_OtLabel_S),0) | J110: =IF(EOMONTH(in_OtLabel_D,0)=EOMONTH(J$23,0),IF($B$3="Lean",in_OtLabel_L,in_OtLabel_S),0) | ... Q110: =IF(EOMONTH(in_OtLabel_D,0)=EOMONTH(Q$23,0),IF($B$3="Lean",in_OtLabel_L,in_OtLabel_S),0) | R110: =SUM(C110:Q110)
A111: Launch kit: shakers, display, sampling supplies, apps | C111: =IF(EOMONTH(in_OtKit_D,0)=EOMONTH(C$23,0),IF($B$3="Lean",in_OtKit_L,in_OtKit_S),0) | D111: =IF(EOMONTH(in_OtKit_D,0)=EOMONTH(D$23,0),IF($B$3="Lean",in_OtKit_L,in_OtKit_S),0) | E111: =IF(EOMONTH(in_OtKit_D,0)=EOMONTH(E$23,0),IF($B$3="Lean",in_OtKit_L,in_OtKit_S),0) | F111: =IF(EOMONTH(in_OtKit_D,0)=EOMONTH(F$23,0),IF($B$3="Lean",in_OtKit_L,in_OtKit_S),0) | G111: =IF(EOMONTH(in_OtKit_D,0)=EOMONTH(G$23,0),IF($B$3="Lean",in_OtKit_L,in_OtKit_S),0) | H111: =IF(EOMONTH(in_OtKit_D,0)=EOMONTH(H$23,0),IF($B$3="Lean",in_OtKit_L,in_OtKit_S),0) | I111: =IF(EOMONTH(in_OtKit_D,0)=EOMONTH(I$23,0),IF($B$3="Lean",in_OtKit_L,in_OtKit_S),0) | J111: =IF(EOMONTH(in_OtKit_D,0)=EOMONTH(J$23,0),IF($B$3="Lean",in_OtKit_L,in_OtKit_S),0) | ... Q111: =IF(EOMONTH(in_OtKit_D,0)=EOMONTH(Q$23,0),IF($B$3="Lean",in_OtKit_L,in_OtKit_S),0) | R111: =SUM(C111:Q111)
A112: Real Fruit Hydration sticks (development and first run) | C112: =IF(EOMONTH(in_OtHydra_D,0)=EOMONTH(C$23,0),IF($B$3="Lean",in_OtHydra_L,in_OtHydra_S),0)*in_HydraOn | D112: =IF(EOMONTH(in_OtHydra_D,0)=EOMONTH(D$23,0),IF($B$3="Lean",in_OtHydra_L,in_OtHydra_S),0)*in_HydraOn | E112: =IF(EOMONTH(in_OtHydra_D,0)=EOMONTH(E$23,0),IF($B$3="Lean",in_OtHydra_L,in_OtHydra_S),0)*in_HydraOn | F112: =IF(EOMONTH(in_OtHydra_D,0)=EOMONTH(F$23,0),IF($B$3="Lean",in_OtHydra_L,in_OtHydra_S),0)*in_HydraOn | G112: =IF(EOMONTH(in_OtHydra_D,0)=EOMONTH(G$23,0),IF($B$3="Lean",in_OtHydra_L,in_OtHydra_S),0)*in_HydraOn | H112: =IF(EOMONTH(in_OtHydra_D,0)=EOMONTH(H$23,0),IF($B$3="Lean",in_OtHydra_L,in_OtHydra_S),0)*in_HydraOn | I112: =IF(EOMONTH(in_OtHydra_D,0)=EOMONTH(I$23,0),IF($B$3="Lean",in_OtHydra_L,in_OtHydra_S),0)*in_HydraOn | J112: =IF(EOMONTH(in_OtHydra_D,0)=EOMONTH(J$23,0),IF($B$3="Lean",in_OtHydra_L,in_OtHydra_S),0)*in_HydraOn | ... Q112: =IF(EOMONTH(in_OtHydra_D,0)=EOMONTH(Q$23,0),IF($B$3="Lean",in_OtHydra_L,in_OtHydra_S),0)*in_HydraOn | R112: =SUM(C112:Q112)
...

Sheet calc_Standard_Low
A1: Calculation copy: Standard runs, Low demand (feeds Scenarios; do not edit)
A2: Months Oct 2026 to Dec 2027. All figures are projections from the Inputs sheet, not actual results. Cash view: inventory is a cash outflow when bought; COGS appears only in the operating view at the bottom.
A3: Run-size mode | B3: ="Standard"
A4: Demand multiplier | B4: =in_MultLow
A5: Demand case | B5: ="Low"
A6: Pouch cost of goods (by mode) | B6: =IF($B$3="Lean",in_CogsLean,in_CogsStd)
A7: Stick cost of goods (by mode) | B7: =IF($B$3="Lean",in_StickCogsLean,in_StickCogsStd)
A8: Pouch run size (by mode) | B8: =IF($B$3="Lean",in_RunLean,in_RunStd)
A9: Stick run size (by mode) | B9: =IF($B$3="Lean",in_StickRunLean,in_StickRunStd)
A10: Sample credit on first order (by mode) | B10: =IF($B$3="Lean",in_SampleCreditLean,in_SampleCreditStd)
A12: Summary for this sheet's mode and case
A13: Lowest cash balance | B13: =MIN($C$120:$Q$120)
A14: Month of lowest cash balance | B14: =INDEX($C$23:$Q$23,MATCH(MIN($C$120:$Q$120),$C$120:$Q$120,0))
A15: Peak funding need (lowest cumulative net cash flow) | B15: =MIN(0,MIN($C$119:$Q$119))
A16: Operating break-even month (first month operating profit >= 0) | B16: =IFERROR(INDEX($C$23:$Q$23,MATCH(1,$C$127:$Q$127,0)),"Not by Dec 2027")
A17: Cash payback month (cumulative net cash flow back to >= 0) | B17: =IFERROR(INDEX($C$23:$Q$23,MATCH(1,$C$128:$Q$128,0)),"Not by Dec 2027")
A18: Cash balance, end of Jun 2027 | B18: =IFERROR(INDEX($C$120:$Q$120,MATCH(DATE(2027,6,1),$C$23:$Q$23,0)),"n/a")
A19: Cash balance, end of Dec 2027 | B19: =IFERROR(INDEX($C$120:$Q$120,MATCH(DATE(2027,12,1),$C$23:$Q$23,0)),"n/a")
A20: Stockout check (pouch + stick units short; should be 0) | B20: =SUM($C$54:$Q$54)+SUM($C$65:$Q$65)
A21: Operating profit, Oct 2026 to Dec 2027 (launch costs excluded) | B21: =SUM($C$126:$Q$126)
A23: Line | B23: Note | C23: =DATE(YEAR(in_ModelStart),MONTH(in_ModelStart),1) | D23: =EDATE(C23,1) | E23: =EDATE(D23,1) | F23: =EDATE(E23,1) | G23: =EDATE(F23,1) | H23: =EDATE(G23,1) | I23: =EDATE(H23,1) | J23: =EDATE(I23,1) | K23: =EDATE(J23,1) | ... Q23: =EDATE(P23,1) | R23: Total
A24: Selling? (1 from the first ship month) | C24: =IF(C$23>=DATE(YEAR(in_FirstShip),MONTH(in_FirstShip),1),1,0) | D24: =IF(D$23>=DATE(YEAR(in_FirstShip),MONTH(in_FirstShip),1),1,0) | E24: =IF(E$23>=DATE(YEAR(in_FirstShip),MONTH(in_FirstShip),1),1,0) | F24: =IF(F$23>=DATE(YEAR(in_FirstShip),MONTH(in_FirstShip),1),1,0) | G24: =IF(G$23>=DATE(YEAR(in_FirstShip),MONTH(in_FirstShip),1),1,0) | H24: =IF(H$23>=DATE(YEAR(in_FirstShip),MONTH(in_FirstShip),1),1,0) | I24: =IF(I$23>=DATE(YEAR(in_FirstShip),MONTH(in_FirstShip),1),1,0) | J24: =IF(J$23>=DATE(YEAR(in_FirstShip),MONTH(in_FirstShip),1),1,0) | ... Q24: =IF(Q$23>=DATE(YEAR(in_FirstShip),MONTH(in_FirstShip),1),1,0)
A26: DTC customers and orders
A27: Waitlist first orders (first ship month only) | B27: Waitlist x conversion | C27: =IF(EOMONTH(in_FirstShip,0)=EOMONTH(C$23,0),in_WaitSize*in_WaitConv*$B$4,0) | D27: =IF(EOMONTH(in_FirstShip,0)=EOMONTH(D$23,0),in_WaitSize*in_WaitConv*$B$4,0) | E27: =IF(EOMONTH(in_FirstShip,0)=EOMONTH(E$23,0),in_WaitSize*in_WaitConv*$B$4,0) | F27: =IF(EOMONTH(in_FirstShip,0)=EOMONTH(F$23,0),in_WaitSize*in_WaitConv*$B$4,0) | G27: =IF(EOMONTH(in_FirstShip,0)=EOMONTH(G$23,0),in_WaitSize*in_WaitConv*$B$4,0) | H27: =IF(EOMONTH(in_FirstShip,0)=EOMONTH(H$23,0),in_WaitSize*in_WaitConv*$B$4,0) | I27: =IF(EOMONTH(in_FirstShip,0)=EOMONTH(I$23,0),in_WaitSize*in_WaitConv*$B$4,0) | J27: =IF(EOMONTH(in_FirstShip,0)=EOMONTH(J$23,0),in_WaitSize*in_WaitConv*$B$4,0) | ... Q27: =IF(EOMONTH(in_FirstShip,0)=EOMONTH(Q$23,0),in_WaitSize*in_WaitConv*$B$4,0) | R27: =SUM(C27:Q27)
A28: Organic new customers | C28: =IFERROR(INDEX(Inputs!$B$98:$B$107,MATCH(C$23,Inputs!$A$98:$A$107,0)),0)*$B$4*C24 | D28: =IFERROR(INDEX(Inputs!$B$98:$B$107,MATCH(D$23,Inputs!$A$98:$A$107,0)),0)*$B$4*D24 | E28: =IFERROR(INDEX(Inputs!$B$98:$B$107,MATCH(E$23,Inputs!$A$98:$A$107,0)),0)*$B$4*E24 | F28: =IFERROR(INDEX(Inputs!$B$98:$B$107,MATCH(F$23,Inputs!$A$98:$A$107,0)),0)*$B$4*F24 | G28: =IFERROR(INDEX(Inputs!$B$98:$B$107,MATCH(G$23,Inputs!$A$98:$A$107,0)),0)*$B$4*G24 | H28: =IFERROR(INDEX(Inputs!$B$98:$B$107,MATCH(H$23,Inputs!$A$98:$A$107,0)),0)*$B$4*H24 | I28: =IFERROR(INDEX(Inputs!$B$98:$B$107,MATCH(I$23,Inputs!$A$98:$A$107,0)),0)*$B$4*I24 | J28: =IFERROR(INDEX(Inputs!$B$98:$B$107,MATCH(J$23,Inputs!$A$98:$A$107,0)),0)*$B$4*J24 | ... Q28: =IFERROR(INDEX(Inputs!$B$98:$B$107,MATCH(Q$23,Inputs!$A$98:$A$107,0)),0)*$B$4*Q24 | R28: =SUM(C28:Q28)
A29: Paid new customers | C29: =IFERROR(INDEX(Inputs!$C$98:$C$107,MATCH(C$23,Inputs!$A$98:$A$107,0)),0)*$B$4*C24 | D29: =IFERROR(INDEX(Inputs!$C$98:$C$107,MATCH(D$23,Inputs!$A$98:$A$107,0)),0)*$B$4*D24 | E29: =IFERROR(INDEX(Inputs!$C$98:$C$107,MATCH(E$23,Inputs!$A$98:$A$107,0)),0)*$B$4*E24 | F29: =IFERROR(INDEX(Inputs!$C$98:$C$107,MATCH(F$23,Inputs!$A$98:$A$107,0)),0)*$B$4*F24 | G29: =IFERROR(INDEX(Inputs!$C$98:$C$107,MATCH(G$23,Inputs!$A$98:$A$107,0)),0)*$B$4*G24 | H29: =IFERROR(INDEX(Inputs!$C$98:$C$107,MATCH(H$23,Inputs!$A$98:$A$107,0)),0)*$B$4*H24 | I29: =IFERROR(INDEX(Inputs!$C$98:$C$107,MATCH(I$23,Inputs!$A$98:$A$107,0)),0)*$B$4*I24 | J29: =IFERROR(INDEX(Inputs!$C$98:$C$107,MATCH(J$23,Inputs!$A$98:$A$107,0)),0)*$B$4*J24 | ... Q29: =IFERROR(INDEX(Inputs!$C$98:$C$107,MATCH(Q$23,Inputs!$A$98:$A$107,0)),0)*$B$4*Q24 | R29: =SUM(C29:Q29)
A30: Total new DTC customers | C30: =C27+C28+C29 | D30: =D27+D28+D29 | E30: =E27+E28+E29 | F30: =F27+F28+F29 | G30: =G27+G28+G29 | H30: =H27+H28+H29 | I30: =I27+I28+I29 | J30: =J27+J28+J29 | ... Q30: =Q27+Q28+Q29 | R30: =SUM(C30:Q30)
A31: New subscribers | C31: =C30*in_SubShare | D31: =D30*in_SubShare | E31: =E30*in_SubShare | F31: =F30*in_SubShare | G31: =G30*in_SubShare | H31: =H30*in_SubShare | I31: =I30*in_SubShare | J31: =J30*in_SubShare | ... Q31: =Q30*in_SubShare | R31: =SUM(C31:Q31)
A32: Active subscribers, end of month (= subscription orders) | B32: 1 pouch/month each | C32: =C31 | D32: =C32*(1-in_SubChurn)+D31 | E32: =D32*(1-in_SubChurn)+E31 | F32: =E32*(1-in_SubChurn)+F31 | G32: =F32*(1-in_SubChurn)+G31 | H32: =G32*(1-in_SubChurn)+H31 | I32: =H32*(1-in_SubChurn)+I31 | J32: =I32*(1-in_SubChurn)+J31 | K32: =J32*(1-in_SubChurn)+K31 | ... Q32: =P32*(1-in_SubChurn)+Q31
A33: One-off first orders | C33: =C30*(1-in_SubShare) | D33: =D30*(1-in_SubShare) | E33: =E30*(1-in_SubShare) | F33: =F30*(1-in_SubShare) | G33: =G30*(1-in_SubShare) | H33: =H30*(1-in_SubShare) | I33: =I30*(1-in_SubShare) | J33: =J30*(1-in_SubShare) | ... Q33: =Q30*(1-in_SubShare) | R33: =SUM(C33:Q33)
A34: One-off repeat orders | C34: =0 | D34: =C35*in_Repeat | E34: =D35*in_Repeat | F34: =E35*in_Repeat | G34: =F35*in_Repeat | H34: =G35*in_Repeat | I34: =H35*in_Repeat | J34: =I35*in_Repeat | K34: =J35*in_Repeat | ... Q34: =P35*in_Repeat | R34: =SUM(C34:Q34)
A35: Total one-off pouch orders | C35: =C33+C34 | D35: =D33+D34 | E35: =E33+E34 | F35: =F33+F34 | G35: =G33+G34 | H35: =H33+H34 | I35: =I33+I34 | J35: =J33+J34 | ... Q35: =Q33+Q34 | R35: =SUM(C35:Q35)
A36: Total DTC pouch orders (one-off + subscription) | C36: =C35+C32 | D36: =D35+D32 | E36: =E35+E32 | F36: =F35+F32 | G36: =G35+G32 | H36: =H35+H32 | I36: =I35+I32 | J36: =J35+J32 | ... Q36: =Q35+Q32 | R36: =SUM(C36:Q36)
A37: DTC stick-box orders | C37: =C36*in_StickAttach | D37: =D36*in_StickAttach | E37: =E36*in_StickAttach | F37: =F36*in_StickAttach | G37: =G36*in_StickAttach | H37: =H36*in_StickAttach | I37: =I36*in_StickAttach | J37: =J36*in_StickAttach | ... Q37: =Q36*in_StickAttach | R37: =SUM(C37:Q37)
A39: Wholesale (direct to stores)
A40: New store accounts | C40: =IFERROR(INDEX(Inputs!$D$98:$D$107,MATCH(C$23,Inputs!$A$98:$A$107,0)),0)*$B$4*C24 | D40: =IFERROR(INDEX(Inputs!$D$98:$D$107,MATCH(D$23,Inputs!$A$98:$A$107,0)),0)*$B$4*D24 | E40: =IFERROR(INDEX(Inputs!$D$98:$D$107,MATCH(E$23,Inputs!$A$98:$A$107,0)),0)*$B$4*E24 | F40: =IFERROR(INDEX(Inputs!$D$98:$D$107,MATCH(F$23,Inputs!$A$98:$A$107,0)),0)*$B$4*F24 | G40: =IFERROR(INDEX(Inputs!$D$98:$D$107,MATCH(G$23,Inputs!$A$98:$A$107,0)),0)*$B$4*G24 | H40: =IFERROR(INDEX(Inputs!$D$98:$D$107,MATCH(H$23,Inputs!$A$98:$A$107,0)),0)*$B$4*H24 | I40: =IFERROR(INDEX(Inputs!$D$98:$D$107,MATCH(I$23,Inputs!$A$98:$A$107,0)),0)*$B$4*I24 | J40: =IFERROR(INDEX(Inputs!$D$98:$D$107,MATCH(J$23,Inputs!$A$98:$A$107,0)),0)*$B$4*J24 | ... Q40: =IFERROR(INDEX(Inputs!$D$98:$D$107,MATCH(Q$23,Inputs!$A$98:$A$107,0)),0)*$B$4*Q24 | R40: =SUM(C40:Q40)
A41: Active store accounts, end of month | C41: =C40 | D41: =C41*(1-in_StoreChurn)+D40 | E41: =D41*(1-in_StoreChurn)+E40 | F41: =E41*(1-in_StoreChurn)+F40 | G41: =F41*(1-in_StoreChurn)+G40 | H41: =G41*(1-in_StoreChurn)+H40 | I41: =H41*(1-in_StoreChurn)+I40 | J41: =I41*(1-in_StoreChurn)+J40 | K41: =J41*(1-in_StoreChurn)+K40 | ... Q41: =P41*(1-in_StoreChurn)+Q40
A42: Wholesale pouches shipped | C42: =C41*in_PouchPerStore | D42: =D41*in_PouchPerStore | E42: =E41*in_PouchPerStore | F42: =F41*in_PouchPerStore | G42: =G41*in_PouchPerStore | H42: =H41*in_PouchPerStore | I42: =I41*in_PouchPerStore | J42: =J41*in_PouchPerStore | ... Q42: =Q41*in_PouchPerStore | R42: =SUM(C42:Q42)
A43: Wholesale sticks shipped | C43: =C41*in_StickPerStore | D43: =D41*in_StickPerStore | E43: =E41*in_StickPerStore | F43: =F41*in_StickPerStore | G43: =G41*in_StickPerStore | H43: =H41*in_StickPerStore | I43: =I41*in_StickPerStore | J43: =J41*in_StickPerStore | ... Q43: =Q41*in_StickPerStore | R43: =SUM(C43:Q43)
A45: Pouch inventory (units)
A46: Pouch demand | C46: =C36*in_PouchPerOrder+C42 | D46: =D36*in_PouchPerOrder+D42 | E46: =E36*in_PouchPerOrder+E42 | F46: =F36*in_PouchPerOrder+F42 | G46: =G36*in_PouchPerOrder+G42 | H46: =H36*in_PouchPerOrder+H42 | I46: =I36*in_PouchPerOrder+I42 | J46: =J36*in_PouchPerOrder+J42 | ... Q46: =Q36*in_PouchPerOrder+Q42 | R46: =SUM(C46:Q46)
A47: Opening stock | C47: =0 | D47: =C55 | E47: =D55 | F47: =E55 | G47: =F55 | H47: =G55 | I47: =H55 | J47: =I55 | K47: =J55 | ... Q47: =P55
A48: First run received | C48: =IF(EOMONTH(in_FirstShip,0)=EOMONTH(C$23,0),$B$8,0) | D48: =IF(EOMONTH(in_FirstShip,0)=EOMONTH(D$23,0),$B$8,0) | E48: =IF(EOMONTH(in_FirstShip,0)=EOMONTH(E$23,0),$B$8,0) | F48: =IF(EOMONTH(in_FirstShip,0)=EOMONTH(F$23,0),$B$8,0) | G48: =IF(EOMONTH(in_FirstShip,0)=EOMONTH(G$23,0),$B$8,0) | H48: =IF(EOMONTH(in_FirstShip,0)=EOMONTH(H$23,0),$B$8,0) | I48: =IF(EOMONTH(in_FirstShip,0)=EOMONTH(I$23,0),$B$8,0) | J48: =IF(EOMONTH(in_FirstShip,0)=EOMONTH(J$23,0),$B$8,0) | ... Q48: =IF(EOMONTH(in_FirstShip,0)=EOMONTH(Q$23,0),$B$8,0) | R48: =SUM(C48:Q48)
A49: Second flavour first run received | C49: =IF(AND(in_Flavor2On=1,EOMONTH(in_Flavor2Run,0)=EOMONTH(C$23,0)),$B$8,0) | D49: =IF(AND(in_Flavor2On=1,EOMONTH(in_Flavor2Run,0)=EOMONTH(D$23,0)),$B$8,0) | E49: =IF(AND(in_Flavor2On=1,EOMONTH(in_Flavor2Run,0)=EOMONTH(E$23,0)),$B$8,0) | F49: =IF(AND(in_Flavor2On=1,EOMONTH(in_Flavor2Run,0)=EOMONTH(F$23,0)),$B$8,0) | G49: =IF(AND(in_Flavor2On=1,EOMONTH(in_Flavor2Run,0)=EOMONTH(G$23,0)),$B$8,0) | H49: =IF(AND(in_Flavor2On=1,EOMONTH(in_Flavor2Run,0)=EOMONTH(H$23,0)),$B$8,0) | I49: =IF(AND(in_Flavor2On=1,EOMONTH(in_Flavor2Run,0)=EOMONTH(I$23,0)),$B$8,0) | J49: =IF(AND(in_Flavor2On=1,EOMONTH(in_Flavor2Run,0)=EOMONTH(J$23,0)),$B$8,0) | ... Q49: =IF(AND(in_Flavor2On=1,EOMONTH(in_Flavor2Run,0)=EOMONTH(Q$23,0)),$B$8,0) | R49: =SUM(C49:Q49)
A50: Reorders received (placed lead-time months earlier) | B50: Lead-time input | C50: =IF(in_Lead=1,0,IF(in_Lead=2,0,IF(in_Lead=3,0,0))) | D50: =IF(in_Lead=1,C52,IF(in_Lead=2,0,IF(in_Lead=3,0,0))) | E50: =IF(in_Lead=1,D52,IF(in_Lead=2,C52,IF(in_Lead=3,0,0))) | F50: =IF(in_Lead=1,E52,IF(in_Lead=2,D52,IF(in_Lead=3,C52,0))) | G50: =IF(in_Lead=1,F52,IF(in_Lead=2,E52,IF(in_Lead=3,D52,0))) | H50: =IF(in_Lead=1,G52,IF(in_Lead=2,F52,IF(in_Lead=3,E52,0))) | I50: =IF(in_Lead=1,H52,IF(in_Lead=2,G52,IF(in_Lead=3,F52,0))) | J50: =IF(in_Lead=1,I52,IF(in_Lead=2,H52,IF(in_Lead=3,G52,0))) | K50: =IF(in_Lead=1,J52,IF(in_Lead=2,I52,IF(in_Lead=3,H52,0))) | L50: =IF(in_Lead=1,K52,IF(in_Lead=2,J52,IF(in_Lead=3,I52,0))) | M50: =IF(in_Lead=1,L52,IF(in_Lead=2,K52,IF(in_Lead=3,J52,0))) | ... Q50: =IF(in_Lead=1,P52,IF(in_Lead=2,O52,IF(in_Lead=3,N52,0))) | R50: =SUM(C50:Q50)
A51: On order, still in transit after this month | C51: =IF(in_Lead>=2,0,0)+IF(in_Lead>=3,0,0) | D51: =IF(in_Lead>=2,C52,0)+IF(in_Lead>=3,0,0) | E51: =IF(in_Lead>=2,D52,0)+IF(in_Lead>=3,C52,0) | F51: =IF(in_Lead>=2,E52,0)+IF(in_Lead>=3,D52,0) | G51: =IF(in_Lead>=2,F52,0)+IF(in_Lead>=3,E52,0) | H51: =IF(in_Lead>=2,G52,0)+IF(in_Lead>=3,F52,0) | I51: =IF(in_Lead>=2,H52,0)+IF(in_Lead>=3,G52,0) | J51: =IF(in_Lead>=2,I52,0)+IF(in_Lead>=3,H52,0) | K51: =IF(in_Lead>=2,J52,0)+IF(in_Lead>=3,I52,0) | L51: =IF(in_Lead>=2,K52,0)+IF(in_Lead>=3,J52,0) | ... Q51: =IF(in_Lead>=2,P52,0)+IF(in_Lead>=3,O52,0)
A52: Reorder placed and paid (stock + on order below reorder point) | B52: Paid when placed | C52: =IF(C24=1,IF(C47+C48+C49+C50+C51<C46*in_Cover,ROUNDUP((C46*in_Cover-(C47+C48+C49+C50+C51))/$B$8,0)*$B$8,0),0) | D52: =IF(D24=1,IF(D47+D48+D49+D50+D51<D46*in_Cover,ROUNDUP((D46*in_Cover-(D47+D48+D49+D50+D51))/$B$8,0)*$B$8,0),0) | E52: =IF(E24=1,IF(E47+E48+E49+E50+E51<E46*in_Cover,ROUNDUP((E46*in_Cover-(E47+E48+E49+E50+E51))/$B$8,0)*$B$8,0),0) | F52: =IF(F24=1,IF(F47+F48+F49+F50+F51<F46*in_Cover,ROUNDUP((F46*in_Cover-(F47+F48+F49+F50+F51))/$B$8,0)*$B$8,0),0) | G52: =IF(G24=1,IF(G47+G48+G49+G50+G51<G46*in_Cover,ROUNDUP((G46*in_Cover-(G47+G48+G49+G50+G51))/$B$8,0)*$B$8,0),0) | H52: =IF(H24=1,IF(H47+H48+H49+H50+H51<H46*in_Cover,ROUNDUP((H46*in_Cover-(H47+H48+H49+H50+H51))/$B$8,0)*$B$8,0),0) | I52: =IF(I24=1,IF(I47+I48+I49+I50+I51<I46*in_Cover,ROUNDUP((I46*in_Cover-(I47+I48+I49+I50+I51))/$B$8,0)*$B$8,0),0) | J52: =IF(J24=1,IF(J47+J48+J49+J50+J51<J46*in_Cover,ROUNDUP((J46*in_Cover-(J47+J48+J49+J50+J51))/$B$8,0)*$B$8,0),0) | ... Q52: =IF(Q24=1,IF(Q47+Q48+Q49+Q50+Q51<Q46*in_Cover,ROUNDUP((Q46*in_Cover-(Q47+Q48+Q49+Q50+Q51))/$B$8,0)*$B$8,0),0) | R52: =SUM(C52:Q52)
A53: Pouches sold | C53: =MIN(C46,C47+C48+C49+C50) | D53: =MIN(D46,D47+D48+D49+D50) | E53: =MIN(E46,E47+E48+E49+E50) | F53: =MIN(F46,F47+F48+F49+F50) | G53: =MIN(G46,G47+G48+G49+G50) | H53: =MIN(H46,H47+H48+H49+H50) | I53: =MIN(I46,I47+I48+I49+I50) | J53: =MIN(J46,J47+J48+J49+J50) | ... Q53: =MIN(Q46,Q47+Q48+Q49+Q50) | R53: =SUM(C53:Q53)
A54: Pouch shortfall (check: should be 0) | B54: Must stay 0 | C54: =C46-C53 | D54: =D46-D53 | E54: =E46-E53 | F54: =F46-F53 | G54: =G46-G53 | H54: =H46-H53 | I54: =I46-I53 | J54: =J46-J53 | ... Q54: =Q46-Q53 | R54: =SUM(C54:Q54)
A55: Closing stock | C55: =C47+C48+C49+C50-C53 | D55: =D47+D48+D49+D50-D53 | E55: =E47+E48+E49+E50-E53 | F55: =F47+F48+F49+F50-F53 | G55: =G47+G48+G49+G50-G53 | H55: =H47+H48+H49+H50-H53 | I55: =I47+I48+I49+I50-I53 | J55: =J47+J48+J49+J50-J53 | ... Q55: =Q47+Q48+Q49+Q50-Q53
